Workbook

Sheet Total
A1: COST AND PRICE FOR RESIDENTIAL SOLAR ROOFTOP IN VIET NAM - DECEMBER 2024
A2: Update 12th December, 2024
B16: OG1P_5.58 kW | C16: OG1P_8.68 kW | D16: OG1P_11.16kW | E16: OG3P_8.68kW | F16: OG3P_11.16kW | G16: OG3P_14.88kW | H16: OG3P_16.74kW
A17: UNIT COST (VND/kWp), EXCLUDING VAT | B17: 6529769.6 | C17: 6236254.3 | D17: 5830685.2 | E17: 6811579 | F17: 6195722.7 | G17: 6070886.9 | H17: 5703011.7
A18: UNIT PRICE (VND/KW), EXCLUDING VAT | B18: 7874226.1 | C18: 7605152.9 | D18: 7062235.3 | E18: 8123586.1 | F18: 7371782.3 | G18: 7064027.4 | H18: 6737699.6
A22: ON - GRID SOLAR ROOFTOP SYSTEM
A23: CATEGOGY | B23: OG1P_5.58 kW | C23: OG1P_8.68 kW | D23: OG1P_11.16kW | E23: OG3P_8.68kW | F23: OG3P_11.16kW | G23: OG3P_14.88kW | H23: OG3P_16.74kW
A24: PV | B24: =B53/$B$60 -> 0.34693216 | C24: =C53/$C$60 -> 0.36326086 | D24: =D53/$D$60 -> 0.38852845 | E24: =E53/$E$60 -> 0.33257885 | F24: =F53/$F$60 -> 0.36563726 | G24: =G53/$G$60 -> 0.37315588 | H24: =H53/$H$60 -> 0.39722645
A25: INVERTER DC-AC | B25: =B54/$B$60 -> 0.23355948 | C25: =C54/$C$60 -> 0.25530805 | D25: =D54/$D$60 -> 0.2123852 | E25: =E54/$E$60 -> 0.27250968 | F25: =F54/$F$60 -> 0.23302005 | G25: =G54/$G$60 -> 0.23867879 | H25: =H54/$H$60 -> 0.22584432
A26: ALUMILUM BRACKET SYSTEM | B26: =B55/$B$60 -> 0.070117246 | C26: =C55/$C$60 -> 0.061377384 | D26: =D55/$D$60 -> 0.077024213 | E26: =E55/$E$60 -> 0.056193282 | F26: =F55/$F$60 -> 0.072486127 | G26: =G55/$G$60 -> 0.070794425 | H26: =H55/$H$60 -> 0.076624294
A27: ELECTRICAL WIRE (AC+DC) | B27: =B56/$B$60 -> 0.068064338 | C27: =C56/$C$60 -> 0.06687519 | D27: =D56/$D$60 -> 0.063008634 | E27: =E56/$E$60 -> 0.082445433 | F27: =F56/$F$60 -> 0.077440196 | G27: =G56/$G$60 -> 0.059274451 | H27: =H56/$H$60 -> 0.056087088
A28: SOLAR CABINET | B28: =B57/$B$60 -> 0.042964366 | C28: =C57/$C$60 -> 0.036443788 | D28: =D57/$D$60 -> 0.030316793 | E28: =E57/$E$60 -> 0.042283652 | F28: =F57/$F$60 -> 0.036156288 | G28: =G57/$G$60 -> 0.037738403 | H28: =H57/$H$60 -> 0.035709097
A29: EARTH GROUND | B29: =B58/$B$60 -> 0.025249674 | C29: =C58/$C$60 -> 0.016995905 | D29: =D58/$D$60 -> 0.028277046 | E29: =E58/$E$60 -> 0.031120768 | F29: =F58/$F$60 -> 0.026611028 | G29: =G58/$G$60 -> 0.020368674 | H29: =H58/$H$60 -> 0.01927339
A30: LABOR COST | B30: =B59/$B$60 -> 0.21311273 | C30: =C59/$C$60 -> 0.19973883 | D30: =D59/$D$60 -> 0.20045966 | E30: =E59/$E$60 -> 0.18286834 | F30: =F59/$F$60 -> 0.18864905 | G30: =G59/$G$60 -> 0.19998938 | H30: =H59/$H$60 -> 0.18923536
A31: UNIT COST (VND/kWp), EXCLUDING VAT | B31: =B60/5.58 -> 6529769.6 | C31: =C60/8.68 -> 6236254.3 | D31: =D60/11.16 -> 5830685.2 | E31: =E60/8.68 -> 6811579 | F31: =F60/11.16 -> 6195722.7 | G31: =G60/14.88 -> 6070886.9 | H31: =H60/16.74 -> 5703011.7
A32: UNIT PRICE (VND/KW), EXCLUDING VAT | B32: =B62 -> 7874226.1 | C32: =C62 -> 7605152.9 | D32: =D62 -> 7062235.3 | E32: =E62 -> 8123586.1 | F32: =F62 -> 7371782.3 | G32: =G62 -> 7064027.4 | H32: =H62 -> 6737699.6
A34: HYBRID SOLAR ROOFTOP SYSTEM
A35: CATEGOGY | B35: HY1P_5.58kWBAT5.12LV | C35: HY1P_8.68kWBAT5.12LV | D35: HY1P_11.16kWBAT5.12LV | E35: HY1P_14.88kWBAT14.3LV | F35: HY3P_11.16kWBAT5.12LV | G35: HY3P_16.74kWBAT14.3LV | H35: HY3P_11.16kWBAT10HV | I35: HY3P_16.74kWBAT15HV
A36: PV | B36: =B66/$B$74 -> 0.18984876 | C36: =C66/$C$74 -> 0.25012752 | D36: =D66/$D$74 -> 0.25219567 | E36: =E66/$E$74 -> 0.23911908 | F36: =F66/$F$74 -> 0.21910821 | G36: =G66/$G$74 -> 0.23108978 | H36: =H66/$H$74 -> 0.17759449 | I36: =I66/$I$74 -> 0.19695711
A37: INVERTER DC-AC | B37: =B67/$B$74 -> 0.27624775 | C37: =C67/$C$74 -> 0.23397363 | D37: =D67/$D$74 -> 0.28228613 | E37: =E67/$E$74 -> 0.200737 | F37: =F67/$F$74 -> 0.35769693 | G37: =G67/$G$74 -> 0.25150465 | H37: =H67/$H$74 -> 0.21865727 | I37: =I67/$I$74 -> 0.21435665
A38: LITHIUM BATTERY | B38: =B68/$B$74 -> 0.24439454 | C38: =C68/$C$74 -> 0.20699491 | D38: =D68/$D$74 -> 0.16232722 | E38: =E68/$E$74 -> 0.30805726 | F38: =F68/$F$74 -> 0.14103029 | G38: =G68/$G$74 -> 0.26463386 | H38: =H68/$H$74 -> 0.37504448 | I38: =I68/$I$74 -> 0.37324969
A39: ALUMILUM BRACKET SYSTEM | B39: =B69/$B$74 -> 0.038369669 | C39: =C69/$C$74 -> 0.042262116 | D39: =D69/$D$74 -> 0.049996784 | E39: =E69/$E$74 -> 0.04536522 | F39: =F69/$F$74 -> 0.043437328 | G39: =G69/$G$74 -> 0.044576818 | H39: =H69/$H$74 -> 0.035207397 | I39: =I69/$I$74 -> 0.037992685
A40: ELECTRICAL WIRE (AC+DC) | B40: =B70/$B$74 -> 0.033641796 | C40: =C70/$C$74 -> 0.03663463 | D40: =D70/$D$74 -> 0.038904122 | E40: =E70/$E$74 -> 0.027948925 | F40: =F70/$F$74 -> 0.044672722 | G40: =G70/$G$74 -> 0.031654132 | H40: =H70/$H$74 -> 0.036208725 | I40: =I70/$I$74 -> 0.02697872
A41: SOLAR CABINET | B41: =B71/$B$74 -> 0.082329557 | C41: =C71/$C$74 -> 0.069730688 | D41: =D71/$D$74 -> 0.054683416 | E41: =E71/$E$74 -> 0.038886022 | F41: =F71/$F$74 -> 0.055387872 | G41: =G71/$G$74 -> 0.038944443 | H41: =H71/$H$74 -> 0.04489371 | I41: =I71/$I$74 -> 0.03319223
A42: EARTH GROUND | B42: =B72/$B$74 -> 0.013817166 | C42: =C72/$C$74 -> 0.011702729 | D42: =D72/$D$74 -> 0.018354765 | E42: =E72/$E$74 -> 0.01305229 | F42: =F72/$F$74 -> 0.015946665 | G42: =G72/$G$74 -> 0.011212454 | H42: =H72/$H$74 -> 0.012925301 | I42: =I72/$I$74 -> 0.0095563404
A43: LABOR COST | B43: =B73/$B$74 -> 0.12135076 | C43: =C73/$C$74 -> 0.14857378 | D43: =D73/$D$74 -> 0.14125189 | E43: =E73/$E$74 -> 0.12683421 | F43: =F73/$F$74 -> 0.12271999 | G43: =G73/$G$74 -> 0.12638386 | H43: =H73/$H$74 -> 0.099468625 | I43: =I73/$I$74 -> 0.10771658
A44: UNIT COST (VND/kWp), EXCLUDING VAT | B44: =B74/3.3 -> 20176922 | C44: =C74/5.5 -> 14293480 | D44: =D74/6.6 -> 15188856 | E44: =E74/8.8 -> 16019481 | F44: =F74/11 -> 10489512 | G44: =G74/13.2 -> 12432063 | H44: =H74/16.5 -> 8627663.5 | I44: =I74/16.5 -> 11669232
A45: UNIT PRICE (VND/KW), EXCLUDING VAT | B45: =B44/0.92 -> 21931437 | C45: =C44/0.92 -> 15536392 | D45: =D44/0.92 -> 16509626 | E45: =E44/0.92 -> 17412479 | F45: =F44/0.92 -> 11401643 | G45: =G44/0.92 -> 13513112 | H45: =H44/0.92 -> 9377895.1 | I45: =I44/0.92 -> 12683948
A48: COST BREAKDOWN (VND, EXCLUDING VAT))
A51: ON - GRID SOLAR ROOFTOP SYSTEM
A52: CATEGOGY | B52: OG1P_5.58 kW | C52: OG1P_8.68 kW | D52: OG1P_11.16kW | E52: OG3P_8.68kW | F52: OG3P_11.16kW | G52: OG3P_14.88kW | H52: OG3P_16.74kW
A53: PV | B53: =OG1P_5.58kW!L2 -> 12640860 | C53: =OG1P_8.68kW!L2 -> 19663560 | D53: =OG1P_11.16kW!L2 -> 25281720 | E53: =OG3P_8.68kW!L2 -> 19663560 | F53: =OG3P_11.16kW!L2 -> 25281720 | G53: =OG3P_14.88kW!L2 -> 33708960 | H53: =OG3P_16.74kW!L2 -> 37922580
A54: INVERTER DC-AC | B54: =OG1P_5.58kW!L3+OG1P_5.58kW!L4 -> 8510000 | C54: =OG1P_8.68kW!L3+OG1P_8.68kW!L4 -> 13820000 | D54: =OG1P_11.16kW!L3+OG1P_11.16kW!L4 -> 13820000 | E54: =OG3P_8.68kW!L3+OG3P_8.68kW!L4 -> 16112000 | F54: =SUM(OG3P_11.16kW!L3:L4) -> 16112000 | G54: =SUM(OG3P_14.88kW!L3:L4) -> 21561000 | H54: =SUM(OG3P_14.88kW!K3:K4) -> 21561000
A55: ALUMILUM BRACKET SYSTEM | B55: =SUM(OG1P_5.58kW!L5:L11) -> 2554800 | C55: =SUM(OG1P_8.68kW!L5:L11) -> 3322400 | D55: =SUM(OG1P_11.16kW!L5:L11) -> 5012000 | E55: =SUM(OG3P_8.68kW!L5:L11) -> 3322400 | F55: =SUM(OG3P_11.16kW!L5:L11) -> 5012000 | G55: =SUM(OG3P_14.88kW!L5:L11) -> 6395200 | H55: =SUM(OG3P_16.74kW!L5:L11) -> 7315200
A56: ELECTRICAL WIRE (AC+DC) | B56: =SUM(OG1P_5.58kW!L12:L16) -> 2480000 | C56: =SUM(OG1P_8.68kW!L12:L16) -> 3620000 | D56: =SUM(OG1P_11.16kW!L12:L16) -> 4100000 | E56: =SUM(OG3P_8.68kW!L12:L16) -> 4874545.5 | F56: =SUM(OG3P_11.16kW!L12:L16) -> 5354545.5 | G56: =SUM(OG3P_14.88kW!L12:L16) -> 5354545.5 | H56: =SUM(OG3P_16.74kW!L12:L16) -> 5354545.5
A57: OG-SOLAR CABINET | B57: =OG1P_5.58kW!L17 -> 1565454.5 | C57: =OG1P_8.68kW!L17 -> 1972727.3 | D57: =OG1P_11.16kW!K17 -> 1972727.3 | E57: =OG3P_8.68kW!L17 -> 2500000 | F57: =OG3P_11.16kW!L17 -> 2500000 | G57: =OG3P_14.88kW!L17 -> 3409090.9 | H57: =OG3P_16.74kW!L17 -> 3409090.9
A58: EARTH GROUND | B58: =SUM(OG1P_5.58kW!L18:L20) -> 920000 | C58: =SUM(OG1P_8.68kW!L18:L20) -> 920000 | D58: =SUM(OG1P_11.16kW!L18:L20) -> 1840000 | E58: =SUM(OG3P_8.68kW!L18:L20) -> 1840000 | F58: =SUM(OG3P_11.16kW!L18:L20) -> 1840000 | G58: =SUM(OG3P_14.88kW!L18:L20) -> 1840000 | H58: =SUM(OG3P_16.74kW!L18:L20) -> 1840000
A59: LABOR COST | B59: =SUM(OG1P_5.58kW!L21:L22) -> 7765000 | C59: =OG1P_8.68kW!L21+OG1P_8.68kW!L22 -> 10812000 | D59: =OG1P_11.16kW!L21+OG1P_11.16kW!L22 -> 13044000 | E59: =SUM(OG3P_8.68kW!L21:L22) -> 10812000 | F59: =SUM(OG3P_11.16kW!L21:L22) -> 13044000 | G59: =SUM(OG3P_16.74kW!L21:L22) -> 18066000 | H59: =SUM(OG3P_16.74kW!L21:L22) -> 18066000
A60: TOTAL COST (VNĐ) | B60: =SUM(B53:B59) -> 36436115 | C60: =SUM(C53:C59) -> 54130687 | D60: =SUM(D53:D59) -> 65070447 | E60: =SUM(E53:E59) -> 59124505 | F60: =SUM(F53:F59) -> 69144265 | G60: =SUM(G53:G59) -> 90334796 | H60: =SUM(H53:H59) -> 95468416
A61: TOTAL PRICE (VNĐ) | B61: =OG1P_5.58kW!H23/1.1 -> 43938182 | C61: =OG1P_8.68kW!H23/1.1 -> 66012727 | D61: =OG1P_11.16kW!H23/1.1 -> 78814545 | E61: =OG3P_8.68kW!H23/1.1 -> 70512727 | F61: =OG3P_11.16kW!H23/1.1 -> 82269091 | G61: =OG3P_14.88kW!H23/1.1 -> 1.0511273e+08 | H61: =OG3P_16.74kW!H23/1.1 -> 1.1278909e+08
A62: UNIT PRICE (VND/KW), EXCLUDING VAT | B62: =B61/5.58 -> 7874226.1 | C62: =C61/8.68 -> 7605152.9 | D62: =D61/11.16 -> 7062235.3 | E62: =E61/8.68 -> 8123586.1 | F62: =F61/11.16 -> 7371782.3 | G62: =G61/14.88 -> 7064027.4 | H62: =H61/16.74 -> 6737699.6
A64: HYBRID SOLAR ROOFTOP SYSTEM
A65: CATEGOGY | B65: HY1P_5.58kWBAT5.12LV | C65: HY1P_8.68kWBAT5.12LV | D65: HY1P_11.16kWBAT5.12LV | E65: HY1P_14.88kWBAT14.3LV | F65: HY3P_11.16kWBAT5.12LV | G65: HY3P_16.74kWBAT14.3LV | H65: HY3P_11.16kWBAT10HV | I65: HY3P_16.74kWBAT15HV
A66: PV | B66: =HY1P_5.58kWBAT5.12LV!L2 -> 12640860 | C66: =HY1P_8.68kWBAT5.12LV!L2 -> 19663560 | D66: =HY1P_11.16kWBAT5.12LV!L2 -> 25281720 | E66: =HY1P_14.88kWBAT14.3LV!L2 -> 33708960 | F66: =HY3P_11.16kWBAT5.12LV!L2 -> 25281720 | G66: =HY3P_16.74kWBAT14.3LV!L2 -> 37922580 | H66: =HY3P_11.16kWBAT10HV!L2 -> 25281720 | I66: =HY3P_16.74kWBAT15HV!L2 -> 37922580
A67: INVERTER DC-AC | B67: =SUM(HY1P_5.58kWBAT5.12LV!L3) -> 18393636 | C67: =HY1P_8.68kWBAT5.12LV!L3 -> 18393636 | D67: =HY1P_11.16kWBAT5.12LV!L3 -> 28298182 | E67: =HY1P_14.88kWBAT14.3LV!L3 -> 28298182 | F67: =HY3P_11.16kWBAT5.12LV!L3 -> 41272727 | G67: =HY3P_16.74kWBAT14.3LV!L3 -> 41272727 | H67: =HY3P_11.16kWBAT10HV!L3 -> 31127273 | I67: =HY3P_16.74kWBAT15HV!L3 -> 41272727
A68: LITHIUM BATTERY | B68: =SUM(HY1P_5.58kWBAT5.12LV!L4:L6) -> 16272727 | C68: =SUM(HY1P_8.68kWBAT5.12LV!L4:L6) -> 16272727 | D68: =SUM(HY1P_11.16kWBAT5.12LV!L4:L6) -> 16272727 | E68: =SUM(HY1P_14.88kWBAT14.3LV!L4:L6) -> 43427273 | F68: =SUM(HY3P_11.16kWBAT5.12LV!L4:L6) -> 16272727 | G68: =SUM(HY3P_16.74kWBAT14.3LV!L4:L6) -> 43427273 | H68: =SUM(HY3P_11.16kWBAT10HV!L4:L8) -> 53390000 | I68: =SUM(HY3P_16.74kWBAT15HV!L4:L8) -> 71866364
A69: ALUMILUM BRACKET SYSTEM | B69: =SUM(HY1P_5.58kWBAT5.12LV!L7:L13) -> 2554800 | C69: =SUM(HY1P_8.68kWBAT5.12LV!L7:L13) -> 3322400 | D69: =SUM(HY1P_11.16kWBAT5.12LV!L7:L13) -> 5012000 | E69: =SUM(HY1P_14.88kWBAT14.3LV!L7:L13) -> 6395200 | F69: =SUM(HY3P_11.16kWBAT5.12LV!L7:L13) -> 5012000 | G69: =SUM(HY3P_16.74kWBAT14.3LV!L7:L13) -> 7315200 | H69: =SUM(HY3P_11.16kWBAT10HV!L9:L15) -> 5012000 | I69: =SUM(HY3P_16.74kWBAT15HV!L9:L15) -> 7315200
A70: ELECTRICAL WIRE (AC+DC) | B70: =SUM(HY1P_5.58kWBAT5.12LV!L14:L18) -> 2240000 | C70: =SUM(HY1P_8.68kWBAT5.12LV!L14:L18) -> 2880000 | D70: =SUM(HY1P_11.16kWBAT5.12LV!L14:L18) -> 3900000 | E70: =SUM(HY1P_14.88kWBAT14.3LV!L14:L18) -> 3940000 | F70: =SUM(HY3P_11.16kWBAT5.12LV!L14:L18) -> 5154545.5 | G70: =SUM(HY3P_16.74kWBAT14.3LV!L14:L18) -> 5194545.5 | H70: =SUM(HY3P_11.16kWBAT10HV!L16:L20) -> 5154545.5 | I70: =SUM(HY3P_16.74kWBAT15HV!L16:L20) -> 5194545.5
A71: HY-SOLAR CABINET | B71: =HY1P_5.58kWBAT5.12LV!L19 -> 5481818.2 | C71: =HY1P_8.68kWBAT5.12LV!L19 -> 5481818.2 | D71: =HY1P_11.16kWBAT5.12LV!L19 -> 5481818.2 | E71: =HY1P_14.88kWBAT14.3LV!L19 -> 5481818.2 | F71: =HY3P_11.16kWBAT5.12LV!L19 -> 6390909.1 | G71: =HY3P_16.74kWBAT14.3LV!L19 -> 6390909.1 | H71: =HY3P_11.16kWBAT10HV!L21 -> 6390909.1 | I71: =HY3P_16.74kWBAT15HV!L21 -> 6390909.1
A72: EARTH GROUND | B72: =SUM(HY1P_5.58kWBAT5.12LV!L20:L22) -> 920000 | C72: =SUM(HY1P_8.68kWBAT5.12LV!L20:L22) -> 920000 | D72: =SUM(HY1P_11.16kWBAT5.12LV!L20:L22) -> 1840000 | E72: =SUM(HY1P_14.88kWBAT14.3LV!L20:L22) -> 1840000 | F72: =SUM(HY3P_11.16kWBAT5.12LV!L20:L22) -> 1840000 | G72: =SUM(HY3P_16.74kWBAT14.3LV!L20:L22) -> 1840000 | H72: =SUM(HY3P_11.16kWBAT10HV!L22:L24) -> 1840000 | I72: =SUM(HY3P_16.74kWBAT15HV!L22:L24) -> 1840000
A73: LABOR COST | B73: =SUM(HY1P_5.58kWBAT5.12LV!L23:L24) -> 8080000 | C73: =SUM(HY1P_8.68kWBAT5.12LV!L23:L24) -> 11680000 | D73: =SUM(HY1P_11.16kWBAT5.12LV!L23:L24) -> 14160000 | E73: =SUM(HY1P_14.88kWBAT14.3LV!L23:L24) -> 17880000 | F73: =SUM(HY3P_11.16kWBAT5.12LV!L23:L24) -> 14160000 | G73: =SUM(HY3P_16.74kWBAT14.3LV!L23:L24) -> 20740000 | H73: =SUM(HY3P_11.16kWBAT10HV!L25:L26) -> 14160000 | I73: =SUM(HY3P_16.74kWBAT15HV!L25:L26) -> 20740000
A74: TOTAL COST (VNĐ) | B74: =SUM(B66:B73) -> 66583842 | C74: =SUM(C66:C73) -> 78614142 | D74: =SUM(D66:D73) -> 1.0024645e+08 | E74: =SUM(E66:E73) -> 1.4097143e+08 | F74: =SUM(F66:F73) -> 1.1538463e+08 | G74: =SUM(G66:G73) -> 1.6410323e+08 | H74: =SUM(H66:H73) -> 1.4235645e+08 | I74: =SUM(I66:I73) -> 1.9254233e+08
A75: TOTAL PRICE (VNĐ) | B75: =HY1P_5.58kWBAT5.12LV!H25/1.1 -> 79392727 | C75: =HY1P_8.68kWBAT5.12LV!H25/1.1 -> 93649091 | D75: =HY1P_11.16kWBAT5.12LV!H25/1.1 -> 1.2068727e+08 | E75: =HY1P_14.88kWBAT14.3LV!H25/1.1 -> 1.7222182e+08 | F75: =HY3P_11.16kWBAT5.12LV!H25/1.1 -> 1.4005091e+08 | G75: =HY3P_16.74kWBAT14.3LV!H25/1.1 -> 1.9926182e+08 | H75: =HY3P_11.16kWBAT10HV!H27/1.1 -> 1.7086909e+08 | I75: =HY3P_16.74kWBAT15HV!H27/1.1 -> 2.3271636e+08
A76: UNIT PRICE (VND/KW), EXCLUDING VAT | B76: =B75/5.58 -> 14228087 | C76: =C75/8.68 -> 10789066 | D76: =D75/11.16 -> 10814272 | E76: =E75/14.88 -> 11574047 | F76: =F75/11.16 -> 12549365 | G76: =G75/16.74 -> 11903334 | H76: =H75/11.16 -> 15310850 | I76: =I75/16.74 -> 13901814
A78: Note: In case of installing IVT Hybrid, but no Battery (BAT will be invested later)
A79: TOTAL PRICE (IVT HYBRID_No BAT) (VND/COMBO, EXCLUDING VAT) | B79: =B75-SUM(HY1P_5.58kWBAT5.12LV!H4:H6)/1.1 -> 57665455 | C79: =C75-SUM(HY1P_8.68kWBAT5.12LV!H4:H6)/1.1 -> 71921818 | D79: =D75-SUM(HY1P_11.16kWBAT5.12LV!H4:H6)/1.1 -> 98960000 | E79: =E75-SUM(HY1P_14.88kWBAT14.3LV!H4:H6)/1.1 -> 1.1685818e+08 | F79: =F75-SUM(HY3P_11.16kWBAT5.12LV!H4:H6)/1.1 -> 1.1832364e+08 | G79: =G75-SUM(HY3P_16.74kWBAT14.3LV!H4:H6)/1.1 -> 1.4389818e+08 | H79: =H75-SUM(HY3P_11.16kWBAT10HV!H4:H8)/1.1 -> 1.0477818e+08 | I79: =I75-SUM(HY3P_16.74kWBAT15HV!H4:H8)/1.1 -> 1.4389818e+08
A80: UNIT PRICE (VND/KW), EXCLUDING VAT | B80: =B79/5.58 -> 10334311 | C80: =C79/8.68 -> 8285923.8 | D80: =D79/11.16 -> 8867383.5 | E80: =E79/14.88 -> 7853372.4 | F80: =F79/11.16 -> 10602476 | G80: =G79/16.74 -> 8596068.2 | H80: =H79/11.16 -> 9388726 | I80: =I79/16.74 -> 8596068.2

Sheet OG1P_5.58kW
A1: No. | B1: Category | C1: Specification | D1: Brand Name | E1: Unit | F1: Quatity | G1: Unit Price (Including VAT) | H1: Total Price (Including VAT) | I1: Warranty | K1: COST (excluding VAT) | L1: TOTAL COST (excluding VAT) | M1: Gross Margin for Small EPC | N1: Unit Price (excluding VAT) | O1: Total Price (excluding VAT) | P1: Unit Price - checked (Including VAT)
A2: 1 | B2: TẤM PIN PV | C2: Tấm Pin mặt trời Trina Vertex TSM-NEG19RC.20 - Công suất 620Wp All New Công nghệ mới nhất: N-Type i-TopCon Top 1 thế giới về hiệu suất và thương hiệu Tấm pin 2 mặt kính. Hiệu suất 30 năm đạt trên 87.4% | D2: TrinaSolar | E2: Tấm | F2: 9 | G2: 2100000 | H2: =F2*G2 -> 18900000 | I2: 12 Năm | J2: =9*620 -> 5580 | K2: =54*25500*(1+2%) -> 1404540 | L2: =F2*K2 -> 12640860 | M2: 0.15 | N2: =K2/(1-M2) -> 1652400 | O2: =N2*F2 -> 14871600 | P2: =N2*1.1 -> 1817640
A3: 2 | B3: INVERTER DC-AC | C3: Inverter Hòa lưới bám tải INVT_ XG5KTL-S, 5kW 1 pha. IP 66 chống bụi chống nước Tản nhiệt nhôm cao cấp, chống ồn Đầu vào Max DC: 7.5 kWp Hiệu suất chuyển đội DC-AC: 97.8% (Tiêu chuẩn EU 97.3%) | D3: INVT | E3: Bộ | F3: 1 | G3: 11900000 | H3: =F3*G3 -> 11900000 | I3: 5 Năm | K3: 7966000 | L3: =F3*K3 -> 7966000 | M3: 0.15 | N3: =K3/(1-M3) -> 9371764.7 | O3: =N3*F3 -> 9371764.7 | P3: =N3*1.1 -> 10308941
A4: 3 | B4: BỘ CHỐNG PHÁT NGƯỢC | C4: Bộ chống phát ngược lên lưới | D4: INVT | E4: Bộ | F4: 1 | G4: 1900000 | H4: =F4*G4 -> 1900000 | I4: 2 Năm | K4: 544000 | L4: =F4*K4 -> 544000 | M4: 0.15 | N4: =K4/(1-M4) -> 640000 | O4: =N4*F4 -> 640000 | P4: =N4*1.1 -> 704000
A5: 4 | B5: HỆ KHUNG GIÁ ĐỠ NHÔM CAO CẤP | C5: Kẹp biên PIN năng lượng mặt trời | D5: Việt Nam | E5: Cái | F5: 8 | G5: 11000 | H5: =F5*G5 -> 88000 | I5: 5 Năm | J5: 5/4 | K5: 8800 | L5: =F5*K5 -> 70400 | M5: 0.1 | N5: =K5/(1-M5) -> 9777.7778 | O5: =N5*F5 -> 78222.222 | P5: =N5*1.1 -> 10755.556
C6: Kẹp giữa PIN năng lượng mặt trời | D6: Việt Nam | E6: Cái | F6: 18 | G6: 11000 | H6: =F6*G6 -> 198000 | I6: 5 Năm | K6: 8800 | L6: =F6*K6 -> 158400 | M6: 0.1 | N6: =K6/(1-M6) -> 9777.7778 | O6: =N6*F6 -> 176000 | P6: =N6*1.1 -> 10755.556
C7: Thanh full rail nhôm cao cấp 4,2m | D7: Việt Nam | E7: Cái | F7: 6 | G7: 360000 | H7: =F7*G7 -> 2160000 | I7: 5 Năm | J7: =9*2*1.2/4.2 -> 5.1428571 | K7: 294000 | L7: =F7*K7 -> 1764000 | M7: 0.1 | N7: =K7/(1-M7) -> 326666.67 | O7: =N7*F7 -> 1960000 | P7: =N7*1.1 -> 359333.33
C8: Thanh nối nhôm cao cấp | D8: Việt Nam | E8: Cái | F8: 6 | G8: 20000 | H8: =F8*G8 -> 120000 | I8: 5 Năm | K8: 12800 | L8: =F8*K8 -> 76800 | M8: 0.1 | N8: =K8/(1-M8) -> 14222.222 | O8: =N8*F8 -> 85333.333 | P8: =N8*1.1 -> 15644.444
C9: Chân L- nhôm cao cấp | D9: Việt Nam | E9: Cái | F9: 28 | G9: 20000 | H9: =F9*G9 -> 560000 | I9: 5 Năm | K9: 16000 | L9: =F9*K9 -> 448000 | M9: 0.1 | N9: =K9/(1-M9) -> 17777.778 | O9: =N9*F9 -> 497777.78 | P9: =N9*1.1 -> 19555.556
C10: Kẹp tiếp địa | D10: Việt Nam | E10: Cái | F10: 2 | G10: 20000 | H10: =F10*G10 -> 40000 | I10: 5 Năm | K10: 12600 | L10: =F10*K10 -> 25200 | M10: 0.1 | N10: =K10/(1-M10) -> 14000 | O10: =N10*F10 -> 28000 | P10: =N10*1.1 -> 15400
C11: Lá tiếp địa | D11: Việt Nam | E11: Cái | F11: 8 | G11: 2000 | H11: =F11*G11 -> 16000 | I11: 5 Năm | K11: 1500 | L11: =F11*K11 -> 12000 | M11: 0.1 | N11: =K11/(1-M11) -> 1666.6667 | O11: =N11*F11 -> 13333.333 | P11: =N11*1.1 -> 1833.3333
A12: 5 | B12: HỆ DÂY ĐIỆN DC-AC | C12: Dây điện DC 4.0 màu đen Cáp điện chuyên dụng DC Solar 0.4 1500V | D12: PN Tech | E12: Mét | F12: 60 | G12: 18000 | H12: =F12*G12 -> 1080000 | I12: 5 Năm | K12: 12000 | L12: =F12*K12 -> 720000 | M12: 0.1 | N12: =K12/(1-M12) -> 13333.333 | O12: =N12*F12 -> 800000 | P12: =N12*1.1 -> 14666.667
C13: Dây điện DC 4.0 màu đỏ Cáp điện chuyên dụng DC Solar 0.4 1500V | D13: PN Tech | E13: Mét | F13: 60 | G13: 18000 | H13: =F13*G13 -> 1080000 | I13: 5 Năm | K13: 12000 | L13: =F13*K13 -> 720000 | M13: 0.1 | N13: =K13/(1-M13) -> 13333.333 | O13: =N13*F13 -> 800000 | P13: =N13*1.1 -> 14666.667
C14: Dây điện AC 1 pha 2 lõi đồng cao cấp CVV 2x6mm | D14: Cadisun/ Trần Phú | E14: Mét | F14: 20 | G14: 40000 | H14: =F14*G14 -> 800000 | I14: 5 Năm | K14: 32000 | L14: =F14*K14 -> 640000 | M14: 0.1 | N14: =K14/(1-M14) -> 35555.556 | O14: =N14*F14 -> 711111.11 | P14: =N14*1.1 -> 39111.111
C15: Dây mạng tín hiệu truyền dẫn phủ tải Inverter đến Tủ điện | D15: Việt Nam | E15: Mét | F15: 20 | G15: 15000 | H15: =F15*G15 -> 300000 | I15: 5 Năm | K15: 12000 | L15: =F15*K15 -> 240000 | M15: 0.1 | N15: =K15/(1-M15) -> 13333.333 | O15: =N15*F15 -> 266666.67 | P15: =N15*1.1 -> 14666.667
C16: Jack MC4 chuyên dụng NLMT 1500V | D16: PN Tech | E16: Bộ | F16: 8 | G16: 30000 | H16: =F16*G16 -> 240000 | I16: 5 Năm | K16: 20000 | L16: =F16*K16 -> 160000 | M16: 0.1 | N16: =K16/(1-M16) -> 22222.222 | O16: =N16*F16 -> 177777.78 | P16: =N16*1.1 -> 24444.444
A17: 6 | B17: TỦ ĐIỆN NLMT | C17: Tủ điện NLMT hòa lưới bám tải 5kW 1 Pha Vỏ tủ điện: Vỏ nhựa Suntree 12 Ways Aptomat AC Grid: 2P-32A LS Hàn Quốc At SPD chống sét lan truyền cho AC. Thương hiệu Suntree At DC và chống sét DC cho giàn pin: Vaneims | D17: SLM | E17: Bộ | F17: 1 | G17: 2400000 | H17: =F17*G17 -> 2400000 | I17: 2 Năm | K17: =1722000/1.1 -> 1565454.5 | L17: =F17*K17 -> 1565454.5 | M17: 0.1 | N17: =K17/(1-M17) -> 1739393.9 | O17: =N17*F17 -> 1739393.9 | P17: =N17*1.1 -> 1913333.3
A18: 7 | B18: HỆ TIẾP ĐỊA | C18: Cáp tiếp địa CV-1x4mm2 | D18: Cadivi | E18: Mét | F18: 30 | G18: 15000 | H18: =F18*G18 -> 450000 | I18: 2 Năm | K18: 12000 | L18: =F18*K18 -> 360000 | M18: 0.1 | N18: =K18/(1-M18) -> 13333.333 | O18: =N18*F18 -> 400000 | P18: =N18*1.1 -> 14666.667
C19: Cọc đồng Tiếp Địa 1,5m | D19: Việt Nam | E19: Cái | F19: 1 | G19: 250000 | H19: =F19*G19 -> 250000 | I19: 2 Năm | K19: 200000 | L19: =F19*K19 -> 200000 | M19: 0.1 | N19: =K19/(1-M19) -> 222222.22 | O19: =N19*F19 -> 222222.22 | P19: =N19*1.1 -> 244444.44
C20: Ống nhựa HDPE đường kính 32mm (cuộn 25m) | D20: Việt Nam | E20: Mét | F20: 30 | G20: 15000 | H20: =F20*G20 -> 450000 | I20: 2 Năm | K20: 12000 | L20: =F20*K20 -> 360000 | M20: 0.1 | N20: =K20/(1-M20) -> 13333.333 | O20: =N20*F20 -> 400000 | P20: =N20*1.1 -> 14666.667
A21: 8 | B21: NHÂN CÔNG LẮP ĐẶT | C21: Phụ kiện lắp đặt trọn gói (Bulong, ốc vít, Kẹp dây điện, băng keo điện, vật tư chống thấm thi công,…) | D21: SLM | E21: Bộ | F21: 1 | G21: 500000 | H21: =F21*G21 -> 500000 | K21: 500000 | L21: =F21*K21 -> 500000 | M21: 0.1 | N21: =K21/(1-M21) -> 555555.56 | O21: =N21*F21 -> 555555.56 | P21: =N21*1.1 -> 611111.11
C22: Nhân công lắp đặt + Vận chuyển + Kiểm định vận hành | D22: SLM | E22: Bộ | F22: 1 | G22: 4900000 | H22: =F22*G22 -> 4900000 | K22: =900000*5.85+2000000 -> 7265000 | L22: =F22*K22 -> 7265000 | M22: 0.1 | N22: =K22/(1-M22) -> 8072222.2 | O22: =N22*F22 -> 8072222.2 | P22: =N22*1.1 -> 8879444.4
A23: TỔNG CỘNG GIÁ TRỊ TRỌN GÓI VẬT TƯ THIẾT BỊ - VẬN CHUYỂN - LẮP ĐẶT - BẢO HÀNH | H23: =SUM(H2:H22) -> 48332000 | K23: Total (Excluding VAT) | L23: =SUM(L2:L22) -> 36436115 | O23: =SUM(O2:O22) -> 41866981
K24: Total (Including VAT) | L24: =L23*1.1 -> 40079726 | O24: =O23*1.1 -> 46053679

Sheet OG1P_8.68kW
A1: No. | B1: Category | C1: Specification | D1: Brand Name | E1: Unit | F1: Quatity | G1: Unit Price (Including VAT) | H1: Total Price (Including VAT) | I1: Warranty | K1: COST (excluding VAT) | L1: TOTAL COST (excluding VAT) | M1: Gross Margin for Small EPC | N1: Unit Price (excluding VAT) | O1: Total Price (excluding VAT) | P1: Unit Price - checked (Including VAT)
A2: 1 | B2: TẤM PIN PV | C2: Tấm Pin mặt trời Trina Vertex TSM-NEG19RC.20 - Công suất 620Wp All New Công nghệ mới nhất: N-Type i-TopCon Top 1 thế giới về hiệu suất và thương hiệu Tấm pin 2 mặt kính. Hiệu suất 30 năm đạt trên 87.4% | D2: TrinaSolar | E2: Tấm | F2: 14 | G2: 2100000 | H2: =F2*G2 -> 29400000 | I2: 12 Năm | J2: =14*620 -> 8680 | K2: =54*25500*(1+2%) -> 1404540 | L2: =F2*K2 -> 19663560 | M2: 0.15 | N2: =K2/(1-M2) -> 1652400 | O2: =N2*F2 -> 23133600 | P2: =N2*1.1 -> 1817640
A3: 2 | B3: INVERTER DC-AC | C3: Inverter Hòa lưới bám tải INVT_ XG10KTL1, 10kW 1 pha. IP 66 chống bụi chống nước Tản nhiệt nhôm cao cấp, chống ồn Đầu vào Max DC: 15 kWp Hiệu suất chuyển đội DC-AC: 98.1% (Tiêu chuẩn EU 97.3%) | D3: INVT | E3: Bộ | F3: 1 | G3: 18600000 | H3: =F3*G3 -> 18600000 | I3: 5 Năm | K3: 13276000 | L3: =F3*K3 -> 13276000 | M3: 0.15 | N3: =K3/(1-M3) -> 15618824 | O3: =N3*F3 -> 15618824 | P3: =N3*1.1 -> 17180706
A4: 3 | B4: BỘ CHỐNG PHÁT NGƯỢC | C4: Bộ chống phát ngược lên lưới | D4: INVT | E4: Bộ | F4: 1 | G4: 1900000 | H4: =F4*G4 -> 1900000 | I4: 2 Năm | K4: 544000 | L4: =F4*K4 -> 544000 | M4: 0.15 | N4: =K4/(1-M4) -> 640000 | O4: =N4*F4 -> 640000 | P4: =N4*1.1 -> 704000
A5: 4 | B5: HỆ KHUNG GIÁ ĐỠ NHÔM CAO CẤP | C5: Kẹp biên PIN năng lượng mặt trời | D5: Việt Nam | E5: Cái | F5: 16 | G5: 11000 | H5: =F5*G5 -> 176000 | I5: 5 Năm | J5: 5-5-4 | K5: 8800 | L5: =F5*K5 -> 140800 | M5: 0.1 | N5: =K5/(1-M5) -> 9777.7778 | O5: =N5*F5 -> 156444.44 | P5: =N5*1.1 -> 10755.556
C6: Kẹp giữa PIN năng lượng mặt trời | D6: Việt Nam | E6: Cái | F6: 16 | G6: 11000 | H6: =F6*G6 -> 176000 | I6: 5 Năm | K6: 8800 | L6: =F6*K6 -> 140800 | M6: 0.1 | N6: =K6/(1-M6) -> 9777.7778 | O6: =N6*F6 -> 156444.44 | P6: =N6*1.1 -> 10755.556
C7: Thanh full rail nhôm cao cấp 4,2m | D7: Việt Nam | E7: Cái | F7: 8 | G7: 360000 | H7: =F7*G7 -> 2880000 | I7: 5 Năm | J7: =14*2*1.2/4.2 -> 8 | K7: 294000 | L7: =F7*K7 -> 2352000 | M7: 0.1 | N7: =K7/(1-M7) -> 326666.67 | O7: =N7*F7 -> 2613333.3 | P7: =N7*1.1 -> 359333.33
C8: Thanh nối nhôm cao cấp | D8: Việt Nam | E8: Cái | F8: 8 | G8: 20000 | H8: =F8*G8 -> 160000 | I8: 5 Năm | K8: 12800 | L8: =F8*K8 -> 102400 | M8: 0.1 | N8: =K8/(1-M8) -> 14222.222 | O8: =N8*F8 -> 113777.78 | P8: =N8*1.1 -> 15644.444
C9: Chân L- nhôm cao cấp | D9: Việt Nam | E9: Cái | F9: 32 | G9: 20000 | H9: =F9*G9 -> 640000 | I9: 5 Năm | K9: 16000 | L9: =F9*K9 -> 512000 | M9: 0.1 | N9: =K9/(1-M9) -> 17777.778 | O9: =N9*F9 -> 568888.89 | P9: =N9*1.1 -> 19555.556
C10: Kẹp tiếp địa | D10: Việt Nam | E10: Cái | F10: 4 | G10: 20000 | H10: =F10*G10 -> 80000 | I10: 5 Năm | K10: 12600 | L10: =F10*K10 -> 50400 | M10: 0.1 | N10: =K10/(1-M10) -> 14000 | O10: =N10*F10 -> 56000 | P10: =N10*1.1 -> 15400
C11: Lá tiếp địa | D11: Việt Nam | E11: Cái | F11: =F6 -> 16 | G11: 2000 | H11: =F11*G11 -> 32000 | I11: 5 Năm | K11: 1500 | L11: =F11*K11 -> 24000 | M11: 0.1 | N11: =K11/(1-M11) -> 1666.6667 | O11: =N11*F11 -> 26666.667 | P11: =N11*1.1 -> 1833.3333
A12: 5 | B12: HỆ DÂY ĐIỆN DC-AC | C12: Dây điện DC 4.0 màu đen Cáp điện chuyên dụng DC Solar 0.4 1500V | D12: PN Tech | E12: Mét | F12: 80 | G12: 18000 | H12: =F12*G12 -> 1440000 | I12: 5 Năm | K12: 12000 | L12: =F12*K12 -> 960000 | M12: 0.1 | N12: =K12/(1-M12) -> 13333.333 | O12: =N12*F12 -> 1066666.7 | P12: =N12*1.1 -> 14666.667
C13: Dây điện DC 4.0 màu đỏ Cáp điện chuyên dụng DC Solar 0.4 1500V | D13: PN Tech | E13: Mét | F13: 80 | G13: 18000 | H13: =F13*G13 -> 1440000 | I13: 5 Năm | K13: 12000 | L13: =F13*K13 -> 960000 | M13: 0.1 | N13: =K13/(1-M13) -> 13333.333 | O13: =N13*F13 -> 1066666.7 | P13: =N13*1.1 -> 14666.667
C14: Dây điện AC 1 pha 2 lõi đồng cao cấp CVV 2x10mm | D14: Cadisun/ Trần Phú | E14: Mét | F14: 20 | G14: 80000 | H14: =F14*G14 -> 1600000 | I14: 5 Năm | K14: 65000 | L14: =F14*K14 -> 1300000 | M14: 0.1 | N14: =K14/(1-M14) -> 72222.222 | O14: =N14*F14 -> 1444444.4 | P14: =N14*1.1 -> 79444.444
C15: Dây mạng tín hiệu truyền dẫn phủ tải Inverter đến Tủ điện | D15: Việt Nam | E15: Mét | F15: 20 | G15: 15000 | H15: =F15*G15 -> 300000 | I15: 5 Năm | K15: 12000 | L15: =F15*K15 -> 240000 | M15: 0.1 | N15: =K15/(1-M15) -> 13333.333 | O15: =N15*F15 -> 266666.67 | P15: =N15*1.1 -> 14666.667
C16: Jack MC4 chuyên dụng NLMT 1500V | D16: PN Tech | E16: Bộ | F16: 8 | G16: 30000 | H16: =F16*G16 -> 240000 | I16: 5 Năm | K16: 20000 | L16: =F16*K16 -> 160000 | M16: 0.1 | N16: =K16/(1-M16) -> 22222.222 | O16: =N16*F16 -> 177777.78 | P16: =N16*1.1 -> 24444.444
A17: 6 | B17: TỦ ĐIỆN NLMT | C17: Tủ điện NLMT hòa lưới bám tải 10kW 1 Pha - 2 strings Vỏ tủ điện: Vỏ nhựa Suntree 12/18 Ways Aptomat AC cho lưới: 2P-63A. Thương hiệu: LS Hàn Quốc At SPD chống sét lan truyền cho AC. Thương hiệu Suntree At DC và chống sét DC - 2 strings: 2 bộ. Thương hiệu Vaneims | D17: SLM | E17: Bộ | F17: 1 | G17: 3500000 | H17: =F17*G17 -> 3500000 | I17: 2 Năm | K17: =2060000/1.1+100000 -> 1972727.3 | L17: =F17*K17 -> 1972727.3 | M17: 0.1 | N17: =K17/(1-M17) -> 2191919.2 | O17: =N17*F17 -> 2191919.2 | P17: =N17*1.1 -> 2411111.1
A18: 7 | B18: HỆ TIẾP ĐỊA | C18: Cáp tiếp địa Cadivi CV-1x4mm2 | D18: Cadivi | E18: Mét | F18: 30 | G18: 15000 | H18: =F18*G18 -> 450000 | I18: 2 Năm | K18: 12000 | L18: =F18*K18 -> 360000 | M18: 0.1 | N18: =K18/(1-M18) -> 13333.333 | O18: =N18*F18 -> 400000 | P18: =N18*1.1 -> 14666.667
C19: Cọc đồng Tiếp Địa 1,5m | D19: Việt Nam | E19: Cái | F19: 1 | G19: 250000 | H19: =F19*G19 -> 250000 | I19: 2 Năm | K19: 200000 | L19: =F19*K19 -> 200000 | M19: 0.1 | N19: =K19/(1-M19) -> 222222.22 | O19: =N19*F19 -> 222222.22 | P19: =N19*1.1 -> 244444.44
C20: Ống nhựa HDPE đường kính 32mm (cuộn 25m) | D20: Việt Nam | E20: Mét | F20: 30 | G20: 15000 | H20: =F20*G20 -> 450000 | I20: 2 Năm | K20: 12000 | L20: =F20*K20 -> 360000 | M20: 0.1 | N20: =K20/(1-M20) -> 13333.333 | O20: =N20*F20 -> 400000 | P20: =N20*1.1 -> 14666.667
A21: 8 | B21: NHÂN CÔNG LẮP ĐẶT | C21: Phụ kiện lắp đặt trọn gói (Bulong, ốc vít, Kẹp dây điện, băng keo điện, vật tư chống thấm thi công,…) | D21: SLM | E21: Bộ | F21: 1 | G21: 1000000 | H21: =F21*G21 -> 1000000 | K21: 1000000 | L21: =F21*K21 -> 1000000 | M21: 0.1 | N21: =K21/(1-M21) -> 1111111.1 | O21: =N21*F21 -> 1111111.1 | P21: =N21*1.1 -> 1222222.2
C22: Nhân công lắp đặt + Vận chuyển + Kiểm định vận hành | D22: SLM | E22: Bộ | F22: 1 | G22: 7900000 | H22: =F22*G22 -> 7900000 | K22: =900000*8.68+2000000 -> 9812000 | L22: =F22*K22 -> 9812000 | M22: 0.1 | N22: =K22/(1-M22) -> 10902222 | O22: =N22*F22 -> 10902222 | P22: =N22*1.1 -> 11992444
A23: TỔNG CỘNG GIÁ TRỊ TRỌN GÓI VẬT TƯ THIẾT BỊ - VẬN CHUYỂN - LẮP ĐẶT - BẢO HÀNH | H23: =SUM(H2:H22) -> 72614000 | K23: Total (Excluding VAT) | L23: =SUM(L2:L22) -> 54130687 | O23: =SUM(O2:O22) -> 62333676
K24: Total (Including VAT) | L24: =L23*1.1 -> 59543756 | O24: =O23*1.1 -> 68567044

Sheet OG1P_11.16kW
A1: No. | B1: Category | C1: Specification | D1: Brand Name | E1: Unit | F1: Quatity | G1: Unit Price (Including VAT) | H1: Total Price (Including VAT) | I1: Warranty | K1: COST (excluding VAT) | L1: TOTAL COST (excluding VAT) | M1: Gross Margin for Small EPC | N1: Unit Price (excluding VAT) | O1: Total Price (excluding VAT) | P1: Unit Price - checked (Including VAT)
A2: 1 | B2: TẤM PIN PV | C2: Tấm Pin mặt trời Trina Vertex TSM-NEG19RC.20 - Công suất 620Wp All New Công nghệ mới nhất: N-Type i-TopCon Top 1 thế giới về hiệu suất và thương hiệu Tấm pin 2 mặt kính. Hiệu suất 30 năm đạt trên 87.4% | D2: TrinaSolar | E2: Tấm | F2: 18 | G2: 2100000 | H2: =F2*G2 -> 37800000 | I2: 12 Năm | J2: =18*620 -> 11160 | K2: =54*25500*(1+2%) -> 1404540 | L2: =F2*K2 -> 25281720 | M2: 0.15 | N2: =K2/(1-M2) -> 1652400 | O2: =N2*F2 -> 29743200 | P2: =N2*1.1 -> 1817640
A3: 2 | B3: INVERTER DC-AC | C3: Inverter Hòa lưới bám tải INVT_ XG10KTL1, 10kW 1 pha. IP 66 chống bụi chống nước Tản nhiệt nhôm cao cấp, chống ồn Đầu vào Max DC: 15 kWp Hiệu suất chuyển đội DC-AC: 98.1% (Tiêu chuẩn EU 97.3%) | D3: INVT | E3: Bộ | F3: 1 | G3: 18600000 | H3: =F3*G3 -> 18600000 | I3: 5 Năm | K3: 13276000 | L3: =F3*K3 -> 13276000 | M3: 0.15 | N3: =K3/(1-M3) -> 15618824 | O3: =N3*F3 -> 15618824 | P3: =N3*1.1 -> 17180706
A4: 3 | B4: BỘ CHỐNG PHÁT NGƯỢC | C4: Bộ chống phát ngược lên lưới | D4: INVT | E4: Bộ | F4: 1 | G4: 1900000 | H4: =F4*G4 -> 1900000 | I4: 2 Năm | K4: 544000 | L4: =F4*K4 -> 544000 | M4: 0.15 | N4: =K4/(1-M4) -> 640000 | O4: =N4*F4 -> 640000 | P4: =N4*1.1 -> 704000
A5: 4 | B5: HỆ KHUNG GIÁ ĐỠ NHÔM CAO CẤP | C5: Kẹp biên PIN năng lượng mặt trời | D5: Việt Nam | E5: Cái | F5: 20 | G5: 11000 | H5: =F5*G5 -> 220000 | I5: 5 Năm | J5: 5-5-4-4 | K5: 8800 | L5: =F5*K5 -> 176000 | M5: 0.1 | N5: =K5/(1-M5) -> 9777.7778 | O5: =N5*F5 -> 195555.56 | P5: =N5*1.1 -> 10755.556
C6: Kẹp giữa PIN năng lượng mặt trời | D6: Việt Nam | E6: Cái | F6: 32 | G6: 11000 | H6: =F6*G6 -> 352000 | I6: 5 Năm | K6: 8800 | L6: =F6*K6 -> 281600 | M6: 0.1 | N6: =K6/(1-M6) -> 9777.7778 | O6: =N6*F6 -> 312888.89 | P6: =N6*1.1 -> 10755.556
C7: Thanh full rail nhôm cao cấp 4,2m | D7: Việt Nam | E7: Cái | F7: 11 | G7: 360000 | H7: =F7*G7 -> 3960000 | I7: 5 Năm | J7: =18*2*1.2/4.2 -> 10.285714 | K7: 294000 | L7: =F7*K7 -> 3234000 | M7: 0.1 | N7: =K7/(1-M7) -> 326666.67 | O7: =N7*F7 -> 3593333.3 | P7: =N7*1.1 -> 359333.33
C8: Thanh nối nhôm cao cấp | D8: Việt Nam | E8: Cái | F8: 11 | G8: 20000 | H8: =F8*G8 -> 220000 | I8: 5 Năm | K8: 12800 | L8: =F8*K8 -> 140800 | M8: 0.1 | N8: =K8/(1-M8) -> 14222.222 | O8: =N8*F8 -> 156444.44 | P8: =N8*1.1 -> 15644.444
C9: Chân L- nhôm cao cấp | D9: Việt Nam | E9: Cái | F9: 66 | G9: 20000 | H9: =F9*G9 -> 1320000 | I9: 5 Năm | K9: 16000 | L9: =F9*K9 -> 1056000 | M9: 0.1 | N9: =K9/(1-M9) -> 17777.778 | O9: =N9*F9 -> 1173333.3 | P9: =N9*1.1 -> 19555.556
C10: Kẹp tiếp địa | D10: Việt Nam | E10: Cái | F10: 6 | G10: 20000 | H10: =F10*G10 -> 120000 | I10: 5 Năm | K10: 12600 | L10: =F10*K10 -> 75600 | M10: 0.1 | N10: =K10/(1-M10) -> 14000 | O10: =N10*F10 -> 84000 | P10: =N10*1.1 -> 15400
C11: Lá tiếp địa | D11: Việt Nam | E11: Cái | F11: =F6 -> 32 | G11: 2000 | H11: =F11*G11 -> 64000 | I11: 5 Năm | K11: 1500 | L11: =F11*K11 -> 48000 | M11: 0.1 | N11: =K11/(1-M11) -> 1666.6667 | O11: =N11*F11 -> 53333.333 | P11: =N11*1.1 -> 1833.3333
A12: 5 | B12: HỆ DÂY ĐIỆN DC-AC | C12: Dây điện DC 4.0 màu đen Cáp điện chuyên dụng DC Solar 0.4 1500V | D12: PN Tech | E12: Mét | F12: 100 | G12: 18000 | H12: =F12*G12 -> 1800000 | I12: 5 Năm | K12: 12000 | L12: =F12*K12 -> 1200000 | M12: 0.1 | N12: =K12/(1-M12) -> 13333.333 | O12: =N12*F12 -> 1333333.3 | P12: =N12*1.1 -> 14666.667
C13: Dây điện DC 4.0 màu đỏ Cáp điện chuyên dụng DC Solar 0.4 1500V | D13: PN Tech | E13: Mét | F13: 100 | G13: 18000 | H13: =F13*G13 -> 1800000 | I13: 5 Năm | K13: 12000 | L13: =F13*K13 -> 1200000 | M13: 0.1 | N13: =K13/(1-M13) -> 13333.333 | O13: =N13*F13 -> 1333333.3 | P13: =N13*1.1 -> 14666.667
C14: Dây điện AC 1 pha 2 lõi đồng cao cấp CVV 2x10mm | D14: Cadisun/ Trần Phú | E14: Mét | F14: 20 | G14: 80000 | H14: =F14*G14 -> 1600000 | I14: 5 Năm | K14: 65000 | L14: =F14*K14 -> 1300000 | M14: 0.1 | N14: =K14/(1-M14) -> 72222.222 | O14: =N14*F14 -> 1444444.4 | P14: =N14*1.1 -> 79444.444
C15: Dây mạng tín hiệu truyền dẫn phủ tải Inverter đến Tủ điện | D15: Việt Nam | E15: Mét | F15: 20 | G15: 15000 | H15: =F15*G15 -> 300000 | I15: 5 Năm | K15: 12000 | L15: =F15*K15 -> 240000 | M15: 0.1 | N15: =K15/(1-M15) -> 13333.333 | O15: =N15*F15 -> 266666.67 | P15: =N15*1.1 -> 14666.667
C16: Jack MC4 chuyên dụng NLMT 1500V | D16: PN Tech | E16: Bộ | F16: 8 | G16: 30000 | H16: =F16*G16 -> 240000 | I16: 5 Năm | K16: 20000 | L16: =F16*K16 -> 160000 | M16: 0.1 | N16: =K16/(1-M16) -> 22222.222 | O16: =N16*F16 -> 177777.78 | P16: =N16*1.1 -> 24444.444
A17: 6 | B17: TỦ ĐIỆN NLMT | C17: Tủ điện NLMT hòa lưới bám tải 10kW 1 Pha - 2 strings Vỏ tủ điện: Vỏ nhựa Suntree 12/18 Ways Aptomat AC cho lưới: 2P-63A. Thương hiệu: LS Hàn Quốc At SPD chống sét lan truyền cho AC. Thương hiệu Suntree At DC và chống sét DC - 2 strings: 2 bộ. Thương hiệu Vaneims | D17: SLM | E17: Bộ | F17: 1 | G17: 3500000 | H17: =F17*G17 -> 3500000 | I17: 2 Năm | K17: =2060000/1.1+100000 -> 1972727.3 | L17: =F17*K17 -> 1972727.3 | M17: 0.1 | N17: =K17/(1-M17) -> 2191919.2 | O17: =N17*F17 -> 2191919.2 | P17: =N17*1.1 -> 2411111.1
A18: 7 | B18: HỆ TIẾP ĐỊA | C18: Cáp tiếp địa Cadivi CV-1x4mm2 | D18: Cadivi | E18: Mét | F18: 60 | G18: 15000 | H18: =F18*G18 -> 900000 | I18: 2 Năm | K18: 12000 | L18: =F18*K18 -> 720000 | M18: 0.1 | N18: =K18/(1-M18) -> 13333.333 | O18: =N18*F18 -> 800000 | P18: =N18*1.1 -> 14666.667
C19: Cọc đồng Tiếp Địa 1,5m | D19: Việt Nam | E19: Cái | F19: 2 | G19: 250000 | H19: =F19*G19 -> 500000 | I19: 2 Năm | K19: 200000 | L19: =F19*K19 -> 400000 | M19: 0.1 | N19: =K19/(1-M19) -> 222222.22 | O19: =N19*F19 -> 444444.44 | P19: =N19*1.1 -> 244444.44
C20: Ống nhựa HDPE đường kính 32mm (cuộn 25m) | D20: Việt Nam | E20: Mét | F20: 60 | G20: 15000 | H20: =F20*G20 -> 900000 | I20: 2 Năm | K20: 12000 | L20: =F20*K20 -> 720000 | M20: 0.1 | N20: =K20/(1-M20) -> 13333.333 | O20: =N20*F20 -> 800000 | P20: =N20*1.1 -> 14666.667
A21: 8 | B21: NHÂN CÔNG LẮP ĐẶT | C21: Phụ kiện lắp đặt trọn gói (Bulong, ốc vít, Kẹp dây điện, băng keo điện, vật tư chống thấm thi công,…) | D21: SLM | E21: Bộ | F21: 1 | G21: 1000000 | H21: =F21*G21 -> 1000000 | K21: 1000000 | L21: =F21*K21 -> 1000000 | M21: 0.1 | N21: =K21/(1-M21) -> 1111111.1 | O21: =N21*F21 -> 1111111.1 | P21: =N21*1.1 -> 1222222.2
C22: Nhân công lắp đặt + Vận chuyển + Kiểm định vận hành | D22: SLM | E22: Bộ | F22: 1 | G22: 9600000 | H22: =F22*G22 -> 9600000 | K22: =900000*11.16+2000000 -> 12044000 | L22: =F22*K22 -> 12044000 | M22: 0.1 | N22: =K22/(1-M22) -> 13382222 | O22: =N22*F22 -> 13382222 | P22: =N22*1.1 -> 14720444
A23: TỔNG CỘNG GIÁ TRỊ TRỌN GÓI VẬT TƯ THIẾT BỊ - VẬN CHUYỂN - LẮP ĐẶT - BẢO HÀNH | H23: =SUM(H2:H22) -> 86696000 | K23: Total (Excluding VAT) | L23: =SUM(L2:L22) -> 65070447 | O23: =SUM(O2:O22) -> 74856165
K24: Total (Including VAT) | L24: =L23*1.1 -> 71577492 | O24: =O23*1.1 -> 82341781

Sheet OG3P_8.68kW
A1: No. | B1: Category | C1: Specification | D1: Brand Name | E1: Unit | F1: Quatity | G1: Unit Price (Including VAT) | H1: Total Price (Including VAT) | I1: Warranty | K1: COST (excluding VAT) | L1: TOTAL COST (excluding VAT) | M1: Gross Margin for Small EPC | N1: Unit Price (excluding VAT) | O1: Total Price (excluding VAT) | P1: Unit Price - checked (Including VAT)
A2: 1 | B2: TẤM PIN PV | C2: Tấm Pin mặt trời Trina Vertex TSM-NEG19RC.20 - Công suất 620Wp All New Công nghệ mới nhất: N-Type i-TopCon Top 1 thế giới về hiệu suất và thương hiệu Tấm pin 2 mặt kính. Hiệu suất 30 năm đạt trên 87.4% | D2: TrinaSolar | E2: Tấm | F2: 14 | G2: 2100000 | H2: =F2*G2 -> 29400000 | I2: 12 Năm | J2: =14*620 -> 8680 | K2: =54*25500*(1+2%) -> 1404540 | L2: =F2*K2 -> 19663560 | M2: 0.15 | N2: =K2/(1-M2) -> 1652400 | O2: =N2*F2 -> 23133600 | P2: =N2*1.1 -> 1817640
A3: 2 | B3: INVERTER DC-AC | C3: Inverter Hòa lưới bám tải INVT_ XG10KTR-S, 10kW 3 pha. IP 66 chống bụi chống nước Tản nhiệt nhôm cao cấp, chống ồn Đầu vào Max DC: 16 kWp Hiệu suất chuyển đội DC-AC: 98.7% (Tiêu chuẩn EU 98.5%) | D3: INVT | E3: Bộ | F3: 1 | G3: 16300000 | H3: =F3*G3 -> 16300000 | I3: 5 Năm | K3: 11793000 | L3: =F3*K3 -> 11793000 | M3: 0.15 | N3: =K3/(1-M3) -> 13874118 | O3: =N3*F3 -> 13874118 | P3: =N3*1.1 -> 15261529
A4: 3 | B4: BỘ CHỐNG PHÁT NGƯỢC | C4: Bộ chống phát ngược lên lưới Metter 3 pha gián tiếp + CT | D4: INVT | E4: Bộ | F4: 1 | G4: 5600000 | H4: =F4*G4 -> 5600000 | I4: 2 Năm | K4: =3449000+870000 -> 4319000 | L4: =F4*K4 -> 4319000 | M4: 0.15 | N4: =K4/(1-M4) -> 5081176.5 | O4: =N4*F4 -> 5081176.5 | P4: =N4*1.1 -> 5589294.1
A5: 4 | B5: HỆ KHUNG GIÁ ĐỠ NHÔM CAO CẤP | C5: Kẹp biên PIN năng lượng mặt trời | D5: Việt Nam | E5: Cái | F5: 16 | G5: 11000 | H5: =F5*G5 -> 176000 | I5: 5 Năm | J5: 5-5-4 | K5: 8800 | L5: =F5*K5 -> 140800 | M5: 0.1 | N5: =K5/(1-M5) -> 9777.7778 | O5: =N5*F5 -> 156444.44 | P5: =N5*1.1 -> 10755.556
C6: Kẹp giữa PIN năng lượng mặt trời | D6: Việt Nam | E6: Cái | F6: 16 | G6: 11000 | H6: =F6*G6 -> 176000 | I6: 5 Năm | K6: 8800 | L6: =F6*K6 -> 140800 | M6: 0.1 | N6: =K6/(1-M6) -> 9777.7778 | O6: =N6*F6 -> 156444.44 | P6: =N6*1.1 -> 10755.556
C7: Thanh full rail nhôm cao cấp 4,2m | D7: Việt Nam | E7: Cái | F7: 8 | G7: 360000 | H7: =F7*G7 -> 2880000 | I7: 5 Năm | J7: =14*2*1.2/4.2 -> 8 | K7: 294000 | L7: =F7*K7 -> 2352000 | M7: 0.1 | N7: =K7/(1-M7) -> 326666.67 | O7: =N7*F7 -> 2613333.3 | P7: =N7*1.1 -> 359333.33
C8: Thanh nối nhôm cao cấp | D8: Việt Nam | E8: Cái | F8: 8 | G8: 20000 | H8: =F8*G8 -> 160000 | I8: 5 Năm | K8: 12800 | L8: =F8*K8 -> 102400 | M8: 0.1 | N8: =K8/(1-M8) -> 14222.222 | O8: =N8*F8 -> 113777.78 | P8: =N8*1.1 -> 15644.444
C9: Chân L- nhôm cao cấp | D9: Việt Nam | E9: Cái | F9: 32 | G9: 20000 | H9: =F9*G9 -> 640000 | I9: 5 Năm | K9: 16000 | L9: =F9*K9 -> 512000 | M9: 0.1 | N9: =K9/(1-M9) -> 17777.778 | O9: =N9*F9 -> 568888.89 | P9: =N9*1.1 -> 19555.556
C10: Kẹp tiếp địa | D10: Việt Nam | E10: Cái | F10: 4 | G10: 20000 | H10: =F10*G10 -> 80000 | I10: 5 Năm | K10: 12600 | L10: =F10*K10 -> 50400 | M10: 0.1 | N10: =K10/(1-M10) -> 14000 | O10: =N10*F10 -> 56000 | P10: =N10*1.1 -> 15400
C11: Lá tiếp địa | D11: Việt Nam | E11: Cái | F11: =F6 -> 16 | G11: 2000 | H11: =F11*G11 -> 32000 | I11: 5 Năm | K11: 1500 | L11: =F11*K11 -> 24000 | M11: 0.1 | N11: =K11/(1-M11) -> 1666.6667 | O11: =N11*F11 -> 26666.667 | P11: =N11*1.1 -> 1833.3333
A12: 5 | B12: HỆ DÂY ĐIỆN DC-AC | C12: Dây điện DC 4.0 màu đen Cáp điện chuyên dụng DC Solar 0.4 1500V | D12: PN Tech | E12: Mét | F12: 80 | G12: 18000 | H12: =F12*G12 -> 1440000 | I12: 5 Năm | K12: 12000 | L12: =F12*K12 -> 960000 | M12: 0.1 | N12: =K12/(1-M12) -> 13333.333 | O12: =N12*F12 -> 1066666.7 | P12: =N12*1.1 -> 14666.667
C13: Dây điện DC 4.0 màu đỏ Cáp điện chuyên dụng DC Solar 0.4 1500V | D13: PN Tech | E13: Mét | F13: 80 | G13: 18000 | H13: =F13*G13 -> 1440000 | I13: 5 Năm | K13: 12000 | L13: =F13*K13 -> 960000 | M13: 0.1 | N13: =K13/(1-M13) -> 13333.333 | O13: =N13*F13 -> 1066666.7 | P13: =N13*1.1 -> 14666.667
C14: Dây điện AC 3 pha 4 lõi đồng cao cấp CVV 4x10mm | D14: Cadisun/Trần Phú Tương đương | E14: Mét | F14: 20 | G14: 150000 | H14: =F14*G14 -> 3000000 | I14: 5 Năm | K14: =135000/1.1+100000/20 -> 127727.27 | L14: =F14*K14 -> 2554545.5 | M14: 0.1 | N14: =K14/(1-M14) -> 141919.19 | O14: =N14*F14 -> 2838383.8 | P14: =N14*1.1 -> 156111.11
C15: Dây mạng tín hiệu truyền dẫn phủ tải Inverter đến Tủ điện | D15: Việt Nam | E15: Mét | F15: 20 | G15: 15000 | H15: =F15*G15 -> 300000 | I15: 5 Năm | K15: 12000 | L15: =F15*K15 -> 240000 | M15: 0.1 | N15: =K15/(1-M15) -> 13333.333 | O15: =N15*F15 -> 266666.67 | P15: =N15*1.1 -> 14666.667
C16: Jack MC4 chuyên dụng NLMT 1500V | D16: PN Tech | E16: Bộ | F16: 8 | G16: 30000 | H16: =F16*G16 -> 240000 | I16: 5 Năm | K16: 20000 | L16: =F16*K16 -> 160000 | M16: 0.1 | N16: =K16/(1-M16) -> 22222.222 | O16: =N16*F16 -> 177777.78 | P16: =N16*1.1 -> 24444.444
A17: 6 | B17: TỦ ĐIỆN NLMT | C17: Tủ điện NLMT hòa lưới bám tải 10kW 3 Pha Vỏ tủ điện: Vỏ tủ sắt sơn tĩnh điện 50x70x25cm Aptomat AC cho lưới: 3P-63A LS Hàn Quốc At SPD chống sét lan truyền cho AC: 3 bộ. Thương hiệu Suntree At DC cho giàn pin: 3 bộ. Thương hiệu Vaneims | D17: SLM | E17: Bộ | F17: 1 | G17: 4500000 | H17: =F17*G17 -> 4500000 | I17: 2 Năm | K17: =2640000/1.1+100000 -> 2500000 | L17: =F17*K17 -> 2500000 | M17: 0.1 | N17: =K17/(1-M17) -> 2777777.8 | O17: =N17*F17 -> 2777777.8 | P17: =N17*1.1 -> 3055555.6
A18: 7 | B18: HỆ TIẾP ĐỊA | C18: Cáp tiếp địa Cadivi CV-1x4mm2 | D18: Cadivi | E18: Mét | F18: 60 | G18: 15000 | H18: =F18*G18 -> 900000 | I18: 2 Năm | K18: 12000 | L18: =F18*K18 -> 720000 | M18: 0.1 | N18: =K18/(1-M18) -> 13333.333 | O18: =N18*F18 -> 800000 | P18: =N18*1.1 -> 14666.667
C19: Cọc đồng Tiếp Địa 1,5m | D19: Việt Nam | E19: Cái | F19: 2 | G19: 250000 | H19: =F19*G19 -> 500000 | I19: 2 Năm | K19: 200000 | L19: =F19*K19 -> 400000 | M19: 0.1 | N19: =K19/(1-M19) -> 222222.22 | O19: =N19*F19 -> 444444.44 | P19: =N19*1.1 -> 244444.44
C20: Ống nhựa HDPE đường kính 32mm (cuộn 25m) | D20: Việt Nam | E20: Mét | F20: 60 | G20: 15000 | H20: =F20*G20 -> 900000 | I20: 2 Năm | K20: 12000 | L20: =F20*K20 -> 720000 | M20: 0.1 | N20: =K20/(1-M20) -> 13333.333 | O20: =N20*F20 -> 800000 | P20: =N20*1.1 -> 14666.667
A21: 8 | B21: NHÂN CÔNG LẮP ĐẶT | C21: Phụ kiện lắp đặt trọn gói (Bulong, ốc vít, Kẹp dây điện, băng keo điện, vật tư chống thấm thi công,…) | D21: SLM | E21: Bộ | F21: 1 | G21: 1000000 | H21: =F21*G21 -> 1000000 | K21: 1000000 | L21: =F21*K21 -> 1000000 | M21: 0.1 | N21: =K21/(1-M21) -> 1111111.1 | O21: =N21*F21 -> 1111111.1 | P21: =N21*1.1 -> 1222222.2
C22: Nhân công lắp đặt + Vận chuyển + Kiểm định vận hành | D22: SLM | E22: Bộ | F22: 1 | G22: 7900000 | H22: =F22*G22 -> 7900000 | K22: =900000*8.68+2000000 -> 9812000 | L22: =F22*K22 -> 9812000 | M22: 0.1 | N22: =K22/(1-M22) -> 10902222 | O22: =N22*F22 -> 10902222 | P22: =N22*1.1 -> 11992444
A23: TỔNG CỘNG GIÁ TRỊ TRỌN GÓI VẬT TƯ THIẾT BỊ - VẬN CHUYỂN - LẮP ĐẶT - BẢO HÀNH | H23: =SUM(H2:H22) -> 77564000 | K23: Total (Excluding VAT) | L23: =SUM(L2:L22) -> 59124505 | O23: =SUM(O2:O22) -> 68032167
K24: Total (Including VAT) | L24: =L23*1.1 -> 65036956 | O24: =O23*1.1 -> 74835384

Sheet OG3P_11.16kW
A1: No. | B1: Category | C1: Specification | D1: Brand Name | E1: Unit | F1: Quatity | G1: Unit Price (Including VAT) | H1: Total Price (Including VAT) | I1: Warranty | K1: COST (excluding VAT) | L1: TOTAL COST (excluding VAT) | M1: Gross Margin for Small EPC | N1: Unit Price (excluding VAT) | O1: Total Price (excluding VAT) | P1: Unit Price - checked (Including VAT)
A2: 1 | B2: TẤM PIN PV | C2: Tấm Pin mặt trời Trina Vertex TSM-NEG19RC.20 - Công suất 620Wp All New Công nghệ mới nhất: N-Type i-TopCon Top 1 thế giới về hiệu suất và thương hiệu Tấm pin 2 mặt kính. Hiệu suất 30 năm đạt trên 87.4% | D2: TrinaSolar | E2: Tấm | F2: 18 | G2: 2100000 | H2: =F2*G2 -> 37800000 | I2: 12 Năm | J2: =18*620 -> 11160 | K2: =54*25500*(1+2%) -> 1404540 | L2: =F2*K2 -> 25281720 | M2: 0.15 | N2: =K2/(1-M2) -> 1652400 | O2: =N2*F2 -> 29743200 | P2: =N2*1.1 -> 1817640
A3: 2 | B3: INVERTER DC-AC | C3: Inverter Hòa lưới bám tải INVT_ XG10KTR-S, 10kW 3 pha. IP 66 chống bụi chống nước Tản nhiệt nhôm cao cấp, chống ồn Đầu vào Max DC: 16 kWp Hiệu suất chuyển đội DC-AC: 98.7% (Tiêu chuẩn EU 98.5%) | D3: INVT | E3: Bộ | F3: 1 | G3: 16300000 | H3: =F3*G3 -> 16300000 | I3: 5 Năm | K3: 11793000 | L3: =F3*K3 -> 11793000 | M3: 0.15 | N3: =K3/(1-M3) -> 13874118 | O3: =N3*F3 -> 13874118 | P3: =N3*1.1 -> 15261529
A4: 3 | B4: BỘ CHỐNG PHÁT NGƯỢC | C4: Bộ chống phát ngược lên lưới Metter 3 pha gián tiếp + CT | D4: INVT | E4: Bộ | F4: 1 | G4: 5600000 | H4: =F4*G4 -> 5600000 | I4: 2 Năm | K4: =3449000+870000 -> 4319000 | L4: =F4*K4 -> 4319000 | M4: 0.15 | N4: =K4/(1-M4) -> 5081176.5 | O4: =N4*F4 -> 5081176.5 | P4: =N4*1.1 -> 5589294.1
A5: 4 | B5: HỆ KHUNG GIÁ ĐỠ NHÔM CAO CẤP | C5: Kẹp biên PIN năng lượng mặt trời | D5: Việt Nam | E5: Cái | F5: 20 | G5: 11000 | H5: =F5*G5 -> 220000 | I5: 5 Năm | J5: 5-5-4-4 | K5: 8800 | L5: =F5*K5 -> 176000 | M5: 0.1 | N5: =K5/(1-M5) -> 9777.7778 | O5: =N5*F5 -> 195555.56 | P5: =N5*1.1 -> 10755.556
C6: Kẹp giữa PIN năng lượng mặt trời | D6: Việt Nam | E6: Cái | F6: 32 | G6: 11000 | H6: =F6*G6 -> 352000 | I6: 5 Năm | K6: 8800 | L6: =F6*K6 -> 281600 | M6: 0.1 | N6: =K6/(1-M6) -> 9777.7778 | O6: =N6*F6 -> 312888.89 | P6: =N6*1.1 -> 10755.556
C7: Thanh full rail nhôm cao cấp 4,2m | D7: Việt Nam | E7: Cái | F7: 11 | G7: 360000 | H7: =F7*G7 -> 3960000 | I7: 5 Năm | J7: =18*2*1.2/4.2 -> 10.285714 | K7: 294000 | L7: =F7*K7 -> 3234000 | M7: 0.1 | N7: =K7/(1-M7) -> 326666.67 | O7: =N7*F7 -> 3593333.3 | P7: =N7*1.1 -> 359333.33
C8: Thanh nối nhôm cao cấp | D8: Việt Nam | E8: Cái | F8: 11 | G8: 20000 | H8: =F8*G8 -> 220000 | I8: 5 Năm | K8: 12800 | L8: =F8*K8 -> 140800 | M8: 0.1 | N8: =K8/(1-M8) -> 14222.222 | O8: =N8*F8 -> 156444.44 | P8: =N8*1.1 -> 15644.444
C9: Chân L- nhôm cao cấp | D9: Việt Nam | E9: Cái | F9: 66 | G9: 20000 | H9: =F9*G9 -> 1320000 | I9: 5 Năm | K9: 16000 | L9: =F9*K9 -> 1056000 | M9: 0.1 | N9: =K9/(1-M9) -> 17777.778 | O9: =N9*F9 -> 1173333.3 | P9: =N9*1.1 -> 19555.556
C10: Kẹp tiếp địa | D10: Việt Nam | E10: Cái | F10: 6 | G10: 20000 | H10: =F10*G10 -> 120000 | I10: 5 Năm | K10: 12600 | L10: =F10*K10 -> 75600 | M10: 0.1 | N10: =K10/(1-M10) -> 14000 | O10: =N10*F10 -> 84000 | P10: =N10*1.1 -> 15400
C11: Lá tiếp địa | D11: Việt Nam | E11: Cái | F11: =F6 -> 32 | G11: 2000 | H11: =F11*G11 -> 64000 | I11: 5 Năm | K11: 1500 | L11: =F11*K11 -> 48000 | M11: 0.1 | N11: =K11/(1-M11) -> 1666.6667 | O11: =N11*F11 -> 53333.333 | P11: =N11*1.1 -> 1833.3333
A12: 5 | B12: HỆ DÂY ĐIỆN DC-AC | C12: Dây điện DC 4.0 màu đen Cáp điện chuyên dụng DC Solar 0.4 1500V | D12: PN Tech | E12: Mét | F12: 100 | G12: 18000 | H12: =F12*G12 -> 1800000 | I12: 5 Năm | K12: 12000 | L12: =F12*K12 -> 1200000 | M12: 0.1 | N12: =K12/(1-M12) -> 13333.333 | O12: =N12*F12 -> 1333333.3 | P12: =N12*1.1 -> 14666.667
C13: Dây điện DC 4.0 màu đỏ Cáp điện chuyên dụng DC Solar 0.4 1500V | D13: PN Tech | E13: Mét | F13: 100 | G13: 18000 | H13: =F13*G13 -> 1800000 | I13: 5 Năm | K13: 12000 | L13: =F13*K13 -> 1200000 | M13: 0.1 | N13: =K13/(1-M13) -> 13333.333 | O13: =N13*F13 -> 1333333.3 | P13: =N13*1.1 -> 14666.667
C14: Dây điện AC 3 pha 4 lõi đồng cao cấp CVV 4x10mm | D14: Cadisun/Trần Phú Tương đương | E14: Mét | F14: 20 | G14: 150000 | H14: =F14*G14 -> 3000000 | I14: 5 Năm | K14: =135000/1.1+100000/20 -> 127727.27 | L14: =F14*K14 -> 2554545.5 | M14: 0.1 | N14: =K14/(1-M14) -> 141919.19 | O14: =N14*F14 -> 2838383.8 | P14: =N14*1.1 -> 156111.11
C15: Dây mạng tín hiệu truyền dẫn phủ tải Inverter đến Tủ điện | D15: Việt Nam | E15: Mét | F15: 20 | G15: 15000 | H15: =F15*G15 -> 300000 | I15: 5 Năm | K15: 12000 | L15: =F15*K15 -> 240000 | M15: 0.1 | N15: =K15/(1-M15) -> 13333.333 | O15: =N15*F15 -> 266666.67 | P15: =N15*1.1 -> 14666.667
C16: Jack MC4 chuyên dụng NLMT 1500V | D16: PN Tech | E16: Bộ | F16: 8 | G16: 30000 | H16: =F16*G16 -> 240000 | I16: 5 Năm | K16: 20000 | L16: =F16*K16 -> 160000 | M16: 0.1 | N16: =K16/(1-M16) -> 22222.222 | O16: =N16*F16 -> 177777.78 | P16: =N16*1.1 -> 24444.444
A17: 6 | B17: TỦ ĐIỆN NLMT | C17: Tủ điện NLMT hòa lưới bám tải 10kW 3 Pha Vỏ tủ điện: Vỏ tủ sắt sơn tĩnh điện 50x70x25cm Aptomat AC cho lưới: 3P-63A LS Hàn Quốc At SPD chống sét lan truyền cho AC: 3 bộ. Thương hiệu Suntree At DC cho giàn pin: 3 bộ. Thương hiệu Vaneims | D17: SLM | E17: Bộ | F17: 1 | G17: 4500000 | H17: =F17*G17 -> 4500000 | I17: 2 Năm | K17: =2640000/1.1+100000 -> 2500000 | L17: =F17*K17 -> 2500000 | M17: 0.1 | N17: =K17/(1-M17) -> 2777777.8 | O17: =N17*F17 -> 2777777.8 | P17: =N17*1.1 -> 3055555.6
A18: 7 | B18: HỆ TIẾP ĐỊA | C18: Cáp tiếp địa Cadivi CV-1x4mm2 | D18: Cadivi | E18: Mét | F18: 60 | G18: 15000 | H18: =F18*G18 -> 900000 | I18: 2 Năm | K18: 12000 | L18: =F18*K18 -> 720000 | M18: 0.1 | N18: =K18/(1-M18) -> 13333.333 | O18: =N18*F18 -> 800000 | P18: =N18*1.1 -> 14666.667
C19: Cọc đồng Tiếp Địa 1,5m | D19: Việt Nam | E19: Cái | F19: 2 | G19: 250000 | H19: =F19*G19 -> 500000 | I19: 2 Năm | K19: 200000 | L19: =F19*K19 -> 400000 | M19: 0.1 | N19: =K19/(1-M19) -> 222222.22 | O19: =N19*F19 -> 444444.44 | P19: =N19*1.1 -> 244444.44
C20: Ống nhựa HDPE đường kính 32mm (cuộn 25m) | D20: Việt Nam | E20: Mét | F20: 60 | G20: 15000 | H20: =F20*G20 -> 900000 | I20: 2 Năm | K20: 12000 | L20: =F20*K20 -> 720000 | M20: 0.1 | N20: =K20/(1-M20) -> 13333.333 | O20: =N20*F20 -> 800000 | P20: =N20*1.1 -> 14666.667
A21: 8 | B21: NHÂN CÔNG LẮP ĐẶT | C21: Phụ kiện lắp đặt trọn gói (Bulong, ốc vít, Kẹp dây điện, băng keo điện, vật tư chống thấm thi công,…) | D21: SLM | E21: Bộ | F21: 1 | G21: 1000000 | H21: =F21*G21 -> 1000000 | K21: 1000000 | L21: =F21*K21 -> 1000000 | M21: 0.1 | N21: =K21/(1-M21) -> 1111111.1 | O21: =N21*F21 -> 1111111.1 | P21: =N21*1.1 -> 1222222.2
C22: Nhân công lắp đặt + Vận chuyển + Kiểm định vận hành | D22: SLM | E22: Bộ | F22: 1 | G22: 9600000 | H22: =F22*G22 -> 9600000 | K22: =900000*11.16+2000000 -> 12044000 | L22: =F22*K22 -> 12044000 | M22: 0.1 | N22: =K22/(1-M22) -> 13382222 | O22: =N22*F22 -> 13382222 | P22: =N22*1.1 -> 14720444
A23: TỔNG CỘNG GIÁ TRỊ TRỌN GÓI VẬT TƯ THIẾT BỊ - VẬN CHUYỂN - LẮP ĐẶT - BẢO HÀNH | H23: =SUM(H2:H22) -> 90496000 | K23: Total (Excluding VAT) | L23: =SUM(L2:L22) -> 69144265 | O23: =SUM(O2:O22) -> 79532434
K24: Total (Including VAT) | L24: =L23*1.1 -> 76058692 | O24: =O23*1.1 -> 87485677

Sheet OG3P_14.88kW
A1: No. | B1: Category | C1: Specification | D1: Brand Name | E1: Unit | F1: Quatity | G1: Unit Price (Including VAT) | H1: Total Price (Including VAT) | I1: Warranty | K1: COST (excluding VAT) | L1: TOTAL COST (excluding VAT) | M1: Gross Margin for Small EPC | N1: Unit Price (excluding VAT) | O1: Total Price (excluding VAT) | P1: Unit Price - checked (Including VAT)
A2: 1 | B2: TẤM PIN PV | C2: Tấm Pin mặt trời Trina Vertex TSM-NEG19RC.20 - Công suất 620Wp All New Công nghệ mới nhất: N-Type i-TopCon Top 1 thế giới về hiệu suất và thương hiệu Tấm pin 2 mặt kính. Hiệu suất 30 năm đạt trên 87.4% | D2: TrinaSolar | E2: Tấm | F2: 24 | G2: 2100000 | H2: =F2*G2 -> 50400000 | I2: 12 Năm | J2: =24*620 -> 14880 | K2: =54*25500*(1+2%) -> 1404540 | L2: =F2*K2 -> 33708960 | M2: 0.15 | N2: =K2/(1-M2) -> 1652400 | O2: =N2*F2 -> 39657600 | P2: =N2*1.1 -> 1817640
A3: 2 | B3: INVERTER DC-AC | C3: Inverter Hòa lưới bám tải INVT_ XG15KTR1-S, 15kW 3 pha. IP 66 chống bụi chống nước Tản nhiệt nhôm cao cấp, chống ồn Đầu vào Max DC: 24 kWp Hiệu suất chuyển đội DC-AC: 98.7% (Tiêu chuẩn EU 98.5%) | D3: INVT | E3: Bộ | F3: 1 | G3: 22300000 | H3: =F3*G3 -> 22300000 | I3: 5 Năm | K3: 17242000 | L3: =F3*K3 -> 17242000 | M3: 0.15 | N3: =K3/(1-M3) -> 20284706 | O3: =N3*F3 -> 20284706 | P3: =N3*1.1 -> 22313176
A4: 3 | B4: BỘ CHỐNG PHÁT NGƯỢC | C4: Bộ chống phát ngược lên lưới Metter 3 pha gián tiếp + CT | D4: INVT | E4: Bộ | F4: 1 | G4: 5600000 | H4: =F4*G4 -> 5600000 | I4: 2 Năm | K4: =3449000+870000 -> 4319000 | L4: =F4*K4 -> 4319000 | M4: 0.15 | N4: =K4/(1-M4) -> 5081176.5 | O4: =N4*F4 -> 5081176.5 | P4: =N4*1.1 -> 5589294.1
A5: 4 | B5: HỆ KHUNG GIÁ ĐỠ NHÔM CAO CẤP | C5: Kẹp biên PIN năng lượng mặt trời | D5: Việt Nam | E5: Cái | F5: 24 | G5: 11000 | H5: =F5*G5 -> 264000 | I5: 5 Năm | J5: 5-5-5-5-4 | K5: 8800 | L5: =F5*K5 -> 211200 | M5: 0.1 | N5: =K5/(1-M5) -> 9777.7778 | O5: =N5*F5 -> 234666.67 | P5: =N5*1.1 -> 10755.556
C6: Kẹp giữa PIN năng lượng mặt trời | D6: Việt Nam | E6: Cái | F6: 40 | G6: 11000 | H6: =F6*G6 -> 440000 | I6: 5 Năm | K6: 8800 | L6: =F6*K6 -> 352000 | M6: 0.1 | N6: =K6/(1-M6) -> 9777.7778 | O6: =N6*F6 -> 391111.11 | P6: =N6*1.1 -> 10755.556
C7: Thanh full rail nhôm cao cấp 4,2m | D7: Việt Nam | E7: Cái | F7: 14 | G7: 360000 | H7: =F7*G7 -> 5040000 | I7: 5 Năm | J7: =24*2*1.2/4.2 -> 13.714286 | K7: 294000 | L7: =F7*K7 -> 4116000 | M7: 0.1 | N7: =K7/(1-M7) -> 326666.67 | O7: =N7*F7 -> 4573333.3 | P7: =N7*1.1 -> 359333.33
C8: Thanh nối nhôm cao cấp | D8: Việt Nam | E8: Cái | F8: 14 | G8: 20000 | H8: =F8*G8 -> 280000 | I8: 5 Năm | K8: 12800 | L8: =F8*K8 -> 179200 | M8: 0.1 | N8: =K8/(1-M8) -> 14222.222 | O8: =N8*F8 -> 199111.11 | P8: =N8*1.1 -> 15644.444
C9: Chân L- nhôm cao cấp | D9: Việt Nam | E9: Cái | F9: 86 | G9: 20000 | H9: =F9*G9 -> 1720000 | I9: 5 Năm | K9: 16000 | L9: =F9*K9 -> 1376000 | M9: 0.1 | N9: =K9/(1-M9) -> 17777.778 | O9: =N9*F9 -> 1528888.9 | P9: =N9*1.1 -> 19555.556
C10: Kẹp tiếp địa | D10: Việt Nam | E10: Cái | F10: 8 | G10: 20000 | H10: =F10*G10 -> 160000 | I10: 5 Năm | K10: 12600 | L10: =F10*K10 -> 100800 | M10: 0.1 | N10: =K10/(1-M10) -> 14000 | O10: =N10*F10 -> 112000 | P10: =N10*1.1 -> 15400
C11: Lá tiếp địa | D11: Việt Nam | E11: Cái | F11: =F6 -> 40 | G11: 2000 | H11: =F11*G11 -> 80000 | I11: 5 Năm | K11: 1500 | L11: =F11*K11 -> 60000 | M11: 0.1 | N11: =K11/(1-M11) -> 1666.6667 | O11: =N11*F11 -> 66666.667 | P11: =N11*1.1 -> 1833.3333
A12: 5 | B12: HỆ DÂY ĐIỆN DC-AC | C12: Dây điện DC 4.0 màu đen Cáp điện chuyên dụng DC Solar 0.4 1500V | D12: PN Tech | E12: Mét | F12: 100 | G12: 18000 | H12: =F12*G12 -> 1800000 | I12: 5 Năm | K12: 12000 | L12: =F12*K12 -> 1200000 | M12: 0.1 | N12: =K12/(1-M12) -> 13333.333 | O12: =N12*F12 -> 1333333.3 | P12: =N12*1.1 -> 14666.667
C13: Dây điện DC 4.0 màu đỏ Cáp điện chuyên dụng DC Solar 0.4 1500V | D13: PN Tech | E13: Mét | F13: 100 | G13: 18000 | H13: =F13*G13 -> 1800000 | I13: 5 Năm | K13: 12000 | L13: =F13*K13 -> 1200000 | M13: 0.1 | N13: =K13/(1-M13) -> 13333.333 | O13: =N13*F13 -> 1333333.3 | P13: =N13*1.1 -> 14666.667
C14: Dây điện AC 3 pha 4 lõi đồng cao cấp CVV 4x10mm | D14: Cadisun/Trần Phú Tương đương | E14: Mét | F14: 20 | G14: 150000 | H14: =F14*G14 -> 3000000 | I14: 5 Năm | K14: =135000/1.1+100000/20 -> 127727.27 | L14: =F14*K14 -> 2554545.5 | M14: 0.1 | N14: =K14/(1-M14) -> 141919.19 | O14: =N14*F14 -> 2838383.8 | P14: =N14*1.1 -> 156111.11
C15: Dây mạng tín hiệu truyền dẫn phủ tải Inverter đến Tủ điện | D15: Việt Nam | E15: Mét | F15: 20 | G15: 15000 | H15: =F15*G15 -> 300000 | I15: 5 Năm | K15: 12000 | L15: =F15*K15 -> 240000 | M15: 0.1 | N15: =K15/(1-M15) -> 13333.333 | O15: =N15*F15 -> 266666.67 | P15: =N15*1.1 -> 14666.667
C16: Jack MC4 chuyên dụng NLMT 1500V | D16: PN Tech | E16: Bộ | F16: 8 | G16: 30000 | H16: =F16*G16 -> 240000 | I16: 5 Năm | K16: 20000 | L16: =F16*K16 -> 160000 | M16: 0.1 | N16: =K16/(1-M16) -> 22222.222 | O16: =N16*F16 -> 177777.78 | P16: =N16*1.1 -> 24444.444
A17: 6 | B17: TỦ ĐIỆN NLMT | C17: Tủ điện NLMT hòa lưới bám tải 15kW 3 Pha Vỏ tủ điện: Vỏ tủ sắt sơn tĩnh điện 50x70x25cm Aptomat AC cho lưới: 3P-63A LS Hàn Quốc At SPD chống sét lan truyền cho AC: 3 bộ. Thương hiệu Suntree At DC cho giàn pin: 3 bộ. Thương hiệu Vaneims | D17: SLM | E17: Bộ | F17: 1 | G17: 5500000 | H17: =F17*G17 -> 5500000 | I17: 2 Năm | K17: =3640000/1.1+100000 -> 3409090.9 | L17: =F17*K17 -> 3409090.9 | M17: 0.1 | N17: =K17/(1-M17) -> 3787878.8 | O17: =N17*F17 -> 3787878.8 | P17: =N17*1.1 -> 4166666.7
A18: 7 | B18: HỆ TIẾP ĐỊA | C18: Cáp tiếp địa Cadivi CV-1x4mm2 | D18: Cadivi | E18: Mét | F18: 60 | G18: 15000 | H18: =F18*G18 -> 900000 | I18: 2 Năm | K18: 12000 | L18: =F18*K18 -> 720000 | M18: 0.1 | N18: =K18/(1-M18) -> 13333.333 | O18: =N18*F18 -> 800000 | P18: =N18*1.1 -> 14666.667
C19: Cọc đồng Tiếp Địa 1,5m | D19: Việt Nam | E19: Cái | F19: 2 | G19: 250000 | H19: =F19*G19 -> 500000 | I19: 2 Năm | K19: 200000 | L19: =F19*K19 -> 400000 | M19: 0.1 | N19: =K19/(1-M19) -> 222222.22 | O19: =N19*F19 -> 444444.44 | P19: =N19*1.1 -> 244444.44
C20: Ống nhựa HDPE đường kính 32mm (cuộn 25m) | D20: Việt Nam | E20: Mét | F20: 60 | G20: 15000 | H20: =F20*G20 -> 900000 | I20: 2 Năm | K20: 12000 | L20: =F20*K20 -> 720000 | M20: 0.1 | N20: =K20/(1-M20) -> 13333.333 | O20: =N20*F20 -> 800000 | P20: =N20*1.1 -> 14666.667
A21: 8 | B21: NHÂN CÔNG LẮP ĐẶT | C21: Phụ kiện lắp đặt trọn gói (Bulong, ốc vít, Kẹp dây điện, băng keo điện, vật tư chống thấm thi công,…) | D21: SLM | E21: Bộ | F21: 1 | G21: 1500000 | H21: =F21*G21 -> 1500000 | K21: 1000000 | L21: =F21*K21 -> 1000000 | M21: 0.1 | N21: =K21/(1-M21) -> 1111111.1 | O21: =N21*F21 -> 1111111.1 | P21: =N21*1.1 -> 1222222.2
C22: Nhân công lắp đặt + Vận chuyển + Kiểm định vận hành | D22: SLM | E22: Bộ | F22: 1 | G22: 12900000 | H22: =F22*G22 -> 12900000 | K22: =900000*14.88+2000000 -> 15392000 | L22: =F22*K22 -> 15392000 | M22: 0.1 | N22: =K22/(1-M22) -> 17102222 | O22: =N22*F22 -> 17102222 | P22: =N22*1.1 -> 18812444
A23: TỔNG CỘNG GIÁ TRỊ TRỌN GÓI VẬT TƯ THIẾT BỊ - VẬN CHUYỂN - LẮP ĐẶT - BẢO HÀNH | H23: =SUM(H2:H22) -> 115624000 | K23: Total (Excluding VAT) | L23: =SUM(L2:L22) -> 88660796 | O23: =SUM(O2:O22) -> 1.0212441e+08
K24: Total (Including VAT) | L24: =L23*1.1 -> 97526876 | O24: =O23*1.1 -> 1.1233685e+08

Sheet OG3P_16.74kW
A1: No. | B1: Category | C1: Specification | D1: Brand Name | E1: Unit | F1: Quatity | G1: Unit Price (Including VAT) | H1: Total Price (Including VAT) | I1: Warranty | K1: COST (excluding VAT) | L1: TOTAL COST (excluding VAT) | M1: Gross Margin for Small EPC | N1: Unit Price (excluding VAT) | O1: Total Price (excluding VAT) | P1: Unit Price - checked (Including VAT)
A2: 1 | B2: TẤM PIN PV | C2: Tấm Pin mặt trời Trina Vertex TSM-NEG19RC.20 - Công suất 620Wp All New Công nghệ mới nhất: N-Type i-TopCon Top 1 thế giới về hiệu suất và thương hiệu Tấm pin 2 mặt kính. Hiệu suất 30 năm đạt trên 87.4% | D2: TrinaSolar | E2: Tấm | F2: 27 | G2: 2100000 | H2: =F2*G2 -> 56700000 | I2: 12 Năm | J2: =27*620 -> 16740 | K2: =54*25500*(1+2%) -> 1404540 | L2: =F2*K2 -> 37922580 | M2: 0.15 | N2: =K2/(1-M2) -> 1652400 | O2: =N2*F2 -> 44614800 | P2: =N2*1.1 -> 1817640
A3: 2 | B3: INVERTER DC-AC | C3: Inverter Hòa lưới bám tải INVT_ XG15KTR1-S, 15kW 3 pha. IP 66 chống bụi chống nước Tản nhiệt nhôm cao cấp, chống ồn Đầu vào Max DC: 24 kWp Hiệu suất chuyển đội DC-AC: 98.7% (Tiêu chuẩn EU 98.5%) | D3: INVT | E3: Bộ | F3: 1 | G3: 22300000 | H3: =F3*G3 -> 22300000 | I3: 5 Năm | K3: 17242000 | L3: =F3*K3 -> 17242000 | M3: 0.15 | N3: =K3/(1-M3) -> 20284706 | O3: =N3*F3 -> 20284706 | P3: =N3*1.1 -> 22313176
A4: 3 | B4: BỘ CHỐNG PHÁT NGƯỢC | C4: Bộ chống phát ngược lên lưới Metter 3 pha gián tiếp + CT | D4: INVT | E4: Bộ | F4: 1 | G4: 5600000 | H4: =F4*G4 -> 5600000 | I4: 2 Năm | K4: =3449000+870000 -> 4319000 | L4: =F4*K4 -> 4319000 | M4: 0.15 | N4: =K4/(1-M4) -> 5081176.5 | O4: =N4*F4 -> 5081176.5 | P4: =N4*1.1 -> 5589294.1
A5: 4 | B5: HỆ KHUNG GIÁ ĐỠ NHÔM CAO CẤP | C5: Kẹp biên PIN năng lượng mặt trời | D5: Việt Nam | E5: Cái | F5: 24 | G5: 11000 | H5: =F5*G5 -> 264000 | I5: 5 Năm | J5: 6-6-5-5-5 | K5: 8800 | L5: =F5*K5 -> 211200 | M5: 0.1 | N5: =K5/(1-M5) -> 9777.7778 | O5: =N5*F5 -> 234666.67 | P5: =N5*1.1 -> 10755.556
C6: Kẹp giữa PIN năng lượng mặt trời | D6: Việt Nam | E6: Cái | F6: 48 | G6: 11000 | H6: =F6*G6 -> 528000 | I6: 5 Năm | K6: 8800 | L6: =F6*K6 -> 422400 | M6: 0.1 | N6: =K6/(1-M6) -> 9777.7778 | O6: =N6*F6 -> 469333.33 | P6: =N6*1.1 -> 10755.556
C7: Thanh full rail nhôm cao cấp 4,2m | D7: Việt Nam | E7: Cái | F7: 16 | G7: 360000 | H7: =F7*G7 -> 5760000 | I7: 5 Năm | J7: =27*2*1.2/4.2 -> 15.428571 | K7: 294000 | L7: =F7*K7 -> 4704000 | M7: 0.1 | N7: =K7/(1-M7) -> 326666.67 | O7: =N7*F7 -> 5226666.7 | P7: =N7*1.1 -> 359333.33
C8: Thanh nối nhôm cao cấp | D8: Việt Nam | E8: Cái | F8: 16 | G8: 20000 | H8: =F8*G8 -> 320000 | I8: 5 Năm | K8: 12800 | L8: =F8*K8 -> 204800 | M8: 0.1 | N8: =K8/(1-M8) -> 14222.222 | O8: =N8*F8 -> 227555.56 | P8: =N8*1.1 -> 15644.444
C9: Chân L- nhôm cao cấp | D9: Việt Nam | E9: Cái | F9: =F7*6+4 -> 100 | G9: 20000 | H9: =F9*G9 -> 2000000 | I9: 5 Năm | K9: 16000 | L9: =F9*K9 -> 1600000 | M9: 0.1 | N9: =K9/(1-M9) -> 17777.778 | O9: =N9*F9 -> 1777777.8 | P9: =N9*1.1 -> 19555.556
C10: Kẹp tiếp địa | D10: Việt Nam | E10: Cái | F10: 8 | G10: 20000 | H10: =F10*G10 -> 160000 | I10: 5 Năm | K10: 12600 | L10: =F10*K10 -> 100800 | M10: 0.1 | N10: =K10/(1-M10) -> 14000 | O10: =N10*F10 -> 112000 | P10: =N10*1.1 -> 15400
C11: Lá tiếp địa | D11: Việt Nam | E11: Cái | F11: =F6 -> 48 | G11: 2000 | H11: =F11*G11 -> 96000 | I11: 5 Năm | K11: 1500 | L11: =F11*K11 -> 72000 | M11: 0.1 | N11: =K11/(1-M11) -> 1666.6667 | O11: =N11*F11 -> 80000 | P11: =N11*1.1 -> 1833.3333
A12: 5 | B12: HỆ DÂY ĐIỆN DC-AC | C12: Dây điện DC 4.0 màu đen Cáp điện chuyên dụng DC Solar 0.4 1500V | D12: PN Tech | E12: Mét | F12: 100 | G12: 18000 | H12: =F12*G12 -> 1800000 | I12: 5 Năm | K12: 12000 | L12: =F12*K12 -> 1200000 | M12: 0.1 | N12: =K12/(1-M12) -> 13333.333 | O12: =N12*F12 -> 1333333.3 | P12: =N12*1.1 -> 14666.667
C13: Dây điện DC 4.0 màu đỏ Cáp điện chuyên dụng DC Solar 0.4 1500V | D13: PN Tech | E13: Mét | F13: 100 | G13: 18000 | H13: =F13*G13 -> 1800000 | I13: 5 Năm | K13: 12000 | L13: =F13*K13 -> 1200000 | M13: 0.1 | N13: =K13/(1-M13) -> 13333.333 | O13: =N13*F13 -> 1333333.3 | P13: =N13*1.1 -> 14666.667
C14: Dây điện AC 3 pha 4 lõi đồng cao cấp CVV 4x10mm | D14: Cadisun/Trần Phú Tương đương | E14: Mét | F14: 20 | G14: 150000 | H14: =F14*G14 -> 3000000 | I14: 5 Năm | K14: =135000/1.1+100000/20 -> 127727.27 | L14: =F14*K14 -> 2554545.5 | M14: 0.1 | N14: =K14/(1-M14) -> 141919.19 | O14: =N14*F14 -> 2838383.8 | P14: =N14*1.1 -> 156111.11
C15: Dây mạng tín hiệu truyền dẫn phủ tải Inverter đến Tủ điện | D15: Việt Nam | E15: Mét | F15: 20 | G15: 15000 | H15: =F15*G15 -> 300000 | I15: 5 Năm | K15: 12000 | L15: =F15*K15 -> 240000 | M15: 0.1 | N15: =K15/(1-M15) -> 13333.333 | O15: =N15*F15 -> 266666.67 | P15: =N15*1.1 -> 14666.667
C16: Jack MC4 chuyên dụng NLMT 1500V | D16: PN Tech | E16: Bộ | F16: 8 | G16: 30000 | H16: =F16*G16 -> 240000 | I16: 5 Năm | K16: 20000 | L16: =F16*K16 -> 160000 | M16: 0.1 | N16: =K16/(1-M16) -> 22222.222 | O16: =N16*F16 -> 177777.78 | P16: =N16*1.1 -> 24444.444
A17: 6 | B17: TỦ ĐIỆN NLMT | C17: Tủ điện NLMT hòa lưới bám tải 15kW 3 Pha Vỏ tủ điện: Vỏ tủ sắt sơn tĩnh điện 50x70x25cm Aptomat AC cho lưới: 3P-63A LS Hàn Quốc At SPD chống sét lan truyền cho AC: 3 bộ. Thương hiệu Suntree At DC cho giàn pin: 3 bộ. Thương hiệu Vaneims | D17: SLM | E17: Bộ | F17: 1 | G17: 5500000 | H17: =F17*G17 -> 5500000 | I17: 2 Năm | K17: =3640000/1.1+100000 -> 3409090.9 | L17: =F17*K17 -> 3409090.9 | M17: 0.1 | N17: =K17/(1-M17) -> 3787878.8 | O17: =N17*F17 -> 3787878.8 | P17: =N17*1.1 -> 4166666.7
A18: 7 | B18: HỆ TIẾP ĐỊA | C18: Cáp tiếp địa Cadivi CV-1x4mm2 | D18: Cadivi | E18: Mét | F18: 60 | G18: 15000 | H18: =F18*G18 -> 900000 | I18: 2 Năm | K18: 12000 | L18: =F18*K18 -> 720000 | M18: 0.1 | N18: =K18/(1-M18) -> 13333.333 | O18: =N18*F18 -> 800000 | P18: =N18*1.1 -> 14666.667
C19: Cọc đồng Tiếp Địa 1,5m | D19: Việt Nam | E19: Cái | F19: 2 | G19: 250000 | H19: =F19*G19 -> 500000 | I19: 2 Năm | K19: 200000 | L19: =F19*K19 -> 400000 | M19: 0.1 | N19: =K19/(1-M19) -> 222222.22 | O19: =N19*F19 -> 444444.44 | P19: =N19*1.1 -> 244444.44
C20: Ống nhựa HDPE đường kính 32mm (cuộn 25m) | D20: Việt Nam | E20: Mét | F20: 60 | G20: 15000 | H20: =F20*G20 -> 900000 | I20: 2 Năm | K20: 12000 | L20: =F20*K20 -> 720000 | M20: 0.1 | N20: =K20/(1-M20) -> 13333.333 | O20: =N20*F20 -> 800000 | P20: =N20*1.1 -> 14666.667
A21: 8 | B21: NHÂN CÔNG LẮP ĐẶT | C21: Phụ kiện lắp đặt trọn gói (Bulong, ốc vít, Kẹp dây điện, băng keo điện, vật tư chống thấm thi công,…) | D21: SLM | E21: Bộ | F21: 1 | G21: 1500000 | H21: =F21*G21 -> 1500000 | K21: 1000000 | L21: =F21*K21 -> 1000000 | M21: 0.1 | N21: =K21/(1-M21) -> 1111111.1 | O21: =N21*F21 -> 1111111.1 | P21: =N21*1.1 -> 1222222.2
C22: Nhân công lắp đặt + Vận chuyển + Kiểm định vận hành | D22: SLM | E22: Bộ | F22: 1 | G22: 13900000 | H22: =F22*G22 -> 13900000 | K22: =900000*16.74+2000000 -> 17066000 | L22: =F22*K22 -> 17066000 | M22: 0.1 | N22: =K22/(1-M22) -> 18962222 | O22: =N22*F22 -> 18962222 | P22: =N22*1.1 -> 20858444
A23: TỔNG CỘNG GIÁ TRỊ TRỌN GÓI VẬT TƯ THIẾT BỊ - VẬN CHUYỂN - LẮP ĐẶT - BẢO HÀNH | H23: =SUM(H2:H22) -> 124068000 | K23: Total (Excluding VAT) | L23: =SUM(L2:L22) -> 95468416 | O23: =SUM(O2:O22) -> 1.0996383e+08
K24: Total (Including VAT) | L24: =L23*1.1 -> 105015258 | O24: =O23*1.1 -> 1.2096022e+08

Sheet HY1P_5.58kWBAT5.12LV
A1: No. | B1: Category | C1: Specification | D1: Brand Name | E1: Unit | F1: Quatity | G1: Unit Price (Including VAT) | H1: Total Price (Including VAT) | I1: Warranty | K1: COST (excluding VAT) | L1: TOTAL COST (excluding VAT) | M1: Gross Margin for Small EPC | N1: Unit Price (excluding VAT) | O1: Total Price (excluding VAT) | P1: Unit Price - checked (Including VAT)
A2: 1 | B2: TẤM PIN PV | C2: Tấm Pin mặt trời Trina Vertex TSM-NEG19RC.20 - Công suất 620Wp All New Công nghệ mới nhất: N-Type i-TopCon Top 1 thế giới về hiệu suất và thương hiệu Tấm pin 2 mặt kính. Hiệu suất 30 năm đạt trên 87.4% | D2: TrinaSolar | E2: Tấm | F2: 9 | G2: 2100000 | H2: =F2*G2 -> 18900000 | I2: 12 Năm | J2: =9*620 -> 5580 | K2: =54*25500*(1+2%) -> 1404540 | L2: =F2*K2 -> 12640860 | M2: 0.15 | N2: =K2/(1-M2) -> 1652400 | O2: =N2*F2 -> 14871600 | P2: =N2*1.1 -> 1817640
A3: 2 | B3: INVERTER DC-AC | C3: Inverter Solis 5KW PRO, Hybrid 1 pha, 2 chuỗi MPPT cho hiệu suất cao 96.9% (Tiêu chuẩn EU 96.5%) Top 3 thế giới về thương hiệu Inverter Cấp độ bảo vệ: IP66 Công suất DC max: 10kWp Đã bao gồm Metter và CT chống phát ngược lưới | D3: Solis | E3: Bộ | F3: 1 | G3: 24800000 | H3: =F3*G3 -> 24800000 | I3: 5 Năm | K3: =20233000/1.1 -> 18393636 | L3: =F3*K3 -> 18393636 | M3: 0.15 | N3: =K3/(1-M3) -> 21639572 | O3: =N3*F3 -> 21639572 | P3: =N3*1.1 -> 23803529
A4: 3 | B4: PIN LƯU TRỮ | C4: Pin Lithium EASYWAY 51,2V-100Ah-5,2kWh Cell Pin từ hãng Gotion - Top 3 thế giới về thương hiệu Cell Pin Bản tiêu chuẩn - màu trắng - Rack IP20 Bảo hành 5 năm | D4: EASYWAY | E4: Bộ | F4: 1 | G4: 23000000 | H4: =F4*G4 -> 23000000 | I4: 5 Năm | K4: =17600000/1.1 -> 16000000 | L4: =F4*K4 -> 16000000 | M4: 0.15 | N4: =K4/(1-M4) -> 18823529 | O4: =N4*F4 -> 18823529 | P4: =N4*1.1 -> 20705882
C5: Dây từ 35, nối Pin Lithium lên Inverter đã bấm sẵn đầu cốt | D5: SLM | E5: Bộ | F5: 1 | G5: 800000 | H5: =F5*G5 -> 800000 | I5: 5 Năm | K5: =300000/1.1 -> 272727.27 | L5: =F5*K5 -> 272727.27 | M5: 0.1 | N5: =K5/(1-M5) -> 303030.3 | O5: =N5*F5 -> 303030.3 | P5: =N5*1.1 -> 333333.33
C6: Dây mạng tín hiệu giao tiếp Inverter - Pin | D6: Việt Nam | E6: Bộ | F6: 1 | G6: 100000 | H6: =F6*G6 -> 100000 | I6: 5 Năm | K6: 0 | L6: =F6*K6 -> 0 | M6: 0.1 | N6: =K6/(1-M6) -> 0 | O6: =N6*F6 -> 0 | P6: =N6*1.1 -> 0
A7: 4 | B7: HỆ KHUNG GIÁ ĐỠ NHÔM CAO CẤP | C7: Kẹp biên PIN năng lượng mặt trời | D7: Việt Nam | E7: Cái | F7: 8 | G7: 11000 | H7: =F7*G7 -> 88000 | I7: 5 Năm | J7: 5/4 | K7: 8800 | L7: =F7*K7 -> 70400 | M7: 0.1 | N7: =K7/(1-M7) -> 9777.7778 | O7: =N7*F7 -> 78222.222 | P7: =N7*1.1 -> 10755.556
C8: Kẹp giữa PIN năng lượng mặt trời | D8: Việt Nam | E8: Cái | F8: 18 | G8: 11000 | H8: =F8*G8 -> 198000 | I8: 5 Năm | K8: 8800 | L8: =F8*K8 -> 158400 | M8: 0.1 | N8: =K8/(1-M8) -> 9777.7778 | O8: =N8*F8 -> 176000 | P8: =N8*1.1 -> 10755.556
C9: Thanh full rail nhôm cao cấp 4,2m | D9: Việt Nam | E9: Cái | F9: 6 | G9: 360000 | H9: =F9*G9 -> 2160000 | I9: 5 Năm | J9: =9*2*1.2/4.2 -> 5.1428571 | K9: 294000 | L9: =F9*K9 -> 1764000 | M9: 0.1 | N9: =K9/(1-M9) -> 326666.67 | O9: =N9*F9 -> 1960000 | P9: =N9*1.1 -> 359333.33
C10: Thanh nối nhôm cao cấp | D10: Việt Nam | E10: Cái | F10: 6 | G10: 20000 | H10: =F10*G10 -> 120000 | I10: 5 Năm | K10: 12800 | L10: =F10*K10 -> 76800 | M10: 0.1 | N10: =K10/(1-M10) -> 14222.222 | O10: =N10*F10 -> 85333.333 | P10: =N10*1.1 -> 15644.444
C11: Chân L- nhôm cao cấp | D11: Việt Nam | E11: Cái | F11: 28 | G11: 20000 | H11: =F11*G11 -> 560000 | I11: 5 Năm | K11: 16000 | L11: =F11*K11 -> 448000 | M11: 0.1 | N11: =K11/(1-M11) -> 17777.778 | O11: =N11*F11 -> 497777.78 | P11: =N11*1.1 -> 19555.556
C12: Kẹp tiếp địa | D12: Việt Nam | E12: Cái | F12: 2 | G12: 20000 | H12: =F12*G12 -> 40000 | I12: 5 Năm | K12: 12600 | L12: =F12*K12 -> 25200 | M12: 0.1 | N12: =K12/(1-M12) -> 14000 | O12: =N12*F12 -> 28000 | P12: =N12*1.1 -> 15400
C13: Lá tiếp địa | D13: Việt Nam | E13: Cái | F13: 8 | G13: 2000 | H13: =F13*G13 -> 16000 | I13: 5 Năm | K13: 1500 | L13: =F13*K13 -> 12000 | M13: 0.1 | N13: =K13/(1-M13) -> 1666.6667 | O13: =N13*F13 -> 13333.333 | P13: =N13*1.1 -> 1833.3333
A14: 5 | B14: HỆ DÂY ĐIỆN DC-AC | C14: Dây điện DC 4.0 màu đen Cáp điện chuyên dụng DC Solar 0.4 1500V | D14: PN Tech/ Leader | E14: Mét | F14: 60 | G14: 18000 | H14: =F14*G14 -> 1080000 | I14: 5 Năm | K14: 12000 | L14: =F14*K14 -> 720000 | M14: 0.1 | N14: =K14/(1-M14) -> 13333.333 | O14: =N14*F14 -> 800000 | P14: =N14*1.1 -> 14666.667
C15: Dây điện DC 4.0 màu đỏ Cáp điện chuyên dụng DC Solar 0.4 1500V | D15: PN Tech/ Leader | E15: Mét | F15: 60 | G15: 18000 | H15: =F15*G15 -> 1080000 | I15: 5 Năm | K15: 12000 | L15: =F15*K15 -> 720000 | M15: 0.1 | N15: =K15/(1-M15) -> 13333.333 | O15: =N15*F15 -> 800000 | P15: =N15*1.1 -> 14666.667
C16: Dây điện AC 1 pha 2 lõi đồng cao cấp CVV 2x6/2x10mm | D16: Cadivi/Trần Phú Tương đương | E16: Mét | F16: 20 | G16: 40000 | H16: =F16*G16 -> 800000 | I16: 5 Năm | K16: 32000 | L16: =F16*K16 -> 640000 | M16: 0.1 | N16: =K16/(1-M16) -> 35555.556 | O16: =N16*F16 -> 711111.11 | P16: =N16*1.1 -> 39111.111
C17: Dây mạng tín hiệu đo tải tiêu thụ. Từ CT+Metter đến Inverter. Chống phát ngược lên lưới | D17: Việt Nam | E17: Bộ | F17: 1 | G17: 300000 | H17: =F17*G17 -> 300000 | I17: 5 Năm | K17: 0 | L17: =F17*K17 -> 0 | M17: 0.1 | N17: =K17/(1-M17) -> 0 | O17: =N17*F17 -> 0 | P17: =N17*1.1 -> 0
C18: Jack MC4 chuyên dụng NLMT 1500V | D18: PN Tech/ Leader | E18: Bộ | F18: 8 | G18: 30000 | H18: =F18*G18 -> 240000 | I18: 5 Năm | K18: 20000 | L18: =F18*K18 -> 160000 | M18: 0.1 | N18: =K18/(1-M18) -> 22222.222 | O18: =N18*F18 -> 177777.78 | P18: =N18*1.1 -> 24444.444
A19: 6 | B19: TỦ ĐIỆN NLMT | C19: Tủ điện hệ NLMT Hybrid 10kW 1 pha - 2 strings đi theo Inverter đầy đủ ATS của hệ: + Vỏ tủ sắt chuyên dụng - Sơn tĩnh điện. Kích thước 40x60x20cm + ATS 4P-63A: Thương hiệu Aisikai Nhật Bản + At AC 2P 63A; At AC 2P 32A: LS Hàn Quốc + At DC-1000V 2 strings: Vaneims + Chống sét AC- SPC lưới lan truyền: Suntree | D19: SLM | E19: Bộ | F19: 1 | G19: 6500000 | H19: =F19*G19 -> 6500000 | I19: 2 Năm | K19: =4380000/1.1+1500000 -> 5481818.2 | L19: =F19*K19 -> 5481818.2 | M19: 0.1 | N19: =K19/(1-M19) -> 6090909.1 | O19: =N19*F19 -> 6090909.1 | P19: =N19*1.1 -> 6700000
A20: 7 | B20: HỆ TIẾP ĐỊA | C20: Cáp tiếp địa PVC/Cu loại 1x4mm2 | D20: Cadivi/Nival | E20: Mét | F20: 30 | G20: 15000 | H20: =F20*G20 -> 450000 | I20: 2 Năm | K20: 12000 | L20: =F20*K20 -> 360000 | M20: 0.1 | N20: =K20/(1-M20) -> 13333.333 | O20: =N20*F20 -> 400000 | P20: =N20*1.1 -> 14666.667
C21: Cọc đồng Tiếp Địa 1 mét | D21: Việt Nam | E21: Cái | F21: 1 | G21: 250000 | H21: =F21*G21 -> 250000 | I21: 2 Năm | K21: 200000 | L21: =F21*K21 -> 200000 | M21: 0.1 | N21: =K21/(1-M21) -> 222222.22 | O21: =N21*F21 -> 222222.22 | P21: =N21*1.1 -> 244444.44
C22: Ống nhựa HDPE đường kính 32mm (cuộn 25m) | D22: Việt Nam | E22: Mét | F22: 30 | G22: 15000 | H22: =F22*G22 -> 450000 | I22: 2 Năm | K22: 12000 | L22: =F22*K22 -> 360000 | M22: 0.1 | N22: =K22/(1-M22) -> 13333.333 | O22: =N22*F22 -> 400000 | P22: =N22*1.1 -> 14666.667
A23: 8 | B23: NHÂN CÔNG LẮP ĐẶT | C23: Phụ kiện lắp đặt trọn gói (Bulong, ốc vít, Kẹp dây điện, băng keo điện, vật tư chống thấm thi công,…) | D23: SLM | E23: Bộ | F23: 1 | G23: 500000 | H23: =F23*G23 -> 500000 | K23: 500000 | L23: =F23*K23 -> 500000 | M23: 0.1 | N23: =K23/(1-M23) -> 555555.56 | O23: =N23*F23 -> 555555.56 | P23: =N23*1.1 -> 611111.11
C24: Nhân công lắp đặt + Vận chuyển + Kiểm định vận hành | D24: SLM | E24: Bộ | F24: 1 | G24: 4900000 | H24: =F24*G24 -> 4900000 | K24: =1000000*5.58+2000000 -> 7580000 | L24: =F24*K24 -> 7580000 | M24: 0.1 | N24: =K24/(1-M24) -> 8422222.2 | O24: =N24*F24 -> 8422222.2 | P24: =N24*1.1 -> 9264444.4
A25: TỔNG CỘNG GIÁ TRỊ TRỌN GÓI VẬT TƯ THIẾT BỊ - VẬN CHUYỂN - LẮP ĐẶT - BẢO HÀNH | H25: =SUM(H2:H24) -> 87332000 | K25: Total (Excluding VAT) | L25: =SUM(L2:L24) -> 66583842 | O25: =SUM(O2:O24) -> 77056197
K26: Total (Including VAT) | L26: =L25*1.1 -> 73242226 | O26: =O25*1.1 -> 84761816

Sheet HY1P_8.68kWBAT5.12LV
A1: No. | B1: Category | C1: Specification | D1: Brand Name | E1: Unit | F1: Quatity | G1: Unit Price (Including VAT) | H1: Total Price (Including VAT) | I1: Warranty | K1: COST (excluding VAT) | L1: TOTAL COST (excluding VAT) | M1: Gross Margin for Small EPC | N1: Price (excluding VAT) | O1: Total Price (excluding VAT) | P1: Unit Price - checked (Including VAT)
A2: 1 | B2: TẤM PIN PV | C2: Tấm Pin mặt trời Trina Vertex TSM-NEG19RC.20 - Công suất 620Wp All New Công nghệ mới nhất: N-Type i-TopCon Top 1 thế giới về hiệu suất và thương hiệu Tấm pin 2 mặt kính. Hiệu suất 30 năm đạt trên 87.4% | D2: TrinaSolar | E2: Tấm | F2: 14 | G2: 2100000 | H2: =F2*G2 -> 29400000 | I2: 12 Năm | J2: =14*620 -> 8680 | K2: =54*25500*(1+2%) -> 1404540 | L2: =F2*K2 -> 19663560 | M2: 0.15 | N2: =K2/(1-M2) -> 1652400 | O2: =N2*F2 -> 23133600 | P2: =N2*1.1 -> 1817640
A3: 2 | B3: INVERTER DC-AC | C3: Inverter Solis 5KW PRO, Hybrid 1 pha, 2 chuỗi MPPT cho hiệu suất cao 96.9% (Tiêu chuẩn EU 96.5%) Top 3 thế giới về thương hiệu Inverter Cấp độ bảo vệ: IP66 Công suất DC max: 10kWp Đã bao gồm Metter và CT chống phát ngược lưới | D3: Solis | E3: Bộ | F3: 1 | G3: 24800000 | H3: =F3*G3 -> 24800000 | I3: 5 Năm | K3: =20233000/1.1 -> 18393636 | L3: =F3*K3 -> 18393636 | M3: 0.15 | N3: =K3/(1-M3) -> 21639572 | O3: =N3*F3 -> 21639572 | P3: =N3*1.1 -> 23803529
A4: 3 | B4: PIN LƯU TRỮ | C4: Pin Lithium EASYWAY 51,2V-100Ah-5,2kWh Cell Pin từ hãng Gotion - Top 3 thế giới về thương hiệu Cell Pin Bản tiêu chuẩn - màu trắng - Rack IP20 Bảo hành 5 năm | D4: EASYWAY | E4: Bộ | F4: 1 | G4: 23000000 | H4: =F4*G4 -> 23000000 | I4: 5 Năm | K4: =17600000/1.1 -> 16000000 | L4: =F4*K4 -> 16000000 | M4: 0.15 | N4: =K4/(1-M4) -> 18823529 | O4: =N4*F4 -> 18823529 | P4: =N4*1.1 -> 20705882
C5: Dây từ 35, nối Pin Lithium lên Inverter đã bấm sẵn đầu cốt | D5: SLM | E5: Bộ | F5: 1 | G5: 800000 | H5: =F5*G5 -> 800000 | I5: 5 Năm | K5: =300000/1.1 -> 272727.27 | L5: =F5*K5 -> 272727.27 | M5: 0.1 | N5: =K5/(1-M5) -> 303030.3 | O5: =N5*F5 -> 303030.3 | P5: =N5*1.1 -> 333333.33
C6: Dây mạng tín hiệu giao tiếp Inverter - Pin | D6: Việt Nam | E6: Bộ | F6: 1 | G6: 100000 | H6: =F6*G6 -> 100000 | I6: 5 Năm | K6: 0 | L6: =F6*K6 -> 0 | M6: 0.1 | N6: =K6/(1-M6) -> 0 | O6: =N6*F6 -> 0 | P6: =N6*1.1 -> 0
A7: 4 | B7: HỆ KHUNG GIÁ ĐỠ NHÔM CAO CẤP | C7: Kẹp biên PIN năng lượng mặt trời | D7: Việt Nam | E7: Cái | F7: 16 | G7: 11000 | H7: =F7*G7 -> 176000 | I7: 5 Năm | J7: 5-5-4 | K7: 8800 | L7: =F7*K7 -> 140800 | M7: 0.1 | N7: =K7/(1-M7) -> 9777.7778 | O7: =N7*F7 -> 156444.44 | P7: =N7*1.1 -> 10755.556
C8: Kẹp giữa PIN năng lượng mặt trời | D8: Việt Nam | E8: Cái | F8: 16 | G8: 11000 | H8: =F8*G8 -> 176000 | I8: 5 Năm | K8: 8800 | L8: =F8*K8 -> 140800 | M8: 0.1 | N8: =K8/(1-M8) -> 9777.7778 | O8: =N8*F8 -> 156444.44 | P8: =N8*1.1 -> 10755.556
C9: Thanh full rail nhôm cao cấp 4,2m | D9: Việt Nam | E9: Cái | F9: 8 | G9: 360000 | H9: =F9*G9 -> 2880000 | I9: 5 Năm | J9: =14*2*1.2/4.2 -> 8 | K9: 294000 | L9: =F9*K9 -> 2352000 | M9: 0.1 | N9: =K9/(1-M9) -> 326666.67 | O9: =N9*F9 -> 2613333.3 | P9: =N9*1.1 -> 359333.33
C10: Thanh nối nhôm cao cấp | D10: Việt Nam | E10: Cái | F10: 8 | G10: 20000 | H10: =F10*G10 -> 160000 | I10: 5 Năm | K10: 12800 | L10: =F10*K10 -> 102400 | M10: 0.1 | N10: =K10/(1-M10) -> 14222.222 | O10: =N10*F10 -> 113777.78 | P10: =N10*1.1 -> 15644.444
C11: Chân L- nhôm cao cấp | D11: Việt Nam | E11: Cái | F11: 32 | G11: 20000 | H11: =F11*G11 -> 640000 | I11: 5 Năm | K11: 16000 | L11: =F11*K11 -> 512000 | M11: 0.1 | N11: =K11/(1-M11) -> 17777.778 | O11: =N11*F11 -> 568888.89 | P11: =N11*1.1 -> 19555.556
C12: Kẹp tiếp địa | D12: Việt Nam | E12: Cái | F12: 4 | G12: 20000 | H12: =F12*G12 -> 80000 | I12: 5 Năm | K12: 12600 | L12: =F12*K12 -> 50400 | M12: 0.1 | N12: =K12/(1-M12) -> 14000 | O12: =N12*F12 -> 56000 | P12: =N12*1.1 -> 15400
C13: Lá tiếp địa | D13: Việt Nam | E13: Cái | F13: =F8 -> 16 | G13: 2000 | H13: =F13*G13 -> 32000 | I13: 5 Năm | K13: 1500 | L13: =F13*K13 -> 24000 | M13: 0.1 | N13: =K13/(1-M13) -> 1666.6667 | O13: =N13*F13 -> 26666.667 | P13: =N13*1.1 -> 1833.3333
A14: 5 | B14: HỆ DÂY ĐIỆN DC-AC | C14: Dây điện DC 4.0 màu đen Cáp điện chuyên dụng DC Solar 0.4 1500V | D14: PN Tech/ Leader | E14: Mét | F14: 80 | G14: 18000 | H14: =F14*G14 -> 1440000 | I14: 5 Năm | K14: 12000 | L14: =F14*K14 -> 960000 | M14: 0.1 | N14: =K14/(1-M14) -> 13333.333 | O14: =N14*F14 -> 1066666.7 | P14: =N14*1.1 -> 14666.667
C15: Dây điện DC 4.0 màu đỏ Cáp điện chuyên dụng DC Solar 0.4 1500V | D15: PN Tech/ Leader | E15: Mét | F15: 80 | G15: 18000 | H15: =F15*G15 -> 1440000 | I15: 5 Năm | K15: 12000 | L15: =F15*K15 -> 960000 | M15: 0.1 | N15: =K15/(1-M15) -> 13333.333 | O15: =N15*F15 -> 1066666.7 | P15: =N15*1.1 -> 14666.667
C16: Dây điện AC 1 pha 2 lõi đồng cao cấp CVV 2x6/2x10mm | D16: Cadivi/Trần Phú Tương đương | E16: Mét | F16: 20 | G16: 40000 | H16: =F16*G16 -> 800000 | I16: 5 Năm | K16: 40000 | L16: =F16*K16 -> 800000 | M16: 0.1 | N16: =K16/(1-M16) -> 44444.444 | O16: =N16*F16 -> 888888.89 | P16: =N16*1.1 -> 48888.889
C17: Dây mạng tín hiệu đo tải tiêu thụ. Từ CT+Metter đến Inverter. Chống phát ngược lên lưới | D17: Việt Nam | E17: Bộ | F17: 1 | G17: 300000 | H17: =F17*G17 -> 300000 | I17: 5 Năm | K17: 0 | L17: =F17*K17 -> 0 | M17: 0.1 | N17: =K17/(1-M17) -> 0 | O17: =N17*F17 -> 0 | P17: =N17*1.1 -> 0
C18: Jack MC4 chuyên dụng NLMT 1500V | D18: PN Tech/ Leader | E18: Bộ | F18: 8 | G18: 30000 | H18: =F18*G18 -> 240000 | I18: 5 Năm | K18: 20000 | L18: =F18*K18 -> 160000 | M18: 0.1 | N18: =K18/(1-M18) -> 22222.222 | O18: =N18*F18 -> 177777.78 | P18: =N18*1.1 -> 24444.444
A19: 6 | B19: TỦ ĐIỆN NLMT | C19: Tủ điện hệ NLMT Hybrid 10kW 1 pha - 2 strings đi theo Inverter đầy đủ ATS của hệ: + Vỏ tủ sắt chuyên dụng - Sơn tĩnh điện. Kích thước 40x60x20cm + ATS 4P-63A: Thương hiệu Aisikai Nhật Bản + At AC 2P 63A; At AC 2P 32A: LS Hàn Quốc + At DC-1000V 2 strings: Vaneims + Chống sét AC- SPC lưới lan truyền: Suntree | D19: SLM | E19: Bộ | F19: 1 | G19: 6500000 | H19: =F19*G19 -> 6500000 | I19: 2 Năm | K19: =4380000/1.1+1500000 -> 5481818.2 | L19: =F19*K19 -> 5481818.2 | M19: 0.1 | N19: =K19/(1-M19) -> 6090909.1 | O19: =N19*F19 -> 6090909.1 | P19: =N19*1.1 -> 6700000
A20: 7 | B20: HỆ TIẾP ĐỊA | C20: Cáp tiếp địa PVC/Cu loại 1x4mm2 | D20: Cadivi/Nival | E20: Mét | F20: 30 | G20: 15000 | H20: =F20*G20 -> 450000 | I20: 2 Năm | K20: 12000 | L20: =F20*K20 -> 360000 | M20: 0.1 | N20: =K20/(1-M20) -> 13333.333 | O20: =N20*F20 -> 400000 | P20: =N20*1.1 -> 14666.667
C21: Cọc đồng Tiếp Địa 1 mét | D21: Việt Nam | E21: Cái | F21: 1 | G21: 250000 | H21: =F21*G21 -> 250000 | I21: 2 Năm | K21: 200000 | L21: =F21*K21 -> 200000 | M21: 0.1 | N21: =K21/(1-M21) -> 222222.22 | O21: =N21*F21 -> 222222.22 | P21: =N21*1.1 -> 244444.44
C22: Ống nhựa HDPE đường kính 32mm (cuộn 25m) | D22: Việt Nam | E22: Mét | F22: 30 | G22: 15000 | H22: =F22*G22 -> 450000 | I22: 2 Năm | K22: 12000 | L22: =F22*K22 -> 360000 | M22: 0.1 | N22: =K22/(1-M22) -> 13333.333 | O22: =N22*F22 -> 400000 | P22: =N22*1.1 -> 14666.667
A23: 8 | B23: NHÂN CÔNG LẮP ĐẶT | C23: Phụ kiện lắp đặt trọn gói (Bulong, ốc vít, Kẹp dây điện, băng keo điện, vật tư chống thấm thi công,…) | D23: SLM | E23: Bộ | F23: 1 | G23: 1000000 | H23: =F23*G23 -> 1000000 | K23: 1000000 | L23: =F23*K23 -> 1000000 | M23: 0.1 | N23: =K23/(1-M23) -> 1111111.1 | O23: =N23*F23 -> 1111111.1 | P23: =N23*1.1 -> 1222222.2
C24: Nhân công lắp đặt + Vận chuyển + Kiểm định vận hành | D24: SLM | E24: Bộ | F24: 1 | G24: 7900000 | H24: =F24*G24 -> 7900000 | K24: =1000000*8.68+2000000 -> 10680000 | L24: =F24*K24 -> 10680000 | M24: 0.1 | N24: =K24/(1-M24) -> 11866667 | O24: =N24*F24 -> 11866667 | P24: =N24*1.1 -> 13053333
A25: TỔNG CỘNG GIÁ TRỊ TRỌN GÓI VẬT TƯ THIẾT BỊ - VẬN CHUYỂN - LẮP ĐẶT - BẢO HÀNH | H25: =SUM(H2:H24) -> 103014000 | K25: Total (Excluding VAT) | L25: =SUM(L2:L24) -> 78614142 | O25: =SUM(O2:O24) -> 90882197
K26: Total (Including VAT) | L26: =L25*1.1 -> 86475556 | O26: =O25*1.1 -> 99970416

Sheet HY1P_11.16kWBAT5.12LV
A1: No. | B1: Category | C1: Specification | D1: Brand Name | E1: Unit | F1: Quatity | G1: Unit Price (Including VAT) | H1: Total Price (Including VAT) | I1: Warranty | K1: COST (excluding VAT) | L1: TOTAL COST (excluding VAT) | M1: Gross Margin for Small EPC | N1: Price (excluding VAT) | O1: Total Price (excluding VAT) | P1: Unit Price - checked (Including VAT)
A2: 1 | B2: TẤM PIN PV | C2: Tấm Pin mặt trời Trina Vertex TSM-NEG19RC.20 - Công suất 620Wp All New Công nghệ mới nhất: N-Type i-TopCon Top 1 thế giới về hiệu suất và thương hiệu Tấm pin 2 mặt kính. Hiệu suất 30 năm đạt trên 87.4% | D2: TrinaSolar | E2: Tấm | F2: 18 | G2: 2100000 | H2: =F2*G2 -> 37800000 | I2: 12 Năm | J2: =18*620 -> 11160 | K2: =54*25500*(1+2%) -> 1404540 | L2: =F2*K2 -> 25281720 | M2: 0.15 | N2: =K2/(1-M2) -> 1652400 | O2: =N2*F2 -> 29743200 | P2: =N2*1.1 -> 1817640
A3: 2 | B3: INVERTER DC-AC | C3: Inverter S6-EH1P8K-L-PRO, Hybrid 1 pha, 2 chuỗi MPPT cho hiệu suất cao 96.9% (Tiêu chuẩn EU 96.5%) Top 3 thế giới về thương hiệu Inverter Đã bao gồm Metter và CT chống phát ngược lưới | D3: Solis | E3: Bộ | F3: 1 | G3: 39600000 | H3: =F3*G3 -> 39600000 | I3: 5 Năm | K3: =31128000/1.1 -> 28298182 | L3: =F3*K3 -> 28298182 | M3: 0.15 | N3: =K3/(1-M3) -> 33291979 | O3: =N3*F3 -> 33291979 | P3: =N3*1.1 -> 36621176
A4: 3 | B4: PIN LƯU TRỮ | C4: Pin Lithium EASYWAY 51,2V-100Ah-5,2kWh Cell Pin từ hãng Gotion - Top 3 thế giới về thương hiệu Cell Pin Bản tiêu chuẩn - màu trắng - Rack IP20 Bảo hành 5 năm | D4: EASYWAY | E4: Bộ | F4: 1 | G4: 23000000 | H4: =F4*G4 -> 23000000 | I4: 5 Năm | K4: =17600000/1.1 -> 16000000 | L4: =F4*K4 -> 16000000 | M4: 0.15 | N4: =K4/(1-M4) -> 18823529 | O4: =N4*F4 -> 18823529 | P4: =N4*1.1 -> 20705882
C5: Dây từ 35, nối Pin Lithium lên Inverter đã bấm sẵn đầu cốt | D5: SLM | E5: Bộ | F5: 1 | G5: 800000 | H5: =F5*G5 -> 800000 | I5: 5 Năm | K5: =300000/1.1 -> 272727.27 | L5: =F5*K5 -> 272727.27 | M5: 0.1 | N5: =K5/(1-M5) -> 303030.3 | O5: =N5*F5 -> 303030.3 | P5: =N5*1.1 -> 333333.33
C6: Dây mạng tín hiệu giao tiếp Inverter - Pin | D6: Việt Nam | E6: Bộ | F6: 1 | G6: 100000 | H6: =F6*G6 -> 100000 | I6: 5 Năm | K6: 0 | L6: =F6*K6 -> 0 | M6: 0.1 | N6: =K6/(1-M6) -> 0 | O6: =N6*F6 -> 0 | P6: =N6*1.1 -> 0
A7: 4 | B7: HỆ KHUNG GIÁ ĐỠ NHÔM CAO CẤP | C7: Kẹp biên PIN năng lượng mặt trời | D7: Việt Nam | E7: Cái | F7: 20 | G7: 11000 | H7: =F7*G7 -> 220000 | I7: 5 Năm | J7: 5-5-4-4 | K7: 8800 | L7: =F7*K7 -> 176000 | M7: 0.1 | N7: =K7/(1-M7) -> 9777.7778 | O7: =N7*F7 -> 195555.56 | P7: =N7*1.1 -> 10755.556
C8: Kẹp giữa PIN năng lượng mặt trời | D8: Việt Nam | E8: Cái | F8: 32 | G8: 11000 | H8: =F8*G8 -> 352000 | I8: 5 Năm | K8: 8800 | L8: =F8*K8 -> 281600 | M8: 0.1 | N8: =K8/(1-M8) -> 9777.7778 | O8: =N8*F8 -> 312888.89 | P8: =N8*1.1 -> 10755.556
C9: Thanh full rail nhôm cao cấp 4,2m | D9: Việt Nam | E9: Cái | F9: 11 | G9: 360000 | H9: =F9*G9 -> 3960000 | I9: 5 Năm | J9: =18*2*1.2/4.2 -> 10.285714 | K9: 294000 | L9: =F9*K9 -> 3234000 | M9: 0.1 | N9: =K9/(1-M9) -> 326666.67 | O9: =N9*F9 -> 3593333.3 | P9: =N9*1.1 -> 359333.33
C10: Thanh nối nhôm cao cấp | D10: Việt Nam | E10: Cái | F10: 11 | G10: 20000 | H10: =F10*G10 -> 220000 | I10: 5 Năm | K10: 12800 | L10: =F10*K10 -> 140800 | M10: 0.1 | N10: =K10/(1-M10) -> 14222.222 | O10: =N10*F10 -> 156444.44 | P10: =N10*1.1 -> 15644.444
C11: Chân L- nhôm cao cấp | D11: Việt Nam | E11: Cái | F11: 66 | G11: 20000 | H11: =F11*G11 -> 1320000 | I11: 5 Năm | K11: 16000 | L11: =F11*K11 -> 1056000 | M11: 0.1 | N11: =K11/(1-M11) -> 17777.778 | O11: =N11*F11 -> 1173333.3 | P11: =N11*1.1 -> 19555.556
C12: Kẹp tiếp địa | D12: Việt Nam | E12: Cái | F12: 6 | G12: 20000 | H12: =F12*G12 -> 120000 | I12: 5 Năm | K12: 12600 | L12: =F12*K12 -> 75600 | M12: 0.1 | N12: =K12/(1-M12) -> 14000 | O12: =N12*F12 -> 84000 | P12: =N12*1.1 -> 15400
C13: Lá tiếp địa | D13: Việt Nam | E13: Cái | F13: =F8 -> 32 | G13: 2000 | H13: =F13*G13 -> 64000 | I13: 5 Năm | K13: 1500 | L13: =F13*K13 -> 48000 | M13: 0.1 | N13: =K13/(1-M13) -> 1666.6667 | O13: =N13*F13 -> 53333.333 | P13: =N13*1.1 -> 1833.3333
A14: 5 | B14: HỆ DÂY ĐIỆN DC-AC | C14: Dây điện DC 4.0 màu đen Cáp điện chuyên dụng DC Solar 0.4 1500V | D14: PN Tech/ Leader | E14: Mét | F14: 100 | G14: 18000 | H14: =F14*G14 -> 1800000 | I14: 5 Năm | K14: 12000 | L14: =F14*K14 -> 1200000 | M14: 0.1 | N14: =K14/(1-M14) -> 13333.333 | O14: =N14*F14 -> 1333333.3 | P14: =N14*1.1 -> 14666.667
C15: Dây điện DC 4.0 màu đỏ Cáp điện chuyên dụng DC Solar 0.4 1500V | D15: PN Tech/ Leader | E15: Mét | F15: 100 | G15: 18000 | H15: =F15*G15 -> 1800000 | I15: 5 Năm | K15: 12000 | L15: =F15*K15 -> 1200000 | M15: 0.1 | N15: =K15/(1-M15) -> 13333.333 | O15: =N15*F15 -> 1333333.3 | P15: =N15*1.1 -> 14666.667
C16: Dây điện AC 1 pha 2 lõi đồng cao cấp CVV 2x10mm | D16: Cadivi/Trần Phú Tương đương | E16: Mét | F16: 20 | G16: 80000 | H16: =F16*G16 -> 1600000 | I16: 5 Năm | K16: 65000 | L16: =F16*K16 -> 1300000 | M16: 0.1 | N16: =K16/(1-M16) -> 72222.222 | O16: =N16*F16 -> 1444444.4 | P16: =N16*1.1 -> 79444.444
C17: Dây mạng tín hiệu đo tải tiêu thụ. Từ CT+Metter đến Inverter. Chống phát ngược lên lưới | D17: Việt Nam | E17: Bộ | F17: 1 | G17: 300000 | H17: =F17*G17 -> 300000 | I17: 5 Năm | K17: 0 | L17: =F17*K17 -> 0 | M17: 0.1 | N17: =K17/(1-M17) -> 0 | O17: =N17*F17 -> 0 | P17: =N17*1.1 -> 0
C18: Jack MC4 chuyên dụng NLMT 1500V | D18: PN Tech/ Leader | E18: Bộ | F18: 10 | G18: 30000 | H18: =F18*G18 -> 300000 | I18: 5 Năm | K18: 20000 | L18: =F18*K18 -> 200000 | M18: 0.1 | N18: =K18/(1-M18) -> 22222.222 | O18: =N18*F18 -> 222222.22 | P18: =N18*1.1 -> 24444.444
A19: 6 | B19: TỦ ĐIỆN NLMT | C19: Tủ điện hệ NLMT Hybrid 15kW 1 pha - 2 strings đi theo Inverter đầy đủ ATS của hệ: + Vỏ tủ sắt chuyên dụng - Sơn tĩnh điện. Kích thước 40x60x20cm + ATS 4P-63A: Thương hiệu Aisikai Nhật Bản + At AC 2P 63A; At AC 2P 32A: LS Hàn Quốc + At DC-1000V 2 strings: Vaneims + Chống sét AC- SPC lưới lan truyền: Suntree | D19: SLM | E19: Bộ | F19: 1 | G19: 6500000 | H19: =F19*G19 -> 6500000 | I19: 2 Năm | K19: =4380000/1.1+1500000 -> 5481818.2 | L19: =F19*K19 -> 5481818.2 | M19: 0.1 | N19: =K19/(1-M19) -> 6090909.1 | O19: =N19*F19 -> 6090909.1 | P19: =N19*1.1 -> 6700000
A20: 7 | B20: HỆ TIẾP ĐỊA | C20: Cáp tiếp địa PVC/Cu loại 1x4mm2 | D20: Cadivi/Nival | E20: Mét | F20: 60 | G20: 15000 | H20: =F20*G20 -> 900000 | I20: 2 Năm | K20: 12000 | L20: =F20*K20 -> 720000 | M20: 0.1 | N20: =K20/(1-M20) -> 13333.333 | O20: =N20*F20 -> 800000 | P20: =N20*1.1 -> 14666.667
C21: Cọc đồng Tiếp Địa 1 mét | D21: Việt Nam | E21: Cái | F21: 2 | G21: 250000 | H21: =F21*G21 -> 500000 | I21: 2 Năm | K21: 200000 | L21: =F21*K21 -> 400000 | M21: 0.1 | N21: =K21/(1-M21) -> 222222.22 | O21: =N21*F21 -> 444444.44 | P21: =N21*1.1 -> 244444.44
C22: Ống nhựa HDPE đường kính 32mm (cuộn 25m) | D22: Việt Nam | E22: Mét | F22: 60 | G22: 15000 | H22: =F22*G22 -> 900000 | I22: 2 Năm | K22: 12000 | L22: =F22*K22 -> 720000 | M22: 0.1 | N22: =K22/(1-M22) -> 13333.333 | O22: =N22*F22 -> 800000 | P22: =N22*1.1 -> 14666.667
A23: 8 | B23: NHÂN CÔNG LẮP ĐẶT | C23: Phụ kiện lắp đặt trọn gói (Bulong, ốc vít, Kẹp dây điện, băng keo điện, vật tư chống thấm thi công,…) | D23: SLM | E23: Bộ | F23: 1 | G23: 1000000 | H23: =F23*G23 -> 1000000 | K23: 1000000 | L23: =F23*K23 -> 1000000 | M23: 0.1 | N23: =K23/(1-M23) -> 1111111.1 | O23: =N23*F23 -> 1111111.1 | P23: =N23*1.1 -> 1222222.2
C24: Nhân công lắp đặt + Vận chuyển + Kiểm định vận hành | D24: SLM | E24: Bộ | F24: 1 | G24: 9600000 | H24: =F24*G24 -> 9600000 | K24: =1000000*11.16+2000000 -> 13160000 | L24: =F24*K24 -> 13160000 | M24: 0.1 | N24: =K24/(1-M24) -> 14622222 | O24: =N24*F24 -> 14622222 | P24: =N24*1.1 -> 16084444
A25: TỔNG CỘNG GIÁ TRỊ TRỌN GÓI VẬT TƯ THIẾT BỊ - VẬN CHUYỂN - LẮP ĐẶT - BẢO HÀNH | H25: =SUM(H2:H24) -> 132756000 | K25: Total (Excluding VAT) | L25: =SUM(L2:L24) -> 1.0024645e+08 | O25: =SUM(O2:O24) -> 1.1593265e+08
K26: Total (Including VAT) | L26: =L25*1.1 -> 110271092 | O26: =O25*1.1 -> 1.2752591e+08

Sheet HY1P_14.88kWBAT14.3LV
A1: No. | B1: Category | C1: Specification | D1: Brand Name | E1: Unit | F1: Quatity | G1: Unit Price (Including VAT) | H1: Total Price (Including VAT) | I1: Warranty | K1: COST (excluding VAT) | L1: TOTAL COST (excluding VAT) | M1: Gross Margin for Small EPC | N1: Price (excluding VAT) | O1: Total Price (excluding VAT) | P1: Unit Price - checked (Including VAT)
A2: 1 | B2: TẤM PIN PV | C2: Tấm Pin mặt trời Trina Vertex TSM-NEG19RC.20 - Công suất 620Wp All New Công nghệ mới nhất: N-Type i-TopCon Top 1 thế giới về hiệu suất và thương hiệu Tấm pin 2 mặt kính. Hiệu suất 30 năm đạt trên 87.4% | D2: TrinaSolar | E2: Tấm | F2: 24 | G2: 2100000 | H2: =F2*G2 -> 50400000 | I2: 12 Năm | J2: =24*620 -> 14880 | K2: =54*25500*(1+2%) -> 1404540 | L2: =F2*K2 -> 33708960 | M2: 0.15 | N2: =K2/(1-M2) -> 1652400 | O2: =N2*F2 -> 39657600 | P2: =N2*1.1 -> 1817640
A3: 2 | B3: INVERTER DC-AC | C3: Inverter S6-EH1P8K-L-PRO, Hybrid 1 pha, 2 chuỗi MPPT cho hiệu suất cao 96.9% (Tiêu chuẩn EU 96.5%) Top 3 thế giới về thương hiệu Inverter Đã bao gồm Metter và CT chống phát ngược lưới | D3: Solis | E3: Bộ | F3: 1 | G3: 39600000 | H3: =F3*G3 -> 39600000 | I3: 5 Năm | K3: =31128000/1.1 -> 28298182 | L3: =F3*K3 -> 28298182 | M3: 0.15 | N3: =K3/(1-M3) -> 33291979 | O3: =N3*F3 -> 33291979 | P3: =N3*1.1 -> 36621176
A4: 3 | B4: PIN LƯU TRỮ | C4: Pin Lithium EASYWAY 51,2V-280Ah. Lưu trữ 14.3kWh Cell Pin từ hãng GreatPower - Top 10 thế giới về thương hiệu Cell Pin Bản cao cấp màu trắng - có bánh xe Cấp bảo vệ: IP54 chống nước chống bụi cao | D4: EASYWAY | E4: Bộ | F4: 1 | G4: 60000000 | H4: =F4*G4 -> 60000000 | I4: 5 Năm | K4: =47470000/1.1 -> 43154545 | L4: =F4*K4 -> 43154545 | M4: 0.15 | N4: =K4/(1-M4) -> 50770053 | O4: =N4*F4 -> 50770053 | P4: =N4*1.1 -> 55847059
C5: Dây từ 35, nối Pin Lithium lên Inverter đã bấm sẵn đầu cốt | D5: SLM | E5: Bộ | F5: 1 | G5: 800000 | H5: =F5*G5 -> 800000 | I5: 5 Năm | K5: =300000/1.1 -> 272727.27 | L5: =F5*K5 -> 272727.27 | M5: 0.1 | N5: =K5/(1-M5) -> 303030.3 | O5: =N5*F5 -> 303030.3 | P5: =N5*1.1 -> 333333.33
C6: Dây mạng tín hiệu giao tiếp Inverter - Pin | D6: Việt Nam | E6: Bộ | F6: 1 | G6: 100000 | H6: =F6*G6 -> 100000 | I6: 5 Năm | K6: 0 | L6: =F6*K6 -> 0 | M6: 0.1 | N6: =K6/(1-M6) -> 0 | O6: =N6*F6 -> 0 | P6: =N6*1.1 -> 0
A7: 4 | B7: HỆ KHUNG GIÁ ĐỠ NHÔM CAO CẤP | C7: Kẹp biên PIN năng lượng mặt trời | D7: Việt Nam | E7: Cái | F7: 24 | G7: 11000 | H7: =F7*G7 -> 264000 | I7: 5 Năm | J7: 5-5-5-5-4 | K7: 8800 | L7: =F7*K7 -> 211200 | M7: 0.1 | N7: =K7/(1-M7) -> 9777.7778 | O7: =N7*F7 -> 234666.67 | P7: =N7*1.1 -> 10755.556
C8: Kẹp giữa PIN năng lượng mặt trời | D8: Việt Nam | E8: Cái | F8: 40 | G8: 11000 | H8: =F8*G8 -> 440000 | I8: 5 Năm | K8: 8800 | L8: =F8*K8 -> 352000 | M8: 0.1 | N8: =K8/(1-M8) -> 9777.7778 | O8: =N8*F8 -> 391111.11 | P8: =N8*1.1 -> 10755.556
C9: Thanh full rail nhôm cao cấp 4,2m | D9: Việt Nam | E9: Cái | F9: 14 | G9: 360000 | H9: =F9*G9 -> 5040000 | I9: 5 Năm | J9: =24*2*1.2/4.2 -> 13.714286 | K9: 294000 | L9: =F9*K9 -> 4116000 | M9: 0.1 | N9: =K9/(1-M9) -> 326666.67 | O9: =N9*F9 -> 4573333.3 | P9: =N9*1.1 -> 359333.33
C10: Thanh nối nhôm cao cấp | D10: Việt Nam | E10: Cái | F10: 14 | G10: 20000 | H10: =F10*G10 -> 280000 | I10: 5 Năm | K10: 12800 | L10: =F10*K10 -> 179200 | M10: 0.1 | N10: =K10/(1-M10) -> 14222.222 | O10: =N10*F10 -> 199111.11 | P10: =N10*1.1 -> 15644.444
C11: Chân L- nhôm cao cấp | D11: Việt Nam | E11: Cái | F11: 86 | G11: 20000 | H11: =F11*G11 -> 1720000 | I11: 5 Năm | K11: 16000 | L11: =F11*K11 -> 1376000 | M11: 0.1 | N11: =K11/(1-M11) -> 17777.778 | O11: =N11*F11 -> 1528888.9 | P11: =N11*1.1 -> 19555.556
C12: Kẹp tiếp địa | D12: Việt Nam | E12: Cái | F12: 8 | G12: 20000 | H12: =F12*G12 -> 160000 | I12: 5 Năm | K12: 12600 | L12: =F12*K12 -> 100800 | M12: 0.1 | N12: =K12/(1-M12) -> 14000 | O12: =N12*F12 -> 112000 | P12: =N12*1.1 -> 15400
C13: Lá tiếp địa | D13: Việt Nam | E13: Cái | F13: =F8 -> 40 | G13: 2000 | H13: =F13*G13 -> 80000 | I13: 5 Năm | K13: 1500 | L13: =F13*K13 -> 60000 | M13: 0.1 | N13: =K13/(1-M13) -> 1666.6667 | O13: =N13*F13 -> 66666.667 | P13: =N13*1.1 -> 1833.3333
A14: 5 | B14: HỆ DÂY ĐIỆN DC-AC | C14: Dây điện DC 4.0 màu đen Cáp điện chuyên dụng DC Solar 0.4 1500V | D14: PN Tech/ Leader | E14: Mét | F14: 100 | G14: 18000 | H14: =F14*G14 -> 1800000 | I14: 5 Năm | K14: 12000 | L14: =F14*K14 -> 1200000 | M14: 0.1 | N14: =K14/(1-M14) -> 13333.333 | O14: =N14*F14 -> 1333333.3 | P14: =N14*1.1 -> 14666.667
C15: Dây điện DC 4.0 màu đỏ Cáp điện chuyên dụng DC Solar 0.4 1500V | D15: PN Tech/ Leader | E15: Mét | F15: 100 | G15: 18000 | H15: =F15*G15 -> 1800000 | I15: 5 Năm | K15: 12000 | L15: =F15*K15 -> 1200000 | M15: 0.1 | N15: =K15/(1-M15) -> 13333.333 | O15: =N15*F15 -> 1333333.3 | P15: =N15*1.1 -> 14666.667
C16: Dây điện AC 1 pha 2 lõi đồng cao cấp CVV 2x10mm | D16: Cadivi/Trần Phú Tương đương | E16: Mét | F16: 20 | G16: 80000 | H16: =F16*G16 -> 1600000 | I16: 5 Năm | K16: 65000 | L16: =F16*K16 -> 1300000 | M16: 0.1 | N16: =K16/(1-M16) -> 72222.222 | O16: =N16*F16 -> 1444444.4 | P16: =N16*1.1 -> 79444.444
C17: Dây mạng tín hiệu đo tải tiêu thụ. Từ CT+Metter đến Inverter. Chống phát ngược lên lưới | D17: Việt Nam | E17: Bộ | F17: 1 | G17: 300000 | H17: =F17*G17 -> 300000 | I17: 5 Năm | K17: 0 | L17: =F17*K17 -> 0 | M17: 0.1 | N17: =K17/(1-M17) -> 0 | O17: =N17*F17 -> 0 | P17: =N17*1.1 -> 0
C18: Jack MC4 chuyên dụng NLMT 1500V | D18: PN Tech/ Leader | E18: Bộ | F18: 12 | G18: 30000 | H18: =F18*G18 -> 360000 | I18: 5 Năm | K18: 20000 | L18: =F18*K18 -> 240000 | M18: 0.1 | N18: =K18/(1-M18) -> 22222.222 | O18: =N18*F18 -> 266666.67 | P18: =N18*1.1 -> 24444.444
A19: 6 | B19: TỦ ĐIỆN NLMT | C19: Tủ điện hệ NLMT Hybrid 15kW 1 pha - 2 strings đi theo Inverter đầy đủ ATS của hệ: + Vỏ tủ sắt chuyên dụng - Sơn tĩnh điện. Kích thước 40x60x20cm + ATS 4P-63A: Thương hiệu Aisikai Nhật Bản + At AC 2P 63A; At AC 2P 32A: LS Hàn Quốc + At DC-1000V 2 strings: Vaneims + Chống sét AC- SPC lưới lan truyền: Suntree | D19: SLM | E19: Bộ | F19: 1 | G19: 6500000 | H19: =F19*G19 -> 6500000 | I19: 2 Năm | K19: =4380000/1.1+1500000 -> 5481818.2 | L19: =F19*K19 -> 5481818.2 | M19: 0.1 | N19: =K19/(1-M19) -> 6090909.1 | O19: =N19*F19 -> 6090909.1 | P19: =N19*1.1 -> 6700000
A20: 7 | B20: HỆ TIẾP ĐỊA | C20: Cáp tiếp địa PVC/Cu loại 1x4mm2 | D20: Cadivi/Nival | E20: Mét | F20: 60 | G20: 15000 | H20: =F20*G20 -> 900000 | I20: 2 Năm | K20: 12000 | L20: =F20*K20 -> 720000 | M20: 0.1 | N20: =K20/(1-M20) -> 13333.333 | O20: =N20*F20 -> 800000 | P20: =N20*1.1 -> 14666.667
C21: Cọc đồng Tiếp Địa 1 mét | D21: Việt Nam | E21: Cái | F21: 2 | G21: 250000 | H21: =F21*G21 -> 500000 | I21: 2 Năm | K21: 200000 | L21: =F21*K21 -> 400000 | M21: 0.1 | N21: =K21/(1-M21) -> 222222.22 | O21: =N21*F21 -> 444444.44 | P21: =N21*1.1 -> 244444.44
C22: Ống nhựa HDPE đường kính 32mm (cuộn 25m) | D22: Việt Nam | E22: Mét | F22: 60 | G22: 15000 | H22: =F22*G22 -> 900000 | I22: 2 Năm | K22: 12000 | L22: =F22*K22 -> 720000 | M22: 0.1 | N22: =K22/(1-M22) -> 13333.333 | O22: =N22*F22 -> 800000 | P22: =N22*1.1 -> 14666.667
A23: 8 | B23: NHÂN CÔNG LẮP ĐẶT | C23: Phụ kiện lắp đặt trọn gói (Bulong, ốc vít, Kẹp dây điện, băng keo điện, vật tư chống thấm thi công,…) | D23: SLM | E23: Bộ | F23: 1 | G23: 2000000 | H23: =F23*G23 -> 2000000 | K23: 1000000 | L23: =F23*K23 -> 1000000 | M23: 0.1 | N23: =K23/(1-M23) -> 1111111.1 | O23: =N23*F23 -> 1111111.1 | P23: =N23*1.1 -> 1222222.2
C24: Nhân công lắp đặt + Vận chuyển + Kiểm định vận hành | D24: SLM | E24: Bộ | F24: 1 | G24: 13900000 | H24: =F24*G24 -> 13900000 | K24: =1000000*14.88+2000000 -> 16880000 | L24: =F24*K24 -> 16880000 | M24: 0.1 | N24: =K24/(1-M24) -> 18755556 | O24: =N24*F24 -> 18755556 | P24: =N24*1.1 -> 20631111
A25: TỔNG CỘNG GIÁ TRỊ TRỌN GÓI VẬT TƯ THIẾT BỊ - VẬN CHUYỂN - LẮP ĐẶT - BẢO HÀNH | H25: =SUM(H2:H24) -> 189444000 | K25: Total (Excluding VAT) | L25: =SUM(L2:L24) -> 1.4097143e+08 | O25: =SUM(O2:O24) -> 1.6350824e+08
K26: Total (Including VAT) | L26: =L25*1.1 -> 155068576 | O26: =O25*1.1 -> 1.7985906e+08

Sheet HY3P_11.16kWBAT5.12LV
A1: No. | B1: Category | C1: Specification | D1: Brand Name | E1: Unit | F1: Quatity | G1: Unit Price (Including VAT) | H1: Total Price (Including VAT) | I1: Warranty | K1: COST (excluding VAT) | L1: TOTAL COST (excluding VAT) | M1: Gross Margin for Small EPC | N1: Price (excluding VAT) | O1: Total Price (excluding VAT) | P1: Unit Price - checked (Including VAT)
A2: 1 | B2: TẤM PIN PV | C2: Tấm Pin mặt trời Trina Vertex TSM-NEG19RC.20 - Công suất 620Wp All New Công nghệ mới nhất: N-Type i-TopCon Top 1 thế giới về hiệu suất và thương hiệu Tấm pin 2 mặt kính. Hiệu suất 30 năm đạt trên 87.4% | D2: TrinaSolar | E2: Tấm | F2: 18 | G2: 2100000 | H2: =F2*G2 -> 37800000 | I2: 12 Năm | J2: =18*620 -> 11160 | K2: =54*25500*(1+2%) -> 1404540 | L2: =F2*K2 -> 25281720 | M2: 0.15 | N2: =K2/(1-M2) -> 1652400 | O2: =N2*F2 -> 29743200 | P2: =N2*1.1 -> 1817640
A3: 2 | B3: INVERTER DC-AC | C3: Inverter S6-EH3P10K2 - NV-YD-L, Hybrid 3 pha áp thấp, 2 MPPT/ 3 String cho hiệu suất cao 97.6% (Tiêu chuẩn EU 97%) Top 3 thế giới về thương hiệu Inverter Đã bao gồm Metter và CT chống phát ngược lưới | D3: Solis | E3: Bộ | F3: 1 | G3: 56500000 | H3: =F3*G3 -> 56500000 | I3: 5 Năm | K3: =45400000/1.1 -> 41272727 | L3: =F3*K3 -> 41272727 | M3: 0.15 | N3: =K3/(1-M3) -> 48556150 | O3: =N3*F3 -> 48556150 | P3: =N3*1.1 -> 53411765
A4: 3 | B4: PIN LƯU TRỮ | C4: Pin Lithium EASYWAY 51,2V-100Ah-5,2kWh Cell Pin từ hãng Gotion - Top 3 thế giới về thương hiệu Cell Pin Bản tiêu chuẩn - màu trắng - Rack IP20 Bảo hành 5 năm | D4: EASYWAY | E4: Bộ | F4: 1 | G4: 23000000 | H4: =F4*G4 -> 23000000 | I4: 5 Năm | K4: =17600000/1.1 -> 16000000 | L4: =F4*K4 -> 16000000 | M4: 0.15 | N4: =K4/(1-M4) -> 18823529 | O4: =N4*F4 -> 18823529 | P4: =N4*1.1 -> 20705882
C5: Dây từ 35, nối Pin Lithium lên Inverter đã bấm sẵn đầu cốt | D5: SLM | E5: Bộ | F5: 1 | G5: 800000 | H5: =F5*G5 -> 800000 | I5: 5 Năm | K5: =300000/1.1 -> 272727.27 | L5: =F5*K5 -> 272727.27 | M5: 0.1 | N5: =K5/(1-M5) -> 303030.3 | O5: =N5*F5 -> 303030.3 | P5: =N5*1.1 -> 333333.33
C6: Dây mạng tín hiệu giao tiếp Inverter - Pin | D6: Việt Nam | E6: Bộ | F6: 1 | G6: 100000 | H6: =F6*G6 -> 100000 | I6: 5 Năm | K6: 0 | L6: =F6*K6 -> 0 | M6: 0.1 | N6: =K6/(1-M6) -> 0 | O6: =N6*F6 -> 0 | P6: =N6*1.1 -> 0
A7: 4 | B7: HỆ KHUNG GIÁ ĐỠ NHÔM CAO CẤP | C7: Kẹp biên PIN năng lượng mặt trời | D7: Việt Nam | E7: Cái | F7: 20 | G7: 11000 | H7: =F7*G7 -> 220000 | I7: 5 Năm | J7: 5-5-4-4 | K7: 8800 | L7: =F7*K7 -> 176000 | M7: 0.1 | N7: =K7/(1-M7) -> 9777.7778 | O7: =N7*F7 -> 195555.56 | P7: =N7*1.1 -> 10755.556
C8: Kẹp giữa PIN năng lượng mặt trời | D8: Việt Nam | E8: Cái | F8: 32 | G8: 11000 | H8: =F8*G8 -> 352000 | I8: 5 Năm | K8: 8800 | L8: =F8*K8 -> 281600 | M8: 0.1 | N8: =K8/(1-M8) -> 9777.7778 | O8: =N8*F8 -> 312888.89 | P8: =N8*1.1 -> 10755.556
C9: Thanh full rail nhôm cao cấp 4,2m | D9: Việt Nam | E9: Cái | F9: 11 | G9: 360000 | H9: =F9*G9 -> 3960000 | I9: 5 Năm | J9: =18*2*1.2/4.2 -> 10.285714 | K9: 294000 | L9: =F9*K9 -> 3234000 | M9: 0.1 | N9: =K9/(1-M9) -> 326666.67 | O9: =N9*F9 -> 3593333.3 | P9: =N9*1.1 -> 359333.33
C10: Thanh nối nhôm cao cấp | D10: Việt Nam | E10: Cái | F10: 11 | G10: 20000 | H10: =F10*G10 -> 220000 | I10: 5 Năm | K10: 12800 | L10: =F10*K10 -> 140800 | M10: 0.1 | N10: =K10/(1-M10) -> 14222.222 | O10: =N10*F10 -> 156444.44 | P10: =N10*1.1 -> 15644.444
C11: Chân L- nhôm cao cấp | D11: Việt Nam | E11: Cái | F11: 66 | G11: 20000 | H11: =F11*G11 -> 1320000 | I11: 5 Năm | K11: 16000 | L11: =F11*K11 -> 1056000 | M11: 0.1 | N11: =K11/(1-M11) -> 17777.778 | O11: =N11*F11 -> 1173333.3 | P11: =N11*1.1 -> 19555.556
C12: Kẹp tiếp địa | D12: Việt Nam | E12: Cái | F12: 6 | G12: 20000 | H12: =F12*G12 -> 120000 | I12: 5 Năm | K12: 12600 | L12: =F12*K12 -> 75600 | M12: 0.1 | N12: =K12/(1-M12) -> 14000 | O12: =N12*F12 -> 84000 | P12: =N12*1.1 -> 15400
C13: Lá tiếp địa | D13: Việt Nam | E13: Cái | F13: =F8 -> 32 | G13: 2000 | H13: =F13*G13 -> 64000 | I13: 5 Năm | K13: 1500 | L13: =F13*K13 -> 48000 | M13: 0.1 | N13: =K13/(1-M13) -> 1666.6667 | O13: =N13*F13 -> 53333.333 | P13: =N13*1.1 -> 1833.3333
A14: 5 | B14: HỆ DÂY ĐIỆN DC-AC | C14: Dây điện DC 4.0 màu đen Cáp điện chuyên dụng DC Solar 0.4 1500V | D14: PN Tech/ Leader | E14: Mét | F14: 100 | G14: 18000 | H14: =F14*G14 -> 1800000 | I14: 5 Năm | K14: 12000 | L14: =F14*K14 -> 1200000 | M14: 0.1 | N14: =K14/(1-M14) -> 13333.333 | O14: =N14*F14 -> 1333333.3 | P14: =N14*1.1 -> 14666.667
C15: Dây điện DC 4.0 màu đỏ Cáp điện chuyên dụng DC Solar 0.4 1500V | D15: PN Tech/ Leader | E15: Mét | F15: 100 | G15: 18000 | H15: =F15*G15 -> 1800000 | I15: 5 Năm | K15: 12000 | L15: =F15*K15 -> 1200000 | M15: 0.1 | N15: =K15/(1-M15) -> 13333.333 | O15: =N15*F15 -> 1333333.3 | P15: =N15*1.1 -> 14666.667
C16: Dây điện AC 3 pha 4 lõi đồng cao cấp CVV 4x10 mm | D16: Cadisun/Trần Phú Tương đương | E16: Mét | F16: 20 | G16: 150000 | H16: =F16*G16 -> 3000000 | I16: 5 Năm | K16: =135000/1.1+100000/20 -> 127727.27 | L16: =F16*K16 -> 2554545.5 | M16: 0.1 | N16: =K16/(1-M16) -> 141919.19 | O16: =N16*F16 -> 2838383.8 | P16: =N16*1.1 -> 156111.11
C17: Dây mạng tín hiệu đo tải tiêu thụ. Từ CT+Metter đến Inverter. Chống phát ngược lên lưới | D17: Việt Nam | E17: Bộ | F17: 1 | G17: 300000 | H17: =F17*G17 -> 300000 | I17: 5 Năm | K17: 0 | L17: =F17*K17 -> 0 | M17: 0.1 | N17: =K17/(1-M17) -> 0 | O17: =N17*F17 -> 0 | P17: =N17*1.1 -> 0
C18: Jack MC4 chuyên dụng NLMT 1500V | D18: PN Tech/ Leader | E18: Bộ | F18: 10 | G18: 30000 | H18: =F18*G18 -> 300000 | I18: 5 Năm | K18: 20000 | L18: =F18*K18 -> 200000 | M18: 0.1 | N18: =K18/(1-M18) -> 22222.222 | O18: =N18*F18 -> 222222.22 | P18: =N18*1.1 -> 24444.444
A19: 6 | B19: TỦ ĐIỆN NLMT | C19: Tủ điện hệ NLMT Hybrid 15kW 3 pha - 3 strings đi theo Inverter đầy đủ ATS của hệ: + Vỏ tủ sắt chuyên dụng - Sơn tĩnh điện. Kích thước 40x60x20cm + ATS 4P-100A: Thương hiệu Aisikai Nhật Bản + At AC 2P 63A; At AC 2P 32A: LS Hàn Quốc + At DC-1000V 3 strings: Vaneims + Chống sét AC- SPC lưới lan truyền: Suntree | D19: SLM | E19: Bộ | F19: 1 | G19: 8500000 | H19: =F19*G19 -> 8500000 | I19: 2 Năm | K19: =5380000/1.1+1500000 -> 6390909.1 | L19: =F19*K19 -> 6390909.1 | M19: 0.1 | N19: =K19/(1-M19) -> 7101010.1 | O19: =N19*F19 -> 7101010.1 | P19: =N19*1.1 -> 7811111.1
A20: 7 | B20: HỆ TIẾP ĐỊA | C20: Cáp tiếp địa PVC/Cu loại 1x4mm2 | D20: Cadivi/Nival | E20: Mét | F20: 60 | G20: 15000 | H20: =F20*G20 -> 900000 | I20: 2 Năm | K20: 12000 | L20: =F20*K20 -> 720000 | M20: 0.1 | N20: =K20/(1-M20) -> 13333.333 | O20: =N20*F20 -> 800000 | P20: =N20*1.1 -> 14666.667
C21: Cọc đồng Tiếp Địa 1 mét | D21: Việt Nam | E21: Cái | F21: 2 | G21: 250000 | H21: =F21*G21 -> 500000 | I21: 2 Năm | K21: 200000 | L21: =F21*K21 -> 400000 | M21: 0.1 | N21: =K21/(1-M21) -> 222222.22 | O21: =N21*F21 -> 444444.44 | P21: =N21*1.1 -> 244444.44
C22: Ống nhựa HDPE đường kính 32mm (cuộn 25m) | D22: Việt Nam | E22: Mét | F22: 60 | G22: 15000 | H22: =F22*G22 -> 900000 | I22: 2 Năm | K22: 12000 | L22: =F22*K22 -> 720000 | M22: 0.1 | N22: =K22/(1-M22) -> 13333.333 | O22: =N22*F22 -> 800000 | P22: =N22*1.1 -> 14666.667
A23: 8 | B23: NHÂN CÔNG LẮP ĐẶT | C23: Phụ kiện lắp đặt trọn gói (Bulong, ốc vít, Kẹp dây điện, băng keo điện, vật tư chống thấm thi công,…) | D23: SLM | E23: Bộ | F23: 1 | G23: 2000000 | H23: =F23*G23 -> 2000000 | K23: 1000000 | L23: =F23*K23 -> 1000000 | M23: 0.1 | N23: =K23/(1-M23) -> 1111111.1 | O23: =N23*F23 -> 1111111.1 | P23: =N23*1.1 -> 1222222.2
C24: Nhân công lắp đặt + Vận chuyển + Kiểm định vận hành | D24: SLM | E24: Bộ | F24: 1 | G24: 9600000 | H24: =F24*G24 -> 9600000 | K24: =1000000*11.16+2000000 -> 13160000 | L24: =F24*K24 -> 13160000 | M24: 0.1 | N24: =K24/(1-M24) -> 14622222 | O24: =N24*F24 -> 14622222 | P24: =N24*1.1 -> 16084444
A25: TỔNG CỘNG GIÁ TRỊ TRỌN GÓI VẬT TƯ THIẾT BỊ - VẬN CHUYỂN - LẮP ĐẶT - BẢO HÀNH | H25: =SUM(H2:H24) -> 154056000 | K25: Total (Excluding VAT) | L25: =SUM(L2:L24) -> 1.1538463e+08 | O25: =SUM(O2:O24) -> 1.3360086e+08
K26: Total (Including VAT) | L26: =L25*1.1 -> 126923092 | O26: =O25*1.1 -> 1.4696094e+08

Sheet HY3P_16.74kWBAT14.3LV
A1: No. | B1: Category | C1: Specification | D1: Brand Name | E1: Unit | F1: Quatity | G1: Unit Price (Including VAT) | H1: Total Price (Including VAT) | I1: Warranty | K1: COST (excluding VAT) | L1: TOTAL COST (excluding VAT) | M1: Gross Margin for Small EPC | N1: Price (excluding VAT) | O1: Total Price (excluding VAT) | P1: Unit Price - checked (Including VAT)
A2: 1 | B2: TẤM PIN PV | C2: Tấm Pin mặt trời Trina Vertex TSM-NEG19RC.20 - Công suất 620Wp All New Công nghệ mới nhất: N-Type i-TopCon Top 1 thế giới về hiệu suất và thương hiệu Tấm pin 2 mặt kính. Hiệu suất 30 năm đạt trên 87.4% | D2: TrinaSolar | E2: Tấm | F2: 27 | G2: 2100000 | H2: =F2*G2 -> 56700000 | I2: 12 Năm | J2: =27*620 -> 16740 | K2: =54*25500*(1+2%) -> 1404540 | L2: =F2*K2 -> 37922580 | M2: 0.15 | N2: =K2/(1-M2) -> 1652400 | O2: =N2*F2 -> 44614800 | P2: =N2*1.1 -> 1817640
A3: 2 | B3: INVERTER DC-AC | C3: Inverter S6-EH3P10K2 - NV-YD-L, Hybrid 3 pha áp thấp, 2 MPPT/ 3 String cho hiệu suất cao 97.6% (Tiêu chuẩn EU 97%) Top 3 thế giới về thương hiệu Inverter Đã bao gồm Metter và CT chống phát ngược lưới | D3: Solis | E3: Bộ | F3: 1 | G3: 56500000 | H3: =F3*G3 -> 56500000 | I3: 5 Năm | K3: =45400000/1.1 -> 41272727 | L3: =F3*K3 -> 41272727 | M3: 0.15 | N3: =K3/(1-M3) -> 48556150 | O3: =N3*F3 -> 48556150 | P3: =N3*1.1 -> 53411765
A4: 3 | B4: PIN LƯU TRỮ | C4: Pin Lithium EASYWAY 51,2V-280Ah. Lưu trữ 14.3kWh Cell Pin từ hãng GreatPower - Top 10 thế giới về thương hiệu Cell Pin Bản cao cấp màu trắng - có bánh xe Cấp bảo vệ: IP54 chống nước chống bụi cao | D4: EASYWAY | E4: Bộ | F4: 1 | G4: 60000000 | H4: =F4*G4 -> 60000000 | I4: 5 Năm | K4: =47470000/1.1 -> 43154545 | L4: =F4*K4 -> 43154545 | M4: 0.15 | N4: =K4/(1-M4) -> 50770053 | O4: =N4*F4 -> 50770053 | P4: =N4*1.1 -> 55847059
C5: Dây từ 35, nối Pin Lithium lên Inverter đã bấm sẵn đầu cốt | D5: SLM | E5: Bộ | F5: 1 | G5: 800000 | H5: =F5*G5 -> 800000 | I5: 5 Năm | K5: =300000/1.1 -> 272727.27 | L5: =F5*K5 -> 272727.27 | M5: 0.1 | N5: =K5/(1-M5) -> 303030.3 | O5: =N5*F5 -> 303030.3 | P5: =N5*1.1 -> 333333.33
C6: Dây mạng tín hiệu giao tiếp Inverter - Pin | D6: Việt Nam | E6: Bộ | F6: 1 | G6: 100000 | H6: =F6*G6 -> 100000 | I6: 5 Năm | K6: 0 | L6: =F6*K6 -> 0 | M6: 0.1 | N6: =K6/(1-M6) -> 0 | O6: =N6*F6 -> 0 | P6: =N6*1.1 -> 0
A7: 4 | B7: HỆ KHUNG GIÁ ĐỠ NHÔM CAO CẤP | C7: Kẹp biên PIN năng lượng mặt trời | D7: Việt Nam | E7: Cái | F7: 24 | G7: 11000 | H7: =F7*G7 -> 264000 | I7: 5 Năm | J7: 6-6-5-5-5 | K7: 8800 | L7: =F7*K7 -> 211200 | M7: 0.1 | N7: =K7/(1-M7) -> 9777.7778 | O7: =N7*F7 -> 234666.67 | P7: =N7*1.1 -> 10755.556
C8: Kẹp giữa PIN năng lượng mặt trời | D8: Việt Nam | E8: Cái | F8: 48 | G8: 11000 | H8: =F8*G8 -> 528000 | I8: 5 Năm | K8: 8800 | L8: =F8*K8 -> 422400 | M8: 0.1 | N8: =K8/(1-M8) -> 9777.7778 | O8: =N8*F8 -> 469333.33 | P8: =N8*1.1 -> 10755.556
C9: Thanh full rail nhôm cao cấp 4,2m | D9: Việt Nam | E9: Cái | F9: 16 | G9: 360000 | H9: =F9*G9 -> 5760000 | I9: 5 Năm | J9: =27*2*1.2/4.2 -> 15.428571 | K9: 294000 | L9: =F9*K9 -> 4704000 | M9: 0.1 | N9: =K9/(1-M9) -> 326666.67 | O9: =N9*F9 -> 5226666.7 | P9: =N9*1.1 -> 359333.33
C10: Thanh nối nhôm cao cấp | D10: Việt Nam | E10: Cái | F10: 16 | G10: 20000 | H10: =F10*G10 -> 320000 | I10: 5 Năm | K10: 12800 | L10: =F10*K10 -> 204800 | M10: 0.1 | N10: =K10/(1-M10) -> 14222.222 | O10: =N10*F10 -> 227555.56 | P10: =N10*1.1 -> 15644.444
C11: Chân L- nhôm cao cấp | D11: Việt Nam | E11: Cái | F11: =F9*6+4 -> 100 | G11: 20000 | H11: =F11*G11 -> 2000000 | I11: 5 Năm | K11: 16000 | L11: =F11*K11 -> 1600000 | M11: 0.1 | N11: =K11/(1-M11) -> 17777.778 | O11: =N11*F11 -> 1777777.8 | P11: =N11*1.1 -> 19555.556
C12: Kẹp tiếp địa | D12: Việt Nam | E12: Cái | F12: 8 | G12: 20000 | H12: =F12*G12 -> 160000 | I12: 5 Năm | K12: 12600 | L12: =F12*K12 -> 100800 | M12: 0.1 | N12: =K12/(1-M12) -> 14000 | O12: =N12*F12 -> 112000 | P12: =N12*1.1 -> 15400
C13: Lá tiếp địa | D13: Việt Nam | E13: Cái | F13: =F8 -> 48 | G13: 2000 | H13: =F13*G13 -> 96000 | I13: 5 Năm | K13: 1500 | L13: =F13*K13 -> 72000 | M13: 0.1 | N13: =K13/(1-M13) -> 1666.6667 | O13: =N13*F13 -> 80000 | P13: =N13*1.1 -> 1833.3333
A14: 5 | B14: HỆ DÂY ĐIỆN DC-AC | C14: Dây điện DC 4.0 màu đen Cáp điện chuyên dụng DC Solar 0.4 1500V | D14: PN Tech/ Leader | E14: Mét | F14: 100 | G14: 18000 | H14: =F14*G14 -> 1800000 | I14: 5 Năm | K14: 12000 | L14: =F14*K14 -> 1200000 | M14: 0.1 | N14: =K14/(1-M14) -> 13333.333 | O14: =N14*F14 -> 1333333.3 | P14: =N14*1.1 -> 14666.667
C15: Dây điện DC 4.0 màu đỏ Cáp điện chuyên dụng DC Solar 0.4 1500V | D15: PN Tech/ Leader | E15: Mét | F15: 100 | G15: 18000 | H15: =F15*G15 -> 1800000 | I15: 5 Năm | K15: 12000 | L15: =F15*K15 -> 1200000 | M15: 0.1 | N15: =K15/(1-M15) -> 13333.333 | O15: =N15*F15 -> 1333333.3 | P15: =N15*1.1 -> 14666.667
C16: Dây điện AC 3 pha 4 lõi đồng cao cấp CVV 4x10 mm | D16: Cadisun/Trần Phú Tương đương | E16: Mét | F16: 20 | G16: 150000 | H16: =F16*G16 -> 3000000 | I16: 5 Năm | K16: =135000/1.1+100000/20 -> 127727.27 | L16: =F16*K16 -> 2554545.5 | M16: 0.1 | N16: =K16/(1-M16) -> 141919.19 | O16: =N16*F16 -> 2838383.8 | P16: =N16*1.1 -> 156111.11
C17: Dây mạng tín hiệu đo tải tiêu thụ. Từ CT+Metter đến Inverter. Chống phát ngược lên lưới | D17: Việt Nam | E17: Bộ | F17: 1 | G17: 300000 | H17: =F17*G17 -> 300000 | I17: 5 Năm | K17: 0 | L17: =F17*K17 -> 0 | M17: 0.1 | N17: =K17/(1-M17) -> 0 | O17: =N17*F17 -> 0 | P17: =N17*1.1 -> 0
C18: Jack MC4 chuyên dụng NLMT 1500V | D18: PN Tech/ Leader | E18: Bộ | F18: 12 | G18: 30000 | H18: =F18*G18 -> 360000 | I18: 5 Năm | K18: 20000 | L18: =F18*K18 -> 240000 | M18: 0.1 | N18: =K18/(1-M18) -> 22222.222 | O18: =N18*F18 -> 266666.67 | P18: =N18*1.1 -> 24444.444
A19: 6 | B19: TỦ ĐIỆN NLMT | C19: Tủ điện hệ NLMT Hybrid 20kW 3 pha - 3 strings đi theo Inverter đầy đủ ATS của hệ: + Vỏ tủ sắt chuyên dụng - Sơn tĩnh điện. Kích thước 40x60x20cm + ATS 4P-100A: Thương hiệu Aisikai Nhật Bản + At AC 2P 63A; At AC 2P 32A: LS Hàn Quốc + At DC-1000V 3 strings: Vaneims + Chống sét AC- SPC lưới lan truyền: Suntree | D19: SLM | E19: Bộ | F19: 1 | G19: 8500000 | H19: =F19*G19 -> 8500000 | I19: 2 Năm | K19: =5380000/1.1+1500000 -> 6390909.1 | L19: =F19*K19 -> 6390909.1 | M19: 0.1 | N19: =K19/(1-M19) -> 7101010.1 | O19: =N19*F19 -> 7101010.1 | P19: =N19*1.1 -> 7811111.1
A20: 7 | B20: HỆ TIẾP ĐỊA | C20: Cáp tiếp địa PVC/Cu loại 1x4mm2 | D20: Cadivi/Nival | E20: Mét | F20: 60 | G20: 15000 | H20: =F20*G20 -> 900000 | I20: 2 Năm | K20: 12000 | L20: =F20*K20 -> 720000 | M20: 0.1 | N20: =K20/(1-M20) -> 13333.333 | O20: =N20*F20 -> 800000 | P20: =N20*1.1 -> 14666.667
C21: Cọc đồng Tiếp Địa 1 mét | D21: Việt Nam | E21: Cái | F21: 2 | G21: 250000 | H21: =F21*G21 -> 500000 | I21: 2 Năm | K21: 200000 | L21: =F21*K21 -> 400000 | M21: 0.1 | N21: =K21/(1-M21) -> 222222.22 | O21: =N21*F21 -> 444444.44 | P21: =N21*1.1 -> 244444.44
C22: Ống nhựa HDPE đường kính 32mm (cuộn 25m) | D22: Việt Nam | E22: Mét | F22: 60 | G22: 15000 | H22: =F22*G22 -> 900000 | I22: 2 Năm | K22: 12000 | L22: =F22*K22 -> 720000 | M22: 0.1 | N22: =K22/(1-M22) -> 13333.333 | O22: =N22*F22 -> 800000 | P22: =N22*1.1 -> 14666.667
A23: 8 | B23: NHÂN CÔNG LẮP ĐẶT | C23: Phụ kiện lắp đặt trọn gói (Bulong, ốc vít, Kẹp dây điện, băng keo điện, vật tư chống thấm thi công,…) | D23: SLM | E23: Bộ | F23: 1 | G23: 3000000 | H23: =F23*G23 -> 3000000 | K23: 2000000 | L23: =F23*K23 -> 2000000 | M23: 0.1 | N23: =K23/(1-M23) -> 2222222.2 | O23: =N23*F23 -> 2222222.2 | P23: =N23*1.1 -> 2444444.4
C24: Nhân công lắp đặt + Vận chuyển + Kiểm định vận hành | D24: SLM | E24: Bộ | F24: 1 | G24: 14900000 | H24: =F24*G24 -> 14900000 | K24: =1000000*16.74+2000000 -> 18740000 | L24: =F24*K24 -> 18740000 | M24: 0.1 | N24: =K24/(1-M24) -> 20822222 | O24: =N24*F24 -> 20822222 | P24: =N24*1.1 -> 22904444
A25: TỔNG CỘNG GIÁ TRỊ TRỌN GÓI VẬT TƯ THIẾT BỊ - VẬN CHUYỂN - LẮP ĐẶT - BẢO HÀNH | H25: =SUM(H2:H24) -> 219188000 | K25: Total (Excluding VAT) | L25: =SUM(L2:L24) -> 1.6410323e+08 | O25: =SUM(O2:O24) -> 1.9033365e+08
K26: Total (Including VAT) | L26: =L25*1.1 -> 180513558 | O26: =O25*1.1 -> 2.0936701e+08

Sheet HY3P_11.16kWBAT10HV
A1: No. | B1: Category | C1: Specification | D1: Brand Name | E1: Unit | F1: Quatity | G1: Unit Price (Including VAT) | H1: Total Price (Including VAT) | I1: Warranty | K1: COST (excluding VAT) | L1: TOTAL COST (excluding VAT) | M1: Gross Margin for Small EPC | N1: Price (excluding VAT) | O1: Total Price (excluding VAT) | P1: Unit Price - checked (Including VAT)
A2: 1 | B2: TẤM PIN PV | C2: Tấm Pin mặt trời Trina Vertex TSM-NEG19RC.20 - Công suất 620Wp All New Công nghệ mới nhất: N-Type i-TopCon Top 1 thế giới về hiệu suất và thương hiệu Tấm pin 2 mặt kính. Hiệu suất 30 năm đạt trên 87.4% | D2: TrinaSolar | E2: Tấm | F2: 18 | G2: 2100000 | H2: =F2*G2 -> 37800000 | I2: 12 Năm | J2: =18*620 -> 11160 | K2: =54*25500*(1+2%) -> 1404540 | L2: =F2*K2 -> 25281720 | M2: 0.15 | N2: =K2/(1-M2) -> 1652400 | O2: =N2*F2 -> 29743200 | P2: =N2*1.1 -> 1817640
A3: 2 | B3: INVERTER DC-AC | C3: Inverter Solis-10K Hybrid 3 pha áp cao, 4 MPPTx4 Strings cho hiệu suất cao. MAX DC 20kW Hiệu suất: 97.9% (Tiêu chuẩn EU 97.5%) IP 65 chống nước chống bụi Giảm hao phí điện năng tối đa | D3: Solis | E3: Bộ | F3: 1 | G3: 41600000 | H3: =F3*G3 -> 41600000 | I3: 5 Năm | K3: =34240000/1.1 -> 31127273 | L3: =F3*K3 -> 31127273 | M3: 0.15 | N3: =K3/(1-M3) -> 36620321 | O3: =N3*F3 -> 36620321 | P3: =N3*1.1 -> 40282353
A4: 3 | B4: PIN LƯU TRỮ | C4: Pin Lithium áp cao EasyWay 50V-100Ah-5kWh Thiết kế dạng xếp chồng không dây tinh tế sang trọng Dung lượng lưu trữ: 10kWh Nâng cấp: Tối đa 5 Pack Pin lưu trữ 25kWh điện | D4: EasyWay | E4: Bộ | F4: 2 | G4: 25000000 | H4: =F4*G4 -> 50000000 | I4: 5 Năm | K4: =20324000/1.1 -> 18476364 | L4: =F4*K4 -> 36952727 | M4: 0.15 | N4: =K4/(1-M4) -> 21736898 | O4: =N4*F4 -> 43473797 | P4: =N4*1.1 -> 23910588
C5: Bộ điều khiển Pin áp cao | D5: EasyWay | E5: Bộ | F5: 1 | G5: 19850000 | H5: =F5*G5 -> 19850000 | I5: 5 Năm | K5: =16345000/1.1 -> 14859091 | L5: =F5*K5 -> 14859091 | M5: 0.15 | N5: =K5/(1-M5) -> 17481283 | O5: =N5*F5 -> 17481283 | P5: =N5*1.1 -> 19229412
C6: Đế đỡ Pin cao đồng bộ hệ | D6: EasyWay | E6: Bộ | F6: 1 | G6: 1950000 | H6: =F6*G6 -> 1950000 | I6: 5 Năm | K6: =1736000/1.1 -> 1578181.8 | L6: =F6*K6 -> 1578181.8 | M6: 0.15 | N6: =K6/(1-M6) -> 1856684.5 | O6: =N6*F6 -> 1856684.5 | P6: =N6*1.1 -> 2042352.9
C7: Dây từ nối Pin Lithium lên Inverter đã bấm sẵn đầu cốt | D7: SLM | E7: Bộ | F7: 1 | G7: 800000 | H7: =F7*G7 -> 800000 | I7: 5 Năm | K7: 0 | L7: =F7*K7 -> 0 | M7: 0.15 | N7: =K7/(1-M7) -> 0 | O7: =N7*F7 -> 0 | P7: =N7*1.1 -> 0
C8: Dây mạng tín hiệu giao tiếp Inverter - Pin | D8: Việt Nam | E8: Cái | F8: 1 | G8: 100000 | H8: =F8*G8 -> 100000 | I8: 5 Năm | K8: 0 | L8: =F8*K8 -> 0 | M8: 0.15 | N8: =K8/(1-M8) -> 0 | O8: =N8*F8 -> 0 | P8: =N8*1.1 -> 0
A9: 4 | B9: HỆ KHUNG GIÁ ĐỠ NHÔM CAO CẤP | C9: Kẹp biên PIN năng lượng mặt trời | D9: Việt Nam | E9: Cái | F9: 20 | G9: 11000 | H9: =F9*G9 -> 220000 | I9: 5 Năm | J9: 5-5-4-4 | K9: 8800 | L9: =F9*K9 -> 176000 | M9: 0.1 | N9: =K9/(1-M9) -> 9777.7778 | O9: =N9*F9 -> 195555.56 | P9: =N9*1.1 -> 10755.556
C10: Kẹp giữa PIN năng lượng mặt trời | D10: Việt Nam | E10: Cái | F10: 32 | G10: 11000 | H10: =F10*G10 -> 352000 | I10: 5 Năm | K10: 8800 | L10: =F10*K10 -> 281600 | M10: 0.1 | N10: =K10/(1-M10) -> 9777.7778 | O10: =N10*F10 -> 312888.89 | P10: =N10*1.1 -> 10755.556
C11: Thanh full rail nhôm cao cấp 4,2m | D11: Việt Nam | E11: Cái | F11: 11 | G11: 360000 | H11: =F11*G11 -> 3960000 | I11: 5 Năm | J11: =18*2*1.2/4.2 -> 10.285714 | K11: 294000 | L11: =F11*K11 -> 3234000 | M11: 0.1 | N11: =K11/(1-M11) -> 326666.67 | O11: =N11*F11 -> 3593333.3 | P11: =N11*1.1 -> 359333.33
C12: Thanh nối nhôm cao cấp | D12: Việt Nam | E12: Cái | F12: 11 | G12: 20000 | H12: =F12*G12 -> 220000 | I12: 5 Năm | K12: 12800 | L12: =F12*K12 -> 140800 | M12: 0.1 | N12: =K12/(1-M12) -> 14222.222 | O12: =N12*F12 -> 156444.44 | P12: =N12*1.1 -> 15644.444
C13: Chân L- nhôm cao cấp | D13: Việt Nam | E13: Cái | F13: 66 | G13: 20000 | H13: =F13*G13 -> 1320000 | I13: 5 Năm | K13: 16000 | L13: =F13*K13 -> 1056000 | M13: 0.1 | N13: =K13/(1-M13) -> 17777.778 | O13: =N13*F13 -> 1173333.3 | P13: =N13*1.1 -> 19555.556
C14: Kẹp tiếp địa | D14: Việt Nam | E14: Cái | F14: 6 | G14: 20000 | H14: =F14*G14 -> 120000 | I14: 5 Năm | K14: 12600 | L14: =F14*K14 -> 75600 | M14: 0.1 | N14: =K14/(1-M14) -> 14000 | O14: =N14*F14 -> 84000 | P14: =N14*1.1 -> 15400
C15: Lá tiếp địa | D15: Việt Nam | E15: Cái | F15: =F10 -> 32 | G15: 2000 | H15: =F15*G15 -> 64000 | I15: 5 Năm | K15: 1500 | L15: =F15*K15 -> 48000 | M15: 0.1 | N15: =K15/(1-M15) -> 1666.6667 | O15: =N15*F15 -> 53333.333 | P15: =N15*1.1 -> 1833.3333
A16: 5 | B16: HỆ DÂY ĐIỆN DC-AC | C16: Dây điện DC 4.0 màu đen Cáp điện chuyên dụng DC Solar 0.4 1500V | D16: PN Tech/ Leader | E16: Mét | F16: 100 | G16: 18000 | H16: =F16*G16 -> 1800000 | I16: 5 Năm | K16: 12000 | L16: =F16*K16 -> 1200000 | M16: 0.1 | N16: =K16/(1-M16) -> 13333.333 | O16: =N16*F16 -> 1333333.3 | P16: =N16*1.1 -> 14666.667
C17: Dây điện DC 4.0 màu đỏ Cáp điện chuyên dụng DC Solar 0.4 1500V | D17: PN Tech/ Leader | E17: Mét | F17: 100 | G17: 18000 | H17: =F17*G17 -> 1800000 | I17: 5 Năm | K17: 12000 | L17: =F17*K17 -> 1200000 | M17: 0.1 | N17: =K17/(1-M17) -> 13333.333 | O17: =N17*F17 -> 1333333.3 | P17: =N17*1.1 -> 14666.667
C18: Dây điện AC 3 pha 4 lõi đồng cao cấp CVV 4x10 mm | D18: Cadisun/Trần Phú Tương đương | E18: Mét | F18: 20 | G18: 150000 | H18: =F18*G18 -> 3000000 | I18: 5 Năm | K18: =135000/1.1+100000/20 -> 127727.27 | L18: =F18*K18 -> 2554545.5 | M18: 0.1 | N18: =K18/(1-M18) -> 141919.19 | O18: =N18*F18 -> 2838383.8 | P18: =N18*1.1 -> 156111.11
C19: Dây mạng tín hiệu đo tải tiêu thụ. Từ CT+Metter đến Inverter. Chống phát ngược lên lưới | D19: Việt Nam | E19: Bộ | F19: 1 | G19: 300000 | H19: =F19*G19 -> 300000 | I19: 5 Năm | K19: 0 | L19: =F19*K19 -> 0 | M19: 0.1 | N19: =K19/(1-M19) -> 0 | O19: =N19*F19 -> 0 | P19: =N19*1.1 -> 0
C20: Jack MC4 chuyên dụng NLMT 1500V | D20: PN Tech/ Leader | E20: Bộ | F20: 10 | G20: 30000 | H20: =F20*G20 -> 300000 | I20: 5 Năm | K20: 20000 | L20: =F20*K20 -> 200000 | M20: 0.1 | N20: =K20/(1-M20) -> 22222.222 | O20: =N20*F20 -> 222222.22 | P20: =N20*1.1 -> 24444.444
A21: 6 | B21: TỦ ĐIỆN NLMT | C21: Tủ điện hệ NLMT Hybrid 15kW 3 pha - 3 strings đi theo Inverter đầy đủ ATS của hệ: + Vỏ tủ sắt chuyên dụng - Sơn tĩnh điện. Kích thước 40x60x20cm + ATS 4P-100A: Thương hiệu Aisikai Nhật Bản + At AC 2P 63A; At AC 2P 32A: LS Hàn Quốc + At DC-1000V 3 strings: Vaneims + Chống sét AC- SPC lưới lan truyền: Suntree | D21: SLM | E21: Bộ | F21: 1 | G21: 8500000 | H21: =F21*G21 -> 8500000 | I21: 2 Năm | K21: =5380000/1.1+1500000 -> 6390909.1 | L21: =F21*K21 -> 6390909.1 | M21: 0.1 | N21: =K21/(1-M21) -> 7101010.1 | O21: =N21*F21 -> 7101010.1 | P21: =N21*1.1 -> 7811111.1
A22: 7 | B22: HỆ TIẾP ĐỊA | C22: Cáp tiếp địa PVC/Cu loại 1x4mm2 | D22: Cadivi/Nival | E22: Mét | F22: 60 | G22: 15000 | H22: =F22*G22 -> 900000 | I22: 2 Năm | K22: 12000 | L22: =F22*K22 -> 720000 | M22: 0.1 | N22: =K22/(1-M22) -> 13333.333 | O22: =N22*F22 -> 800000 | P22: =N22*1.1 -> 14666.667
C23: Cọc đồng Tiếp Địa 1 mét | D23: Việt Nam | E23: Cái | F23: 2 | G23: 250000 | H23: =F23*G23 -> 500000 | I23: 2 Năm | K23: 200000 | L23: =F23*K23 -> 400000 | M23: 0.1 | N23: =K23/(1-M23) -> 222222.22 | O23: =N23*F23 -> 444444.44 | P23: =N23*1.1 -> 244444.44
C24: Ống nhựa HDPE đường kính 32mm (cuộn 25m) | D24: Việt Nam | E24: Mét | F24: 60 | G24: 15000 | H24: =F24*G24 -> 900000 | I24: 2 Năm | K24: 12000 | L24: =F24*K24 -> 720000 | M24: 0.1 | N24: =K24/(1-M24) -> 13333.333 | O24: =N24*F24 -> 800000 | P24: =N24*1.1 -> 14666.667
A25: 8 | B25: NHÂN CÔNG LẮP ĐẶT | C25: Phụ kiện lắp đặt trọn gói (Bulong, ốc vít, Kẹp dây điện, băng keo điện, vật tư chống thấm thi công,…) | D25: SLM | E25: Bộ | F25: 1 | G25: 2000000 | H25: =F25*G25 -> 2000000 | K25: 1000000 | L25: =F25*K25 -> 1000000 | M25: 0.1 | N25: =K25/(1-M25) -> 1111111.1 | O25: =N25*F25 -> 1111111.1 | P25: =N25*1.1 -> 1222222.2
C26: Nhân công lắp đặt + Vận chuyển + Kiểm định vận hành | D26: SLM | E26: Bộ | F26: 1 | G26: 9600000 | H26: =F26*G26 -> 9600000 | K26: =1000000*11.16+2000000 -> 13160000 | L26: =F26*K26 -> 13160000 | M26: 0.1 | N26: =K26/(1-M26) -> 14622222 | O26: =N26*F26 -> 14622222 | P26: =N26*1.1 -> 16084444
A27: TỔNG CỘNG GIÁ TRỊ TRỌN GÓI VẬT TƯ THIẾT BỊ - VẬN CHUYỂN - LẮP ĐẶT - BẢO HÀNH | H27: =SUM(H2:H26) -> 187956000 | K27: Total (Excluding VAT) | L27: =SUM(L2:L26) -> 1.4235645e+08 | O27: =SUM(O2:O26) -> 1.6535024e+08
K28: Total (Including VAT) | L28: =L27*1.1 -> 156592092 | O28: =O27*1.1 -> 1.8188526e+08

Sheet HY3P_16.74kWBAT15HV
A1: No. | B1: Category | C1: Specification | D1: Brand Name | E1: Unit | F1: Quatity | G1: Unit Price (Including VAT) | H1: Total Price (Including VAT) | I1: Warranty | K1: COST (excluding VAT) | L1: TOTAL COST (excluding VAT) | M1: Gross Margin for Small EPC | N1: Price (excluding VAT) | O1: Total Price (excluding VAT) | P1: Unit Price - checked (Including VAT)
A2: 1 | B2: TẤM PIN PV | C2: Tấm Pin mặt trời Trina Vertex TSM-NEG19RC.20 - Công suất 620Wp All New Công nghệ mới nhất: N-Type i-TopCon Top 1 thế giới về hiệu suất và thương hiệu Tấm pin 2 mặt kính. Hiệu suất 30 năm đạt trên 87.4% | D2: TrinaSolar | E2: Tấm | F2: 27 | G2: 2100000 | H2: =F2*G2 -> 56700000 | I2: 12 Năm | J2: =27*620 -> 16740 | K2: =54*25500*(1+2%) -> 1404540 | L2: =F2*K2 -> 37922580 | M2: 0.15 | N2: =K2/(1-M2) -> 1652400 | O2: =N2*F2 -> 44614800 | P2: =N2*1.1 -> 1817640
A3: 2 | B3: INVERTER DC-AC | C3: Inverter S6-EH3P10K2 - NV-YD-L, Hybrid 3 pha áp thấp, 2 MPPT/ 3 String cho hiệu suất cao 97.6% (Tiêu chuẩn EU 97%) Top 3 thế giới về thương hiệu Inverter Đã bao gồm Metter và CT chống phát ngược lưới | D3: Solis | E3: Bộ | F3: 1 | G3: 56500000 | H3: =F3*G3 -> 56500000 | I3: 5 Năm | K3: =45400000/1.1 -> 41272727 | L3: =F3*K3 -> 41272727 | M3: 0.15 | N3: =K3/(1-M3) -> 48556150 | O3: =N3*F3 -> 48556150 | P3: =N3*1.1 -> 53411765
A4: 3 | B4: PIN LƯU TRỮ | C4: Pin Lithium áp cao EasyWay 50V-100Ah-5kWh Thiết kế dạng xếp chồng không dây tinh tế sang trọng Dung lượng lưu trữ: 10kWh Nâng cấp: Tối đa 5 Pack Pin lưu trữ 25kWh điện | D4: EasyWay | E4: Bộ | F4: 3 | G4: 25000000 | H4: =F4*G4 -> 75000000 | I4: 5 Năm | K4: =20324000/1.1 -> 18476364 | L4: =F4*K4 -> 55429091 | M4: 0.15 | N4: =K4/(1-M4) -> 21736898 | O4: =N4*F4 -> 65210695 | P4: =N4*1.1 -> 23910588
C5: Bộ điều khiển Pin áp cao | D5: EasyWay | E5: Bộ | F5: 1 | G5: 19850000 | H5: =F5*G5 -> 19850000 | I5: 5 Năm | K5: =16345000/1.1 -> 14859091 | L5: =F5*K5 -> 14859091 | M5: 0.1 | N5: =K5/(1-M5) -> 16510101 | O5: =N5*F5 -> 16510101 | P5: =N5*1.1 -> 18161111
C6: Đế đỡ Pin cao đồng bộ hệ | D6: EasyWay | E6: Bộ | F6: 1 | G6: 1950000 | H6: =F6*G6 -> 1950000 | I6: 5 Năm | K6: =1736000/1.1 -> 1578181.8 | L6: =F6*K6 -> 1578181.8 | M6: 0.1 | N6: =K6/(1-M6) -> 1753535.4 | O6: =N6*F6 -> 1753535.4 | P6: =N6*1.1 -> 1928888.9
C7: Dây từ nối Pin Lithium lên Inverter đã bấm sẵn đầu cốt | D7: SLM | E7: Bộ | F7: 1 | G7: 800000 | H7: =F7*G7 -> 800000 | I7: 5 Năm | K7: 0 | L7: =F7*K7 -> 0 | M7: 0.1 | N7: =K7/(1-M7) -> 0 | O7: =N7*F7 -> 0 | P7: =N7*1.1 -> 0
C8: Dây mạng tín hiệu giao tiếp Inverter - Pin | D8: Việt Nam | E8: Cái | F8: 1 | G8: 100000 | H8: =F8*G8 -> 100000 | I8: 5 Năm | K8: 0 | L8: =F8*K8 -> 0 | M8: 0.1 | N8: =K8/(1-M8) -> 0 | O8: =N8*F8 -> 0 | P8: =N8*1.1 -> 0
A9: 4 | B9: HỆ KHUNG GIÁ ĐỠ NHÔM CAO CẤP | C9: Kẹp biên PIN năng lượng mặt trời | D9: Việt Nam | E9: Cái | F9: 24 | G9: 11000 | H9: =F9*G9 -> 264000 | I9: 5 Năm | J9: 6-6-5-5-5 | K9: 8800 | L9: =F9*K9 -> 211200 | M9: 0.1 | N9: =K9/(1-M9) -> 9777.7778 | O9: =N9*F9 -> 234666.67 | P9: =N9*1.1 -> 10755.556
C10: Kẹp giữa PIN năng lượng mặt trời | D10: Việt Nam | E10: Cái | F10: 48 | G10: 11000 | H10: =F10*G10 -> 528000 | I10: 5 Năm | K10: 8800 | L10: =F10*K10 -> 422400 | M10: 0.1 | N10: =K10/(1-M10) -> 9777.7778 | O10: =N10*F10 -> 469333.33 | P10: =N10*1.1 -> 10755.556
C11: Thanh full rail nhôm cao cấp 4,2m | D11: Việt Nam | E11: Cái | F11: 16 | G11: 360000 | H11: =F11*G11 -> 5760000 | I11: 5 Năm | J11: =27*2*1.2/4.2 -> 15.428571 | K11: 294000 | L11: =F11*K11 -> 4704000 | M11: 0.1 | N11: =K11/(1-M11) -> 326666.67 | O11: =N11*F11 -> 5226666.7 | P11: =N11*1.1 -> 359333.33
C12: Thanh nối nhôm cao cấp | D12: Việt Nam | E12: Cái | F12: 16 | G12: 20000 | H12: =F12*G12 -> 320000 | I12: 5 Năm | K12: 12800 | L12: =F12*K12 -> 204800 | M12: 0.1 | N12: =K12/(1-M12) -> 14222.222 | O12: =N12*F12 -> 227555.56 | P12: =N12*1.1 -> 15644.444
C13: Chân L- nhôm cao cấp | D13: Việt Nam | E13: Cái | F13: =F11*6+4 -> 100 | G13: 20000 | H13: =F13*G13 -> 2000000 | I13: 5 Năm | K13: 16000 | L13: =F13*K13 -> 1600000 | M13: 0.1 | N13: =K13/(1-M13) -> 17777.778 | O13: =N13*F13 -> 1777777.8 | P13: =N13*1.1 -> 19555.556
C14: Kẹp tiếp địa | D14: Việt Nam | E14: Cái | F14: 8 | G14: 20000 | H14: =F14*G14 -> 160000 | I14: 5 Năm | K14: 12600 | L14: =F14*K14 -> 100800 | M14: 0.1 | N14: =K14/(1-M14) -> 14000 | O14: =N14*F14 -> 112000 | P14: =N14*1.1 -> 15400
C15: Lá tiếp địa | D15: Việt Nam | E15: Cái | F15: =F10 -> 48 | G15: 2000 | H15: =F15*G15 -> 96000 | I15: 5 Năm | K15: 1500 | L15: =F15*K15 -> 72000 | M15: 0.1 | N15: =K15/(1-M15) -> 1666.6667 | O15: =N15*F15 -> 80000 | P15: =N15*1.1 -> 1833.3333
A16: 5 | B16: HỆ DÂY ĐIỆN DC-AC | C16: Dây điện DC 4.0 màu đen Cáp điện chuyên dụng DC Solar 0.4 1500V | D16: PN Tech/ Leader | E16: Mét | F16: 100 | G16: 18000 | H16: =F16*G16 -> 1800000 | I16: 5 Năm | K16: 12000 | L16: =F16*K16 -> 1200000 | M16: 0.1 | N16: =K16/(1-M16) -> 13333.333 | O16: =N16*F16 -> 1333333.3 | P16: =N16*1.1 -> 14666.667
C17: Dây điện DC 4.0 màu đỏ Cáp điện chuyên dụng DC Solar 0.4 1500V | D17: PN Tech/ Leader | E17: Mét | F17: 100 | G17: 18000 | H17: =F17*G17 -> 1800000 | I17: 5 Năm | K17: 12000 | L17: =F17*K17 -> 1200000 | M17: 0.1 | N17: =K17/(1-M17) -> 13333.333 | O17: =N17*F17 -> 1333333.3 | P17: =N17*1.1 -> 14666.667
C18: Dây điện AC 3 pha 4 lõi đồng cao cấp CVV 4x10 mm | D18: Cadisun/Trần Phú Tương đương | E18: Mét | F18: 20 | G18: 150000 | H18: =F18*G18 -> 3000000 | I18: 5 Năm | K18: =135000/1.1+100000/20 -> 127727.27 | L18: =F18*K18 -> 2554545.5 | M18: 0.1 | N18: =K18/(1-M18) -> 141919.19 | O18: =N18*F18 -> 2838383.8 | P18: =N18*1.1 -> 156111.11
C19: Dây mạng tín hiệu đo tải tiêu thụ. Từ CT+Metter đến Inverter. Chống phát ngược lên lưới | D19: Việt Nam | E19: Bộ | F19: 1 | G19: 300000 | H19: =F19*G19 -> 300000 | I19: 5 Năm | K19: 0 | L19: =F19*K19 -> 0 | M19: 0.1 | N19: =K19/(1-M19) -> 0 | O19: =N19*F19 -> 0 | P19: =N19*1.1 -> 0
C20: Jack MC4 chuyên dụng NLMT 1500V | D20: PN Tech/ Leader | E20: Bộ | F20: 12 | G20: 30000 | H20: =F20*G20 -> 360000 | I20: 5 Năm | K20: 20000 | L20: =F20*K20 -> 240000 | M20: 0.1 | N20: =K20/(1-M20) -> 22222.222 | O20: =N20*F20 -> 266666.67 | P20: =N20*1.1 -> 24444.444
A21: 6 | B21: TỦ ĐIỆN NLMT | C21: Tủ điện hệ NLMT Hybrid 20kW 3 pha - 3 strings đi theo Inverter đầy đủ ATS của hệ: + Vỏ tủ sắt chuyên dụng - Sơn tĩnh điện. Kích thước 40x60x20cm + ATS 4P-100A: Thương hiệu Aisikai Nhật Bản + At AC 2P 63A; At AC 2P 32A: LS Hàn Quốc + At DC-1000V 3 strings: Vaneims + Chống sét AC- SPC lưới lan truyền: Suntree | D21: SLM | E21: Bộ | F21: 1 | G21: 8500000 | H21: =F21*G21 -> 8500000 | I21: 2 Năm | K21: =5380000/1.1+1500000 -> 6390909.1 | L21: =F21*K21 -> 6390909.1 | M21: 0.1 | N21: =K21/(1-M21) -> 7101010.1 | O21: =N21*F21 -> 7101010.1 | P21: =N21*1.1 -> 7811111.1
A22: 7 | B22: HỆ TIẾP ĐỊA | C22: Cáp tiếp địa PVC/Cu loại 1x4mm2 | D22: Cadivi/Nival | E22: Mét | F22: 60 | G22: 15000 | H22: =F22*G22 -> 900000 | I22: 2 Năm | K22: 12000 | L22: =F22*K22 -> 720000 | M22: 0.1 | N22: =K22/(1-M22) -> 13333.333 | O22: =N22*F22 -> 800000 | P22: =N22*1.1 -> 14666.667
C23: Cọc đồng Tiếp Địa 1 mét | D23: Việt Nam | E23: Cái | F23: 2 | G23: 250000 | H23: =F23*G23 -> 500000 | I23: 2 Năm | K23: 200000 | L23: =F23*K23 -> 400000 | M23: 0.1 | N23: =K23/(1-M23) -> 222222.22 | O23: =N23*F23 -> 444444.44 | P23: =N23*1.1 -> 244444.44
C24: Ống nhựa HDPE đường kính 32mm (cuộn 25m) | D24: Việt Nam | E24: Mét | F24: 60 | G24: 15000 | H24: =F24*G24 -> 900000 | I24: 2 Năm | K24: 12000 | L24: =F24*K24 -> 720000 | M24: 0.1 | N24: =K24/(1-M24) -> 13333.333 | O24: =N24*F24 -> 800000 | P24: =N24*1.1 -> 14666.667
A25: 8 | B25: NHÂN CÔNG LẮP ĐẶT | C25: Phụ kiện lắp đặt trọn gói (Bulong, ốc vít, Kẹp dây điện, băng keo điện, vật tư chống thấm thi công,…) | D25: SLM | E25: Bộ | F25: 1 | G25: 3000000 | H25: =F25*G25 -> 3000000 | K25: 2000000 | L25: =F25*K25 -> 2000000 | M25: 0.1 | N25: =K25/(1-M25) -> 2222222.2 | O25: =N25*F25 -> 2222222.2 | P25: =N25*1.1 -> 2444444.4
C26: Nhân công lắp đặt + Vận chuyển + Kiểm định vận hành | D26: SLM | E26: Bộ | F26: 1 | G26: 14900000 | H26: =F26*G26 -> 14900000 | K26: =1000000*16.74+2000000 -> 18740000 | L26: =F26*K26 -> 18740000 | M26: 0.1 | N26: =K26/(1-M26) -> 20822222 | O26: =N26*F26 -> 20822222 | P26: =N26*1.1 -> 22904444
A27: TỔNG CỘNG GIÁ TRỊ TRỌN GÓI VẬT TƯ THIẾT BỊ - VẬN CHUYỂN - LẮP ĐẶT - BẢO HÀNH | H27: =SUM(H2:H26) -> 255988000 | K27: Total (Excluding VAT) | L27: =SUM(L2:L26) -> 1.9254233e+08 | O27: =SUM(O2:O26) -> 2.227349e+08
K28: Total (Including VAT) | L28: =L27*1.1 -> 2.1179656e+08 | O28: =O27*1.1 -> 2.4500839e+08
